Workbook

Sheet Validar HU y tareas
B2: SIGRO · Sprint 1 · Historias de usuario y sus tareas (para validar)
B3: Cada integrante revisa las tareas de su área y marca «¿De acuerdo?». Si es «No», escribe qué cambiar. Lo validado pasa al tablero de GitHub.
B5: HU / ID | C5: Historia de usuario / tarea | D5: Fase / área | E5: Responsable | F5: Horas | G5: Estado | H5: Fecha límite | I5: Depende de | J5: ¿De acuerdo? | K5: Observación
B6: HU-01 · Crear proyecto 3 pts
B7: Como residente de obra, quiero crear el proyecto con su nombre y su plazo, para acotar todo el movimiento a ese periodo.
B8: T-001 | C8: Programar el endpoint para crear la obra, validando nombre y plazo obligatorios, fin ≥ inicio y estado inicial «en ejecución» | D8: Backend | E8: Adiel | F8: 2 | G8: Done | H8: 25/10 | K8: hecho en la API de Adiel (PR #1 fusionado a main), con pruebas
B9: T-002 | C9: Programar la pantalla web para crear la obra | D9: Web | E9: Fernando | F9: 2 | G9: Done | H9: 26/10 | K9: pantalla hecha con datos simulados; falta conectarla a la API real
B10: T-003 | C10: Conectar la pantalla «Crear la obra» con el endpoint real de la API | D10: Web | E10: Fernando | F10: 2 | G10: To Do | H10: 26/10 | I10: T-001, T-140
B11: T-004 | C11: Probar HU-01 en el ambiente de pruebas contra sus condiciones finales y aprobar su PR | D11: Pruebas | E11: Henry | F11: 1 | G11: To Do | H11: 27/10 | I11: T-001, T-002, T-003, T-139 | K11: alguien distinto del autor (T1, T5, T8)
B12: T-005 | C12: Aceptar HU-01 como Product Owner desde la interfaz y moverla a Done | D12: Aceptación | E12: Adiel | F12: 0.5 | G12: To Do | H12: 27/10 | I12: T-004 | K12: mueve la HU a Done
B13: HU-03 · Reportar la obra en semanas 3 pts
B14: Como residente de obra, quiero dividir el plazo de la obra en periodos semanales de control, para comparar lo consumido de un periodo con otro sin armar el corte a mano.
B15: T-006 | C15: Programar la generación automática de semanas al crear la obra y al ampliar el plazo, con sus pruebas | D15: Backend | E15: Adiel | F15: 2 | G15: To Do | H15: 25/10 | K15: confirmar si la API ya las genera
B16: T-007 | C16: Programar la tira de semanas en la web (cerrada, en curso, por venir) | D16: Web | E16: Fernando | F16: 2 | G16: Done | H16: 26/10 | K16: pantalla hecha con datos simulados; falta conectarla a la API real
B17: T-008 | C17: Conectar la tira de semanas con la API real | D17: Web | E17: Fernando | F17: 2 | G17: To Do | H17: 26/10 | I17: T-006, T-140
B18: T-009 | C18: Probar HU-03 en el ambiente de pruebas contra sus condiciones finales y aprobar su PR | D18: Pruebas | E18: Henry | F18: 1 | G18: To Do | H18: 27/10 | I18: T-006, T-007, T-008, T-139 | K18: alguien distinto del autor (T1, T5, T8)
B19: T-010 | C19: Aceptar HU-03 como Product Owner desde la interfaz y moverla a Done | D19: Aceptación | E19: Adiel | F19: 0.5 | G19: To Do | H19: 27/10 | I19: T-009 | K19: mueve la HU a Done
B20: HU-07 · Importar catálogo de insumos del S10 8 pts
B21: Como residente de obra, quiero importar el catálogo de insumos del S10, para evitar cargar a mano cientos de insumos.
B22: T-011 | C22: Programar el lector del PDF «Relación de insumos» del S10 en el microservicio | D22: Integraciones | E22: Fernando | F22: 4 | G22: Done | H22: 25/10 | K22: probado con el archivo real: 284 insumos, 0 fallidos, total exacto
B23: T-012 | C23: Programar el endpoint que aplica la importación: crear o actualizar insumos por código sin tocar saldos | D23: Backend | E23: Adiel | F23: 4 | G23: To Do | H23: 25/10
B24: T-013 | C24: Configurar la llamada de la API a Integraciones con el token de servicio en docker compose | D24: Backend | E24: Adiel | F24: 4 | G24: To Do | H24: 25/10 | K24: decisión B del 22/10
B25: T-014 | C25: Programar la pantalla web «Importar del S10» con el resumen de creados, actualizados y fallidos | D25: Web | E25: Fernando | F25: 4 | G25: Done | H25: 26/10 | K25: conectada al micro real
B26: T-015 | C26: Probar HU-07 en el ambiente de pruebas contra sus condiciones finales y aprobar su PR | D26: Pruebas | E26: Henry | F26: 1 | G26: To Do | H26: 27/10 | I26: T-011, T-012, T-013, T-014, T-139 | K26: alguien distinto del autor (T1, T5, T8)
B27: T-016 | C27: Aceptar HU-07 como Product Owner desde la interfaz y moverla a Done | D27: Aceptación | E27: Adiel | F27: 0.5 | G27: To Do | H27: 27/10 | I27: T-015 | K27: mueve la HU a Done
B28: HU-08 · Registrar insumos 5 pts
B29: Como almacenero, quiero registrar un insumo con información estandarizada, para identificarlo de la misma manera en todas las obras.
B30: T-017 | C30: Programar el endpoint del catálogo: generar código único, rechazar duplicados y marcar «por verificar» | D30: Backend | E30: Adiel | F30: 3 | G30: To Do | H30: 25/10
B31: T-018 | C31: Programar la pantalla web del catálogo para ver, dar de alta y editar insumos | D31: Web | E31: Fernando | F31: 3 | G31: Done | H31: 26/10 | K31: pantalla hecha con datos simulados; falta conectarla a la API real
B32: T-019 | C32: Conectar la pantalla del catálogo con la API real | D32: Web | E32: Fernando | F32: 3 | G32: To Do | H32: 26/10 | I32: T-017, T-140
B33: T-020 | C33: Probar HU-08 en el ambiente de pruebas contra sus condiciones finales y aprobar su PR | D33: Pruebas | E33: Henry | F33: 1 | G33: To Do | H33: 27/10 | I33: T-017, T-018, T-019, T-139 | K33: alguien distinto del autor (T1, T5, T8)
B34: T-021 | C34: Aceptar HU-08 como Product Owner desde la interfaz y moverla a Done | D34: Aceptación | E34: Adiel | F34: 0.5 | G34: To Do | H34: 27/10 | I34: T-020 | K34: mueve la HU a Done
B35: HU-12 · Loguear usuario 5 pts
B36: Como administrador, quiero entrar al sistema con mi usuario y contraseña, para que mis registros queden atribuidos a mí.
B37: T-022 | C37: Programar el login con Argon2id, sesión que caduca y se renueva, y bloqueo por intentos fallidos | D37: Backend | E37: Adiel | F37: 3 | G37: Done | H37: 25/10 | K37: hecho en la API de Adiel (PR #1 fusionado a main), con pruebas
B38: T-023 | C38: Programar la pantalla web de login y el manejo de la sesión | D38: Web | E38: Henry | F38: 3 | G38: To Do | H38: 26/10
B39: T-024 | C39: Programar el login en la app del almacenero | D39: Android | E39: Nicolás | F39: 3 | G39: To Do | H39: 26/10 | I39: T-141
B40: T-025 | C40: Probar HU-12 en el ambiente de pruebas contra sus condiciones finales y aprobar su PR | D40: Pruebas | E40: Henry | F40: 1 | G40: To Do | H40: 27/10 | I40: T-022, T-023, T-024, T-139 | K40: alguien distinto del autor (T1, T5, T8)
B41: T-026 | C41: Aceptar HU-12 como Product Owner desde la interfaz y moverla a Done | D41: Aceptación | E41: Adiel | F41: 0.5 | G41: To Do | H41: 27/10 | I41: T-025 | K41: mueve la HU a Done
B42: HU-13 · Asignar roles 5 pts
B43: Como administrador, quiero asignar a cada persona un usuario y un rol, para limitar lo que cada quien ve y registra.
B44: T-027 | C44: Programar los roles y verificar sus permisos en el servidor | D44: Backend | E44: Adiel | F44: 4 | G44: Done | H44: 25/10 | K44: hecho en la API de Adiel (PR #1 fusionado a main), con pruebas
B45: T-028 | C45: Programar la pantalla web para crear usuarios, asignar su rol y darlos de baja | D45: Web | E45: Henry | F45: 4 | G45: To Do | H45: 26/10
B46: T-029 | C46: Probar HU-13 en el ambiente de pruebas contra sus condiciones finales y aprobar su PR | D46: Pruebas | E46: Fernando | F46: 1 | G46: To Do | H46: 27/10 | I46: T-027, T-028, T-139 | K46: alguien distinto del autor (T1, T5, T8)
B47: T-030 | C47: Aceptar HU-13 como Product Owner desde la interfaz y moverla a Done | D47: Aceptación | E47: Adiel | F47: 0.5 | G47: To Do | H47: 27/10 | I47: T-029 | K47: mueve la HU a Done
B48: HU-14 · Asignar usuarios a obras 3 pts
B49: Como administrador, quiero asignar usuarios a los proyectos, para que cada quien opere solo en sus obras.
B50: T-031 | C50: Programar el endpoint para asignar usuarios a obras | D50: Backend | E50: Adiel | F50: 2 | G50: Done | H50: 25/10 | K50: hecho en la API de Adiel (PR #1 fusionado a main), con pruebas
B51: T-032 | C51: Programar la pantalla web para asignar usuarios a obras | D51: Web | E51: Henry | F51: 2 | G51: To Do | H51: 26/10
B52: T-033 | C52: Probar HU-14 en el ambiente de pruebas contra sus condiciones finales y aprobar su PR | D52: Pruebas | E52: Fernando | F52: 1 | G52: To Do | H52: 27/10 | I52: T-031, T-032, T-139 | K52: alguien distinto del autor (T1, T5, T8)
B53: T-034 | C53: Aceptar HU-14 como Product Owner desde la interfaz y moverla a Done | D53: Aceptación | E53: Adiel | F53: 0.5 | G53: To Do | H53: 27/10 | I53: T-033 | K53: mueve la HU a Done
B54: HU-15 · Autorizar celular de la obra 5 pts
B55: Como administrador, quiero autorizar el dispositivo que registra movimientos en cada obra, para impedir que un equipo ajeno opere en nombre de la obra.
B56: T-035 | C56: Programar el registro de dispositivos autorizados por obra (máximo dos) y el rechazo del no autorizado | D56: Backend | E56: Adiel | F56: 3 | G56: Done | H56: 25/10 | K56: hecho en la API de Adiel (PR #1 fusionado a main), con pruebas
B57: T-036 | C57: Programar en la app la generación del código del dispositivo en la primera instalación | D57: Android | E57: Nicolás | F57: 3 | G57: To Do | H57: 26/10 | I57: T-141
B58: T-037 | C58: Programar la pantalla web para autorizar o cambiar el celular de la obra | D58: Web | E58: Henry | F58: 3 | G58: To Do | H58: 26/10
B59: T-038 | C59: Probar HU-15 en el ambiente de pruebas contra sus condiciones finales y aprobar su PR | D59: Pruebas | E59: Henry | F59: 1 | G59: To Do | H59: 27/10 | I59: T-035, T-036, T-037, T-139 | K59: alguien distinto del autor (T1, T5, T8)
B60: T-039 | C60: Aceptar HU-15 como Product Owner desde la interfaz y moverla a Done | D60: Aceptación | E60: Adiel | F60: 0.5 | G60: To Do | H60: 27/10 | I60: T-038 | K60: mueve la HU a Done
B61: HU-16 · Importar precios unitarios 8 pts
B62: Como residente de obra, quiero importar el análisis de precios unitarios del S10, para conocer cuánto material exige cada partida.
B63: T-040 | C63: Programar el lector del PDF del APU (371 páginas), identificando la partida por código y descripción | D63: Integraciones | E63: Fernando | F63: 5 | G63: Doing | H63: 25/10 | K63: extracción ya probada: 6 902 filas, 1 217 partidas
B64: T-041 | C64: Crear la tabla partida–recurso y programar el endpoint que la guarda | D64: Backend | E64: Adiel | F64: 5 | G64: To Do | H64: 25/10
B65: T-042 | C65: Programar la pantalla web para importar el APU | D65: Web | E65: Fernando | F65: 5 | G65: To Do | H65: 26/10
B66: T-043 | C66: Probar HU-16 en el ambiente de pruebas contra sus condiciones finales y aprobar su PR | D66: Pruebas | E66: Henry | F66: 1 | G66: To Do | H66: 27/10 | I66: T-040, T-041, T-042, T-139 | K66: alguien distinto del autor (T1, T5, T8)
B67: T-044 | C67: Aceptar HU-16 como Product Owner desde la interfaz y moverla a Done | D67: Aceptación | E67: Adiel | F67: 0.5 | G67: To Do | H67: 27/10 | I67: T-043 | K67: mueve la HU a Done
B68: HU-17 · Convertir unidades (kg a varillas) 3 pts
B69: Como almacenero, quiero registrar el factor entre la unidad del S10 y la unidad de compra, para comparar en una misma unidad lo presupuestado, lo comprado y lo consumido.
B70: T-045 | C70: Programar el registro del factor de conversión con su fecha y su usuario | D70: Backend | E70: Adiel | F70: 2 | G70: To Do | H70: 25/10
B71: T-046 | C71: Programar el formulario web del factor de conversión (kg ↔ varillas) | D71: Web | E71: Fernando | F71: 2 | G71: To Do | H71: 26/10
B72: T-047 | C72: Probar HU-17 en el ambiente de pruebas contra sus condiciones finales y aprobar su PR | D72: Pruebas | E72: Henry | F72: 1 | G72: To Do | H72: 27/10 | I72: T-045, T-046, T-139 | K72: alguien distinto del autor (T1, T5, T8)
B73: T-048 | C73: Aceptar HU-17 como Product Owner desde la interfaz y moverla a Done | D73: Aceptación | E73: Adiel | F73: 0.5 | G73: To Do | H73: 27/10 | I73: T-047 | K73: mueve la HU a Done
B74: HU-19 · Importar requerimiento de la obra 5 pts
B75: Como residente de obra, quiero importar el requerimiento total de la obra desde el reporte de recursos del S10, para fijar el cien por ciento contra el que se controla todo.
B76: T-049 | C76: Adaptar el lector de la Relación de insumos para obtener el requerimiento total | D76: Integraciones | E76: Fernando | F76: 3 | G76: To Do | H76: 25/10 | K76: el lector ya trae cantidades y precios
B77: T-050 | C77: Programar el guardado del requerimiento total y de sus ajustes con motivo | D77: Backend | E77: Adiel | F77: 3 | G77: To Do | H77: 25/10
B78: T-051 | C78: Programar la pantalla web del requerimiento total | D78: Web | E78: Fernando | F78: 3 | G78: To Do | H78: 26/10
B79: T-052 | C79: Probar HU-19 en el ambiente de pruebas contra sus condiciones finales y aprobar su PR | D79: Pruebas | E79: Henry | F79: 1 | G79: To Do | H79: 27/10 | I79: T-049, T-050, T-051, T-139 | K79: alguien distinto del autor (T1, T5, T8)
B80: T-053 | C80: Aceptar HU-19 como Product Owner desde la interfaz y moverla a Done | D80: Aceptación | E80: Adiel | F80: 0.5 | G80: To Do | H80: 27/10 | I80: T-052 | K80: mueve la HU a Done
B81: HU-23 · Consultar cuánto se compró y consumió 5 pts
B82: Como residente de obra, quiero consultar qué porcentaje de cada insumo se compró y se consumió, para distinguir lo que ingresó de lo que se usó.
B83: T-054 | C83: Programar la consulta de avance: requerido, comprado, recibido y consumido por insumo | D83: Backend | E83: Adiel | F83: 3 | G83: To Do | H83: 25/10
B84: T-055 | C84: Programar la pantalla web de avance de compra y consumo | D84: Web | E84: Fernando | F84: 3 | G84: Done | H84: 26/10 | K84: pantalla hecha con datos simulados; falta conectarla a la API real
B85: T-056 | C85: Conectar la pantalla de avance con la API real | D85: Web | E85: Fernando | F85: 3 | G85: To Do | H85: 26/10 | I85: T-054, T-140
B86: T-057 | C86: Probar HU-23 en el ambiente de pruebas contra sus condiciones finales y aprobar su PR | D86: Pruebas | E86: Henry | F86: 1 | G86: To Do | H86: 27/10 | I86: T-054, T-055, T-056, T-139 | K86: alguien distinto del autor (T1, T5, T8)
B87: T-058 | C87: Aceptar HU-23 como Product Owner desde la interfaz y moverla a Done | D87: Aceptación | E87: Adiel | F87: 0.5 | G87: To Do | H87: 27/10 | I87: T-057 | K87: mueve la HU a Done
B88: HU-24 · Consultar cuánto falta comprar 3 pts
B89: Como residente de obra, quiero consultar cuánto falta comprar de cada insumo, para formular el siguiente requerimiento sobre una base cierta.
B90: T-059 | C90: Programar la consulta de lo que falta comprar por insumo | D90: Backend | E90: Adiel | F90: 2 | G90: To Do | H90: 25/10
B91: T-060 | C91: Programar la pantalla web «Saldo por comprar» con filtros y exportación CSV | D91: Web | E91: Fernando | F91: 2 | G91: Done | H91: 26/10 | K91: pantalla hecha con datos simulados; falta conectarla a la API real
B92: T-061 | C92: Conectar la pantalla de saldo por comprar con la API real | D92: Web | E92: Fernando | F92: 2 | G92: To Do | H92: 26/10 | I92: T-059, T-140
B93: T-062 | C93: Probar HU-24 en el ambiente de pruebas contra sus condiciones finales y aprobar su PR | D93: Pruebas | E93: Henry | F93: 1 | G93: To Do | H93: 27/10 | I93: T-059, T-060, T-061, T-139 | K93: alguien distinto del autor (T1, T5, T8)
B94: T-063 | C94: Aceptar HU-24 como Product Owner desde la interfaz y moverla a Done | D94: Aceptación | E94: Adiel | F94: 0.5 | G94: To Do | H94: 27/10 | I94: T-062 | K94: mueve la HU a Done
B95: HU-25 · Definir punto de reposición 5 pts
B96: Como residente de obra, quiero definir para cada insumo su stock de seguridad y su punto de reposición, para saber cuándo reponer y con cuánto colchón frente a la demora del proveedor.
B97: T-064 | C97: Programar el registro del stock de seguridad y del punto de reposición, con histórico | D97: Backend | E97: Adiel | F97: 4 | G97: To Do | H97: 25/10
B98: T-065 | C98: Programar el formulario web de parámetros de reposición | D98: Web | E98: Fernando | F98: 4 | G98: To Do | H98: 26/10
B99: T-066 | C99: Probar HU-25 en el ambiente de pruebas contra sus condiciones finales y aprobar su PR | D99: Pruebas | E99: Henry | F99: 1 | G99: To Do | H99: 27/10 | I99: T-064, T-065, T-139 | K99: alguien distinto del autor (T1, T5, T8)
B100: T-067 | C100: Aceptar HU-25 como Product Owner desde la interfaz y moverla a Done | D100: Aceptación | E100: Adiel | F100: 0.5 | G100: To Do | H100: 27/10 | I100: T-066 | K100: mueve la HU a Done
B101: HU-26 · Avisar cuándo reponer 5 pts
B102: Como residente de obra, quiero recibir un aviso cuando un insumo baje de su punto de reposición, para reponer antes de que la obra se detenga.
...

Sheet Tablero
B2: SIGRO · Sprint 1 · Tablero Scrum (15 al 28 de octubre)
B3: Cada HU se parte en tareas. To Do → Doing solo si la HU cumple la DoR (L1–L12). Doing → Done solo con la DoD (T1–T10 + condiciones finales). Meta: el lunes 27/10 (penúltimo día) todo en Done; el martes 28 es la Review.
B5: ID | C5: HU | D5: Historia | E5: Fase / área | F5: Tarea | G5: Responsable | H5: Horas | I5: Estado | J5: Fecha límite | K5: Evidencia / nota | L5: Depende de
B6: T-001 | C6: HU-01 | D6: Crear proyecto | E6: Backend | F6: Programar el endpoint para crear la obra, validando nombre y plazo obligatorios, fin ≥ inicio y estado inicial «en ejecución» | G6: Adiel | H6: 2 | I6: Done | J6: 25/10 | K6: hecho en la API de Adiel (PR #1 fusionado a main), con pruebas
B7: T-002 | C7: HU-01 | D7: Crear proyecto | E7: Web | F7: Programar la pantalla web para crear la obra | G7: Fernando | H7: 2 | I7: Done | J7: 26/10 | K7: pantalla hecha con datos simulados; falta conectarla a la API real
B8: T-003 | C8: HU-01 | D8: Crear proyecto | E8: Web | F8: Conectar la pantalla «Crear la obra» con el endpoint real de la API | G8: Fernando | H8: 2 | I8: To Do | J8: 26/10 | L8: T-001, T-140
B9: T-004 | C9: HU-01 | D9: Crear proyecto | E9: Pruebas | F9: Probar HU-01 en el ambiente de pruebas contra sus condiciones finales y aprobar su PR | G9: Henry | H9: 1 | I9: To Do | J9: 27/10 | K9: alguien distinto del autor (T1, T5, T8) | L9: T-001, T-002, T-003, T-139
B10: T-005 | C10: HU-01 | D10: Crear proyecto | E10: Aceptación | F10: Aceptar HU-01 como Product Owner desde la interfaz y moverla a Done | G10: Adiel | H10: 0.5 | I10: To Do | J10: 27/10 | K10: mueve la HU a Done | L10: T-004
B11: T-006 | C11: HU-03 | D11: Reportar la obra en semanas | E11: Backend | F11: Programar la generación automática de semanas al crear la obra y al ampliar el plazo, con sus pruebas | G11: Adiel | H11: 2 | I11: To Do | J11: 25/10 | K11: confirmar si la API ya las genera
B12: T-007 | C12: HU-03 | D12: Reportar la obra en semanas | E12: Web | F12: Programar la tira de semanas en la web (cerrada, en curso, por venir) | G12: Fernando | H12: 2 | I12: Done | J12: 26/10 | K12: pantalla hecha con datos simulados; falta conectarla a la API real
B13: T-008 | C13: HU-03 | D13: Reportar la obra en semanas | E13: Web | F13: Conectar la tira de semanas con la API real | G13: Fernando | H13: 2 | I13: To Do | J13: 26/10 | L13: T-006, T-140
B14: T-009 | C14: HU-03 | D14: Reportar la obra en semanas | E14: Pruebas | F14: Probar HU-03 en el ambiente de pruebas contra sus condiciones finales y aprobar su PR | G14: Henry | H14: 1 | I14: To Do | J14: 27/10 | K14: alguien distinto del autor (T1, T5, T8) | L14: T-006, T-007, T-008, T-139
B15: T-010 | C15: HU-03 | D15: Reportar la obra en semanas | E15: Aceptación | F15: Aceptar HU-03 como Product Owner desde la interfaz y moverla a Done | G15: Adiel | H15: 0.5 | I15: To Do | J15: 27/10 | K15: mueve la HU a Done | L15: T-009
B16: T-011 | C16: HU-07 | D16: Importar catálogo de insumos del S10 | E16: Integraciones | F16: Programar el lector del PDF «Relación de insumos» del S10 en el microservicio | G16: Fernando | H16: 4 | I16: Done | J16: 25/10 | K16: probado con el archivo real: 284 insumos, 0 fallidos, total exacto
B17: T-012 | C17: HU-07 | D17: Importar catálogo de insumos del S10 | E17: Backend | F17: Programar el endpoint que aplica la importación: crear o actualizar insumos por código sin tocar saldos | G17: Adiel | H17: 4 | I17: To Do | J17: 25/10
B18: T-013 | C18: HU-07 | D18: Importar catálogo de insumos del S10 | E18: Backend | F18: Configurar la llamada de la API a Integraciones con el token de servicio en docker compose | G18: Adiel | H18: 4 | I18: To Do | J18: 25/10 | K18: decisión B del 22/10
B19: T-014 | C19: HU-07 | D19: Importar catálogo de insumos del S10 | E19: Web | F19: Programar la pantalla web «Importar del S10» con el resumen de creados, actualizados y fallidos | G19: Fernando | H19: 4 | I19: Done | J19: 26/10 | K19: conectada al micro real
B20: T-015 | C20: HU-07 | D20: Importar catálogo de insumos del S10 | E20: Pruebas | F20: Probar HU-07 en el ambiente de pruebas contra sus condiciones finales y aprobar su PR | G20: Henry | H20: 1 | I20: To Do | J20: 27/10 | K20: alguien distinto del autor (T1, T5, T8) | L20: T-011, T-012, T-013, T-014, T-139
B21: T-016 | C21: HU-07 | D21: Importar catálogo de insumos del S10 | E21: Aceptación | F21: Aceptar HU-07 como Product Owner desde la interfaz y moverla a Done | G21: Adiel | H21: 0.5 | I21: To Do | J21: 27/10 | K21: mueve la HU a Done | L21: T-015
B22: T-017 | C22: HU-08 | D22: Registrar insumos | E22: Backend | F22: Programar el endpoint del catálogo: generar código único, rechazar duplicados y marcar «por verificar» | G22: Adiel | H22: 3 | I22: To Do | J22: 25/10
B23: T-018 | C23: HU-08 | D23: Registrar insumos | E23: Web | F23: Programar la pantalla web del catálogo para ver, dar de alta y editar insumos | G23: Fernando | H23: 3 | I23: Done | J23: 26/10 | K23: pantalla hecha con datos simulados; falta conectarla a la API real
B24: T-019 | C24: HU-08 | D24: Registrar insumos | E24: Web | F24: Conectar la pantalla del catálogo con la API real | G24: Fernando | H24: 3 | I24: To Do | J24: 26/10 | L24: T-017, T-140
B25: T-020 | C25: HU-08 | D25: Registrar insumos | E25: Pruebas | F25: Probar HU-08 en el ambiente de pruebas contra sus condiciones finales y aprobar su PR | G25: Henry | H25: 1 | I25: To Do | J25: 27/10 | K25: alguien distinto del autor (T1, T5, T8) | L25: T-017, T-018, T-019, T-139
B26: T-021 | C26: HU-08 | D26: Registrar insumos | E26: Aceptación | F26: Aceptar HU-08 como Product Owner desde la interfaz y moverla a Done | G26: Adiel | H26: 0.5 | I26: To Do | J26: 27/10 | K26: mueve la HU a Done | L26: T-020
B27: T-022 | C27: HU-12 | D27: Loguear usuario | E27: Backend | F27: Programar el login con Argon2id, sesión que caduca y se renueva, y bloqueo por intentos fallidos | G27: Adiel | H27: 3 | I27: Done | J27: 25/10 | K27: hecho en la API de Adiel (PR #1 fusionado a main), con pruebas
B28: T-023 | C28: HU-12 | D28: Loguear usuario | E28: Web | F28: Programar la pantalla web de login y el manejo de la sesión | G28: Henry | H28: 3 | I28: To Do | J28: 26/10
B29: T-024 | C29: HU-12 | D29: Loguear usuario | E29: Android | F29: Programar el login en la app del almacenero | G29: Nicolás | H29: 3 | I29: To Do | J29: 26/10 | L29: T-141
B30: T-025 | C30: HU-12 | D30: Loguear usuario | E30: Pruebas | F30: Probar HU-12 en el ambiente de pruebas contra sus condiciones finales y aprobar su PR | G30: Henry | H30: 1 | I30: To Do | J30: 27/10 | K30: alguien distinto del autor (T1, T5, T8) | L30: T-022, T-023, T-024, T-139
B31: T-026 | C31: HU-12 | D31: Loguear usuario | E31: Aceptación | F31: Aceptar HU-12 como Product Owner desde la interfaz y moverla a Done | G31: Adiel | H31: 0.5 | I31: To Do | J31: 27/10 | K31: mueve la HU a Done | L31: T-025
B32: T-027 | C32: HU-13 | D32: Asignar roles | E32: Backend | F32: Programar los roles y verificar sus permisos en el servidor | G32: Adiel | H32: 4 | I32: Done | J32: 25/10 | K32: hecho en la API de Adiel (PR #1 fusionado a main), con pruebas
B33: T-028 | C33: HU-13 | D33: Asignar roles | E33: Web | F33: Programar la pantalla web para crear usuarios, asignar su rol y darlos de baja | G33: Henry | H33: 4 | I33: To Do | J33: 26/10
B34: T-029 | C34: HU-13 | D34: Asignar roles | E34: Pruebas | F34: Probar HU-13 en el ambiente de pruebas contra sus condiciones finales y aprobar su PR | G34: Fernando | H34: 1 | I34: To Do | J34: 27/10 | K34: alguien distinto del autor (T1, T5, T8) | L34: T-027, T-028, T-139
B35: T-030 | C35: HU-13 | D35: Asignar roles | E35: Aceptación | F35: Aceptar HU-13 como Product Owner desde la interfaz y moverla a Done | G35: Adiel | H35: 0.5 | I35: To Do | J35: 27/10 | K35: mueve la HU a Done | L35: T-029
B36: T-031 | C36: HU-14 | D36: Asignar usuarios a obras | E36: Backend | F36: Programar el endpoint para asignar usuarios a obras | G36: Adiel | H36: 2 | I36: Done | J36: 25/10 | K36: hecho en la API de Adiel (PR #1 fusionado a main), con pruebas
B37: T-032 | C37: HU-14 | D37: Asignar usuarios a obras | E37: Web | F37: Programar la pantalla web para asignar usuarios a obras | G37: Henry | H37: 2 | I37: To Do | J37: 26/10
B38: T-033 | C38: HU-14 | D38: Asignar usuarios a obras | E38: Pruebas | F38: Probar HU-14 en el ambiente de pruebas contra sus condiciones finales y aprobar su PR | G38: Fernando | H38: 1 | I38: To Do | J38: 27/10 | K38: alguien distinto del autor (T1, T5, T8) | L38: T-031, T-032, T-139
B39: T-034 | C39: HU-14 | D39: Asignar usuarios a obras | E39: Aceptación | F39: Aceptar HU-14 como Product Owner desde la interfaz y moverla a Done | G39: Adiel | H39: 0.5 | I39: To Do | J39: 27/10 | K39: mueve la HU a Done | L39: T-033
B40: T-035 | C40: HU-15 | D40: Autorizar celular de la obra | E40: Backend | F40: Programar el registro de dispositivos autorizados por obra (máximo dos) y el rechazo del no autorizado | G40: Adiel | H40: 3 | I40: Done | J40: 25/10 | K40: hecho en la API de Adiel (PR #1 fusionado a main), con pruebas
B41: T-036 | C41: HU-15 | D41: Autorizar celular de la obra | E41: Android | F41: Programar en la app la generación del código del dispositivo en la primera instalación | G41: Nicolás | H41: 3 | I41: To Do | J41: 26/10 | L41: T-141
B42: T-037 | C42: HU-15 | D42: Autorizar celular de la obra | E42: Web | F42: Programar la pantalla web para autorizar o cambiar el celular de la obra | G42: Henry | H42: 3 | I42: To Do | J42: 26/10
B43: T-038 | C43: HU-15 | D43: Autorizar celular de la obra | E43: Pruebas | F43: Probar HU-15 en el ambiente de pruebas contra sus condiciones finales y aprobar su PR | G43: Henry | H43: 1 | I43: To Do | J43: 27/10 | K43: alguien distinto del autor (T1, T5, T8) | L43: T-035, T-036, T-037, T-139
B44: T-039 | C44: HU-15 | D44: Autorizar celular de la obra | E44: Aceptación | F44: Aceptar HU-15 como Product Owner desde la interfaz y moverla a Done | G44: Adiel | H44: 0.5 | I44: To Do | J44: 27/10 | K44: mueve la HU a Done | L44: T-038
B45: T-040 | C45: HU-16 | D45: Importar precios unitarios | E45: Integraciones | F45: Programar el lector del PDF del APU (371 páginas), identificando la partida por código y descripción | G45: Fernando | H45: 5 | I45: Doing | J45: 25/10 | K45: extracción ya probada: 6 902 filas, 1 217 partidas
B46: T-041 | C46: HU-16 | D46: Importar precios unitarios | E46: Backend | F46: Crear la tabla partida–recurso y programar el endpoint que la guarda | G46: Adiel | H46: 5 | I46: To Do | J46: 25/10
B47: T-042 | C47: HU-16 | D47: Importar precios unitarios | E47: Web | F47: Programar la pantalla web para importar el APU | G47: Fernando | H47: 5 | I47: To Do | J47: 26/10
B48: T-043 | C48: HU-16 | D48: Importar precios unitarios | E48: Pruebas | F48: Probar HU-16 en el ambiente de pruebas contra sus condiciones finales y aprobar su PR | G48: Henry | H48: 1 | I48: To Do | J48: 27/10 | K48: alguien distinto del autor (T1, T5, T8) | L48: T-040, T-041, T-042, T-139
B49: T-044 | C49: HU-16 | D49: Importar precios unitarios | E49: Aceptación | F49: Aceptar HU-16 como Product Owner desde la interfaz y moverla a Done | G49: Adiel | H49: 0.5 | I49: To Do | J49: 27/10 | K49: mueve la HU a Done | L49: T-043
B50: T-045 | C50: HU-17 | D50: Convertir unidades (kg a varillas) | E50: Backend | F50: Programar el registro del factor de conversión con su fecha y su usuario | G50: Adiel | H50: 2 | I50: To Do | J50: 25/10
B51: T-046 | C51: HU-17 | D51: Convertir unidades (kg a varillas) | E51: Web | F51: Programar el formulario web del factor de conversión (kg ↔ varillas) | G51: Fernando | H51: 2 | I51: To Do | J51: 26/10
B52: T-047 | C52: HU-17 | D52: Convertir unidades (kg a varillas) | E52: Pruebas | F52: Probar HU-17 en el ambiente de pruebas contra sus condiciones finales y aprobar su PR | G52: Henry | H52: 1 | I52: To Do | J52: 27/10 | K52: alguien distinto del autor (T1, T5, T8) | L52: T-045, T-046, T-139
B53: T-048 | C53: HU-17 | D53: Convertir unidades (kg a varillas) | E53: Aceptación | F53: Aceptar HU-17 como Product Owner desde la interfaz y moverla a Done | G53: Adiel | H53: 0.5 | I53: To Do | J53: 27/10 | K53: mueve la HU a Done | L53: T-047
B54: T-049 | C54: HU-19 | D54: Importar requerimiento de la obra | E54: Integraciones | F54: Adaptar el lector de la Relación de insumos para obtener el requerimiento total | G54: Fernando | H54: 3 | I54: To Do | J54: 25/10 | K54: el lector ya trae cantidades y precios
B55: T-050 | C55: HU-19 | D55: Importar requerimiento de la obra | E55: Backend | F55: Programar el guardado del requerimiento total y de sus ajustes con motivo | G55: Adiel | H55: 3 | I55: To Do | J55: 25/10
B56: T-051 | C56: HU-19 | D56: Importar requerimiento de la obra | E56: Web | F56: Programar la pantalla web del requerimiento total | G56: Fernando | H56: 3 | I56: To Do | J56: 26/10
B57: T-052 | C57: HU-19 | D57: Importar requerimiento de la obra | E57: Pruebas | F57: Probar HU-19 en el ambiente de pruebas contra sus condiciones finales y aprobar su PR | G57: Henry | H57: 1 | I57: To Do | J57: 27/10 | K57: alguien distinto del autor (T1, T5, T8) | L57: T-049, T-050, T-051, T-139
B58: T-053 | C58: HU-19 | D58: Importar requerimiento de la obra | E58: Aceptación | F58: Aceptar HU-19 como Product Owner desde la interfaz y moverla a Done | G58: Adiel | H58: 0.5 | I58: To Do | J58: 27/10 | K58: mueve la HU a Done | L58: T-052
B59: T-054 | C59: HU-23 | D59: Consultar cuánto se compró y consumió | E59: Backend | F59: Programar la consulta de avance: requerido, comprado, recibido y consumido por insumo | G59: Adiel | H59: 3 | I59: To Do | J59: 25/10
B60: T-055 | C60: HU-23 | D60: Consultar cuánto se compró y consumió | E60: Web | F60: Programar la pantalla web de avance de compra y consumo | G60: Fernando | H60: 3 | I60: Done | J60: 26/10 | K60: pantalla hecha con datos simulados; falta conectarla a la API real
B61: T-056 | C61: HU-23 | D61: Consultar cuánto se compró y consumió | E61: Web | F61: Conectar la pantalla de avance con la API real | G61: Fernando | H61: 3 | I61: To Do | J61: 26/10 | L61: T-054, T-140
B62: T-057 | C62: HU-23 | D62: Consultar cuánto se compró y consumió | E62: Pruebas | F62: Probar HU-23 en el ambiente de pruebas contra sus condiciones finales y aprobar su PR | G62: Henry | H62: 1 | I62: To Do | J62: 27/10 | K62: alguien distinto del autor (T1, T5, T8) | L62: T-054, T-055, T-056, T-139
B63: T-058 | C63: HU-23 | D63: Consultar cuánto se compró y consumió | E63: Aceptación | F63: Aceptar HU-23 como Product Owner desde la interfaz y moverla a Done | G63: Adiel | H63: 0.5 | I63: To Do | J63: 27/10 | K63: mueve la HU a Done | L63: T-057
B64: T-059 | C64: HU-24 | D64: Consultar cuánto falta comprar | E64: Backend | F64: Programar la consulta de lo que falta comprar por insumo | G64: Adiel | H64: 2 | I64: To Do | J64: 25/10
B65: T-060 | C65: HU-24 | D65: Consultar cuánto falta comprar | E65: Web | F65: Programar la pantalla web «Saldo por comprar» con filtros y exportación CSV | G65: Fernando | H65: 2 | I65: Done | J65: 26/10 | K65: pantalla hecha con datos simulados; falta conectarla a la API real
B66: T-061 | C66: HU-24 | D66: Consultar cuánto falta comprar | E66: Web | F66: Conectar la pantalla de saldo por comprar con la API real | G66: Fernando | H66: 2 | I66: To Do | J66: 26/10 | L66: T-059, T-140
B67: T-062 | C67: HU-24 | D67: Consultar cuánto falta comprar | E67: Pruebas | F67: Probar HU-24 en el ambiente de pruebas contra sus condiciones finales y aprobar su PR | G67: Henry | H67: 1 | I67: To Do | J67: 27/10 | K67: alguien distinto del autor (T1, T5, T8) | L67: T-059, T-060, T-061, T-139
B68: T-063 | C68: HU-24 | D68: Consultar cuánto falta comprar | E68: Aceptación | F68: Aceptar HU-24 como Product Owner desde la interfaz y moverla a Done | G68: Adiel | H68: 0.5 | I68: To Do | J68: 27/10 | K68: mueve la HU a Done | L68: T-062
B69: T-064 | C69: HU-25 | D69: Definir punto de reposición | E69: Backend | F69: Programar el registro del stock de seguridad y del punto de reposición, con histórico | G69: Adiel | H69: 4 | I69: To Do | J69: 25/10
B70: T-065 | C70: HU-25 | D70: Definir punto de reposición | E70: Web | F70: Programar el formulario web de parámetros de reposición | G70: Fernando | H70: 4 | I70: To Do | J70: 26/10
B71: T-066 | C71: HU-25 | D71: Definir punto de reposición | E71: Pruebas | F71: Probar HU-25 en el ambiente de pruebas contra sus condiciones finales y aprobar su PR | G71: Henry | H71: 1 | I71: To Do | J71: 27/10 | K71: alguien distinto del autor (T1, T5, T8) | L71: T-064, T-065, T-139
B72: T-067 | C72: HU-25 | D72: Definir punto de reposición | E72: Aceptación | F72: Aceptar HU-25 como Product Owner desde la interfaz y moverla a Done | G72: Adiel | H72: 0.5 | I72: To Do | J72: 27/10 | K72: mueve la HU a Done | L72: T-066
B73: T-068 | C73: HU-26 | D73: Avisar cuándo reponer | E73: Backend | F73: Programar el motor de alertas: una por insumo y marcada como atendida al comprar | G73: Adiel | H73: 3 | I73: To Do | J73: 25/10
B74: T-069 | C74: HU-26 | D74: Avisar cuándo reponer | E74: Web | F74: Programar las alertas de reposición en la web | G74: Fernando | H74: 3 | I74: Done | J74: 26/10 | K74: pantalla hecha con datos simulados; falta conectarla a la API real
B75: T-070 | C75: HU-26 | D75: Avisar cuándo reponer | E75: Web | F75: Conectar las alertas con la API real | G75: Fernando | H75: 3 | I75: To Do | J75: 26/10 | L75: T-068, T-140
B76: T-071 | C76: HU-26 | D76: Avisar cuándo reponer | E76: Pruebas | F76: Probar HU-26 en el ambiente de pruebas contra sus condiciones finales y aprobar su PR | G76: Henry | H76: 1 | I76: To Do | J76: 27/10 | K76: alguien distinto del autor (T1, T5, T8) | L76: T-068, T-069, T-070, T-139
B77: T-072 | C77: HU-26 | D77: Avisar cuándo reponer | E77: Aceptación | F77: Aceptar HU-26 como Product Owner desde la interfaz y moverla a Done | G77: Adiel | H77: 0.5 | I77: To Do | J77: 27/10 | K77: mueve la HU a Done | L77: T-071
B78: T-073 | C78: HU-27 | D78: Sugerir cuánto comprar | E78: Backend | F78: Programar el cálculo de la sugerencia de compra con su criterio | G78: Adiel | H78: 3 | I78: To Do | J78: 25/10
B79: T-074 | C79: HU-27 | D79: Sugerir cuánto comprar | E79: Web | F79: Programar la sugerencia editable dentro de la alerta | G79: Fernando | H79: 3 | I79: Done | J79: 26/10 | K79: pantalla hecha con datos simulados; falta conectarla a la API real
B80: T-075 | C80: HU-27 | D80: Sugerir cuánto comprar | E80: Web | F80: Conectar la sugerencia con la API real | G80: Fernando | H80: 3 | I80: To Do | J80: 26/10 | L80: T-073, T-140
B81: T-076 | C81: HU-27 | D81: Sugerir cuánto comprar | E81: Pruebas | F81: Probar HU-27 en el ambiente de pruebas contra sus condiciones finales y aprobar su PR | G81: Henry | H81: 1 | I81: To Do | J81: 27/10 | K81: alguien distinto del autor (T1, T5, T8) | L81: T-073, T-074, T-075, T-139
B82: T-077 | C82: HU-27 | D82: Sugerir cuánto comprar | E82: Aceptación | F82: Aceptar HU-27 como Product Owner desde la interfaz y moverla a Done | G82: Adiel | H82: 0.5 | I82: To Do | J82: 27/10 | K82: mueve la HU a Done | L82: T-076
B83: T-078 | C83: HU-29 | D83: Consultar proveedores | E83: Backend | F83: Programar la búsqueda de proveedores por razón social o RUC | G83: Adiel | H83: 2 | I83: Done | J83: 25/10 | K83: hecho en la API de Adiel (PR #1 fusionado a main), con pruebas
B84: T-079 | C84: HU-29 | D84: Consultar proveedores | E84: Web | F84: Programar la pantalla web de proveedores con los 626 reales | G84: Fernando | H84: 2 | I84: Done | J84: 26/10 | K84: pantalla hecha con datos simulados; falta conectarla a la API real
B85: T-080 | C85: HU-29 | D85: Consultar proveedores | E85: Web | F85: Conectar la pantalla de proveedores con la API real | G85: Henry | H85: 2 | I85: To Do | J85: 26/10 | L85: T-078, T-140
B86: T-081 | C86: HU-29 | D86: Consultar proveedores | E86: Pruebas | F86: Probar HU-29 en el ambiente de pruebas contra sus condiciones finales y aprobar su PR | G86: Fernando | H86: 1 | I86: To Do | J86: 27/10 | K86: alguien distinto del autor (T1, T5, T8) | L86: T-078, T-079, T-080, T-139
B87: T-082 | C87: HU-29 | D87: Consultar proveedores | E87: Aceptación | F87: Aceptar HU-29 como Product Owner desde la interfaz y moverla a Done | G87: Adiel | H87: 0.5 | I87: To Do | J87: 27/10 | K87: mueve la HU a Done | L87: T-081
B88: T-083 | C88: HU-30 | D88: Registrar proveedores | E88: Backend | F88: Programar el alta de proveedor rechazando RUC o DNI repetidos | G88: Adiel | H88: 2 | I88: Done | J88: 25/10 | K88: hecho en la API de Adiel (PR #1 fusionado a main), con pruebas
B89: T-084 | C89: HU-30 | D89: Registrar proveedores | E89: Web | F89: Programar el alta rápida de proveedor desde la compra | G89: Fernando | H89: 2 | I89: Done | J89: 26/10 | K89: pantalla hecha con datos simulados; falta conectarla a la API real
B90: T-085 | C90: HU-30 | D90: Registrar proveedores | E90: Web | F90: Conectar el alta de proveedor con la API real | G90: Henry | H90: 2 | I90: To Do | J90: 26/10 | L90: T-083, T-140
B91: T-086 | C91: HU-30 | D91: Registrar proveedores | E91: Pruebas | F91: Probar HU-30 en el ambiente de pruebas contra sus condiciones finales y aprobar su PR | G91: Fernando | H91: 1 | I91: To Do | J91: 27/10 | K91: alguien distinto del autor (T1, T5, T8) | L91: T-083, T-084, T-085, T-139
B92: T-087 | C92: HU-30 | D92: Registrar proveedores | E92: Aceptación | F92: Aceptar HU-30 como Product Owner desde la interfaz y moverla a Done | G92: Adiel | H92: 0.5 | I92: To Do | J92: 27/10 | K92: mueve la HU a Done | L92: T-086
B93: T-088 | C93: HU-32 | D93: Registrar compras | E93: Backend | F93: Programar el registro de compra: comprobante único, base, IGV y total, sin mover stock | G93: Adiel | H93: 5 | I93: Done | J93: 25/10 | K93: hecho en la API de Adiel (PR #1 fusionado a main), con pruebas
B94: T-089 | C94: HU-32 | D94: Registrar compras | E94: Web | F94: Programar la pantalla web de compras | G94: Fernando | H94: 5 | I94: Done | J94: 26/10 | K94: pantalla hecha con datos simulados; falta conectarla a la API real
B95: T-090 | C95: HU-32 | D95: Registrar compras | E95: Web | F95: Conectar la pantalla de compras con la API real | G95: Henry | H95: 5 | I95: To Do | J95: 26/10 | L95: T-088, T-140
B96: T-091 | C96: HU-32 | D96: Registrar compras | E96: Pruebas | F96: Probar HU-32 en el ambiente de pruebas contra sus condiciones finales y aprobar su PR | G96: Fernando | H96: 1 | I96: To Do | J96: 27/10 | K96: alguien distinto del autor (T1, T5, T8) | L96: T-088, T-089, T-090, T-139
B97: T-092 | C97: HU-32 | D97: Registrar compras | E97: Aceptación | F97: Aceptar HU-32 como Product Owner desde la interfaz y moverla a Done | G97: Adiel | H97: 0.5 | I97: To Do | J97: 27/10 | K97: mueve la HU a Done | L97: T-091
B98: T-093 | C98: HU-35 | D98: Recibir compras | E98: Backend | F98: Programar la recepción total o parcial que genera el ingreso al kárdex | G98: Adiel | H98: 4 | I98: To Do | J98: 25/10
B99: T-094 | C99: HU-35 | D99: Recibir compras | E99: Web | F99: Programar el registro de recepción en la web (pedido, recibido, pendiente) | G99: Fernando | H99: 4 | I99: Done | J99: 26/10 | K99: pantalla hecha con datos simulados; falta conectarla a la API real
B100: T-095 | C100: HU-35 | D100: Recibir compras | E100: Web | F100: Conectar la recepción con la API real | G100: Henry | H100: 4 | I100: To Do | J100: 26/10 | L100: T-093, T-140
B101: T-096 | C101: HU-35 | D101: Recibir compras | E101: Android | F101: Programar la recepción de compras en la app del almacenero | G101: Nicolás | H101: 4 | I101: To Do | J101: 26/10 | L101: T-141
B102: T-097 | C102: HU-35 | D102: Recibir compras | E102: Pruebas | F102: Probar HU-35 en el ambiente de pruebas contra sus condiciones finales y aprobar su PR | G102: Henry | H102: 1 | I102: To Do | J102: 27/10 | K102: alguien distinto del autor (T1, T5, T8) | L102: T-093, T-094, T-095, T-096, T-139
...

Sheet Resumen
B2: Resumen del tablero (se actualiza solo)
B4: Responsable | C4: To Do | D4: Doing | E4: Done | F4: Horas pendientes | G4: Doing ≤ 2 (sin Scrum)
B5: Fernando | C5: =COUNTIFS(Tablero!$G$6:$G$161,B5,Tablero!$I$6:$I$161,"To Do") | D5: =COUNTIFS(Tablero!$G$6:$G$161,B5,Tablero!$I$6:$I$161,"Doing") | E5: =COUNTIFS(Tablero!$G$6:$G$161,B5,Tablero!$I$6:$I$161,"Done") | F5: =SUMIFS(Tablero!$H$6:$H$161,Tablero!$G$6:$G$161,B5,Tablero!$I$6:$I$161,"<>Done") | G5: =IF(COUNTIFS(Tablero!$G$6:$G$161,B5,Tablero!$I$6:$I$161,"Doing",Tablero!$E$6:$E$161,"<>Scrum")<=2,"ok","demasiado en curso")
B6: Henry | C6: =COUNTIFS(Tablero!$G$6:$G$161,B6,Tablero!$I$6:$I$161,"To Do") | D6: =COUNTIFS(Tablero!$G$6:$G$161,B6,Tablero!$I$6:$I$161,"Doing") | E6: =COUNTIFS(Tablero!$G$6:$G$161,B6,Tablero!$I$6:$I$161,"Done") | F6: =SUMIFS(Tablero!$H$6:$H$161,Tablero!$G$6:$G$161,B6,Tablero!$I$6:$I$161,"<>Done") | G6: =IF(COUNTIFS(Tablero!$G$6:$G$161,B6,Tablero!$I$6:$I$161,"Doing",Tablero!$E$6:$E$161,"<>Scrum")<=2,"ok","demasiado en curso")
B7: Nicolás | C7: =COUNTIFS(Tablero!$G$6:$G$161,B7,Tablero!$I$6:$I$161,"To Do") | D7: =COUNTIFS(Tablero!$G$6:$G$161,B7,Tablero!$I$6:$I$161,"Doing") | E7: =COUNTIFS(Tablero!$G$6:$G$161,B7,Tablero!$I$6:$I$161,"Done") | F7: =SUMIFS(Tablero!$H$6:$H$161,Tablero!$G$6:$G$161,B7,Tablero!$I$6:$I$161,"<>Done") | G7: =IF(COUNTIFS(Tablero!$G$6:$G$161,B7,Tablero!$I$6:$I$161,"Doing",Tablero!$E$6:$E$161,"<>Scrum")<=2,"ok","demasiado en curso")
B8: Adiel | C8: =COUNTIFS(Tablero!$G$6:$G$161,B8,Tablero!$I$6:$I$161,"To Do") | D8: =COUNTIFS(Tablero!$G$6:$G$161,B8,Tablero!$I$6:$I$161,"Doing") | E8: =COUNTIFS(Tablero!$G$6:$G$161,B8,Tablero!$I$6:$I$161,"Done") | F8: =SUMIFS(Tablero!$H$6:$H$161,Tablero!$G$6:$G$161,B8,Tablero!$I$6:$I$161,"<>Done") | G8: =IF(COUNTIFS(Tablero!$G$6:$G$161,B8,Tablero!$I$6:$I$161,"Doing",Tablero!$E$6:$E$161,"<>Scrum")<=2,"ok","demasiado en curso")
B9: Total | C9: =SUM(C5:C8) | D9: =SUM(D5:D8) | E9: =SUM(E5:E8) | F9: =SUM(F5:F8)
B12: HU | C12: Historia | D12: Puntos | E12: Tareas | F12: Tareas Done | G12: % avance | H12: Estado de la HU
B13: HU-01 | C13: Crear proyecto | D13: 3 | E13: =COUNTIF(Tablero!$C$6:$C$161,B13) | F13: =COUNTIFS(Tablero!$C$6:$C$161,B13,Tablero!$I$6:$I$161,"Done") | G13: =IF(E13=0,0,F13/E13) | H13: =IF(COUNTIFS(Tablero!$C$6:$C$161,B13,Tablero!$E$6:$E$161,"Aceptación",Tablero!$I$6:$I$161,"Done")=1,"Done",IF(F13>0,"Doing","To Do"))
B14: HU-03 | C14: Reportar la obra en semanas | D14: 3 | E14: =COUNTIF(Tablero!$C$6:$C$161,B14) | F14: =COUNTIFS(Tablero!$C$6:$C$161,B14,Tablero!$I$6:$I$161,"Done") | G14: =IF(E14=0,0,F14/E14) | H14: =IF(COUNTIFS(Tablero!$C$6:$C$161,B14,Tablero!$E$6:$E$161,"Aceptación",Tablero!$I$6:$I$161,"Done")=1,"Done",IF(F14>0,"Doing","To Do"))
B15: HU-07 | C15: Importar catálogo de insumos del S10 | D15: 8 | E15: =COUNTIF(Tablero!$C$6:$C$161,B15) | F15: =COUNTIFS(Tablero!$C$6:$C$161,B15,Tablero!$I$6:$I$161,"Done") | G15: =IF(E15=0,0,F15/E15) | H15: =IF(COUNTIFS(Tablero!$C$6:$C$161,B15,Tablero!$E$6:$E$161,"Aceptación",Tablero!$I$6:$I$161,"Done")=1,"Done",IF(F15>0,"Doing","To Do"))
B16: HU-08 | C16: Registrar insumos | D16: 5 | E16: =COUNTIF(Tablero!$C$6:$C$161,B16) | F16: =COUNTIFS(Tablero!$C$6:$C$161,B16,Tablero!$I$6:$I$161,"Done") | G16: =IF(E16=0,0,F16/E16) | H16: =IF(COUNTIFS(Tablero!$C$6:$C$161,B16,Tablero!$E$6:$E$161,"Aceptación",Tablero!$I$6:$I$161,"Done")=1,"Done",IF(F16>0,"Doing","To Do"))
B17: HU-12 | C17: Loguear usuario | D17: 5 | E17: =COUNTIF(Tablero!$C$6:$C$161,B17) | F17: =COUNTIFS(Tablero!$C$6:$C$161,B17,Tablero!$I$6:$I$161,"Done") | G17: =IF(E17=0,0,F17/E17) | H17: =IF(COUNTIFS(Tablero!$C$6:$C$161,B17,Tablero!$E$6:$E$161,"Aceptación",Tablero!$I$6:$I$161,"Done")=1,"Done",IF(F17>0,"Doing","To Do"))
B18: HU-13 | C18: Asignar roles | D18: 5 | E18: =COUNTIF(Tablero!$C$6:$C$161,B18) | F18: =COUNTIFS(Tablero!$C$6:$C$161,B18,Tablero!$I$6:$I$161,"Done") | G18: =IF(E18=0,0,F18/E18) | H18: =IF(COUNTIFS(Tablero!$C$6:$C$161,B18,Tablero!$E$6:$E$161,"Aceptación",Tablero!$I$6:$I$161,"Done")=1,"Done",IF(F18>0,"Doing","To Do"))
B19: HU-14 | C19: Asignar usuarios a obras | D19: 3 | E19: =COUNTIF(Tablero!$C$6:$C$161,B19) | F19: =COUNTIFS(Tablero!$C$6:$C$161,B19,Tablero!$I$6:$I$161,"Done") | G19: =IF(E19=0,0,F19/E19) | H19: =IF(COUNTIFS(Tablero!$C$6:$C$161,B19,Tablero!$E$6:$E$161,"Aceptación",Tablero!$I$6:$I$161,"Done")=1,"Done",IF(F19>0,"Doing","To Do"))
B20: HU-15 | C20: Autorizar celular de la obra | D20: 5 | E20: =COUNTIF(Tablero!$C$6:$C$161,B20) | F20: =COUNTIFS(Tablero!$C$6:$C$161,B20,Tablero!$I$6:$I$161,"Done") | G20: =IF(E20=0,0,F20/E20) | H20: =IF(COUNTIFS(Tablero!$C$6:$C$161,B20,Tablero!$E$6:$E$161,"Aceptación",Tablero!$I$6:$I$161,"Done")=1,"Done",IF(F20>0,"Doing","To Do"))
B21: HU-16 | C21: Importar precios unitarios | D21: 8 | E21: =COUNTIF(Tablero!$C$6:$C$161,B21) | F21: =COUNTIFS(Tablero!$C$6:$C$161,B21,Tablero!$I$6:$I$161,"Done") | G21: =IF(E21=0,0,F21/E21) | H21: =IF(COUNTIFS(Tablero!$C$6:$C$161,B21,Tablero!$E$6:$E$161,"Aceptación",Tablero!$I$6:$I$161,"Done")=1,"Done",IF(F21>0,"Doing","To Do"))
B22: HU-17 | C22: Convertir unidades (kg a varillas) | D22: 3 | E22: =COUNTIF(Tablero!$C$6:$C$161,B22) | F22: =COUNTIFS(Tablero!$C$6:$C$161,B22,Tablero!$I$6:$I$161,"Done") | G22: =IF(E22=0,0,F22/E22) | H22: =IF(COUNTIFS(Tablero!$C$6:$C$161,B22,Tablero!$E$6:$E$161,"Aceptación",Tablero!$I$6:$I$161,"Done")=1,"Done",IF(F22>0,"Doing","To Do"))
B23: HU-19 | C23: Importar requerimiento de la obra | D23: 5 | E23: =COUNTIF(Tablero!$C$6:$C$161,B23) | F23: =COUNTIFS(Tablero!$C$6:$C$161,B23,Tablero!$I$6:$I$161,"Done") | G23: =IF(E23=0,0,F23/E23) | H23: =IF(COUNTIFS(Tablero!$C$6:$C$161,B23,Tablero!$E$6:$E$161,"Aceptación",Tablero!$I$6:$I$161,"Done")=1,"Done",IF(F23>0,"Doing","To Do"))
B24: HU-23 | C24: Consultar cuánto se compró y consumió | D24: 5 | E24: =COUNTIF(Tablero!$C$6:$C$161,B24) | F24: =COUNTIFS(Tablero!$C$6:$C$161,B24,Tablero!$I$6:$I$161,"Done") | G24: =IF(E24=0,0,F24/E24) | H24: =IF(COUNTIFS(Tablero!$C$6:$C$161,B24,Tablero!$E$6:$E$161,"Aceptación",Tablero!$I$6:$I$161,"Done")=1,"Done",IF(F24>0,"Doing","To Do"))
... B41: HU-63 | C41: Tomar asistencia | D41: 5 | E41: =COUNTIF(Tablero!$C$6:$C$161,B41) | F41: =COUNTIFS(Tablero!$C$6:$C$161,B41,Tablero!$I$6:$I$161,"Done") | G41: =IF(E41=0,0,F41/E41) | H41: =IF(COUNTIFS(Tablero!$C$6:$C$161,B41,Tablero!$E$6:$E$161,"Aceptación",Tablero!$I$6:$I$161,"Done")=1,"Done",IF(F41>0,"Doing","To Do"))
B42: Puntos terminados (velocidad) | D42: =SUMIF(H13:H41,"Done",D13:D41)
B43: Puntos comprometidos | D43: =SUM(D13:D41)

Sheet Reglas del tablero
B2: Reglas del tablero
B4: Columnas | C4: To Do → Doing → Done. Una tarjeta por TAREA; la HU queda Done cuando su tarea «Aceptar … como Product Owner» pasa a Done.
B5: Criterio de las tareas | C5: Una tarea entra solo si produce algo que la DoD verifica o si desbloquea a otra. Lo ya hecho se cuenta una vez; el diseño de pantallas y el UML se hacen por flujo, no por HU.
B6: Entrada a Doing (DoR) | C6: Una tarea solo pasa a Doing si su HU cumple L1–L12: entre ellos recursos identificados, requisitos técnicos y accesos de red.
B7: Entrada a Done (DoD) | C7: La tarea de cierre pasa a Done solo con T1–T10 y las condiciones finales de la tarjeta verificadas desde la interfaz y aceptadas por el PO.
B8: Límite de trabajo en curso | C8: Máximo 2 tareas en Doing por persona: se termina antes de empezar otra.
B9: Daily Scrum | C9: Todos los días, 15 minutos, frente al tablero: qué terminé, qué hago hoy, qué me bloquea. Se mueve la tarjeta en la reunión, no después.
B10: Fecha de cierre | C10: Lunes 27/10 (penúltimo día): todo en Done. Martes 28/10: Sprint Review y Retrospectiva. Lo que no llegue vuelve al Product Backlog, no se arrastra a escondidas.
B11: Bloqueos | C11: Las tareas «Conectar… a la API real» dependen del ClienteHttp (Henry) y del ambiente de pruebas (Adiel): esas dos van primero.
B12: Reparto | C12: Web: Fernando y Henry · App Android: Nicolás · Backend: Adiel (además PO) · Integraciones: Fernando (además Scrum Master).
