Workbook

Sheet Registro de incidencias
B2: Nombre del proyecto | C2: SIGRO · Sistema de Gestión de Recursos de Obra
B3: Organización | C3: SEVENS INGENIEROS SAC (RUC 20606456892) | F3: HU / tarea | G3: Solución
B4: Solución | C4: Web de oficina (React), app Android del almacenero que registra sin señal, API FastAPI + PostgreSQL y microservicios de Integraciones (S10, SUNAT, RENIEC) y Notificaciones
B5: Objetivo del proyecto | C5: Mejorar el control operativo de los recursos de obra —materiales, herramientas y horas hombre— de SEVENS INGENIEROS SAC, para reducir las interrupciones de obra por falta de material y el capital inmovilizado en material que sobra
B6: |No. sprint | C6: 1 | G6: Objetivo del Sprint | H6: El objetivo del primer sprint es poder controlar los recursos de la obra: desde lo que pide el S10 hasta lo que se compra, se consume y cuesta.
B8: Fecha | C8: Incidencia | D8: Persona relacionada | E8: Rol | F8: Artefacto relacionado | G8: Solución | H8: Referencia
B9: 15/10/2026 | C9: El docente redujo el curso de tres a dos sprints | D9: Omar Loaiza | E9: Docente | F9: Cronograma del Project Charter | G9: Se replanificó: Sprint 1 del 15 al 28/10 y Sprint 2 del 29/10 al 11/11 | H9: Indicación en clase, 15/10
B10: 16/10/2026 | C10: La mano de obra entra al alcance (antes estaba fuera, decisión D6) | D10: Fernando Istaña | E10: Scrum Master | F10: Product Backlog | G10: Nueva épica E7 limitada al tareo: HU-62 a HU-65 | H10: Acuerdo del equipo, 16/10
B11: 21/10/2026 | C11: Faltaban los reportes del S10 y bloqueaban la importación (HU-07, 16, 17 y 19) | D11: Pool Briones | E11: Cliente | F11: HU-07, HU-16, HU-17, HU-19 | G11: El cliente entregó Presupuesto, APU y Relación de insumos del presupuesto 2701006 | H11: Reportes 5.1, 5.2 y 5.3 del S10
B12: 21/10/2026 | C12: El objetivo del sprint hablaba de «compras» y de «presupuestado» | D12: Ing. Junior Cercado | E12: Revisor | F12: Objetivo del Sprint 1 | G12: Se redactó con «ingresos y salidas», «planificado» y horas hombre medidas contra las planificadas | H12: Corrección del 21/10
B13: 22/10/2026 | C13: Compras y proveedores tenían el actor equivocado (almacenero en vez de residente) | D13: Pool Briones | E13: Cliente | F13: HU-29, HU-30, HU-31, HU-32 | G13: Ficha de cambio CR-05: el actor pasa a residente de obra | H13: Respuesta del cliente por WhatsApp, 22/10
B14: 22/10/2026 | C14: Requisito nuevo del cliente: un formato para pedir materiales | D14: Pool Briones | E14: Cliente | F14: Product Backlog | G14: Ficha CR-04: «solicitud de materiales», HU-66 y HU-67 en el Sprint 2 | H14: Respuesta del cliente por WhatsApp, 22/10
B15: 22/10/2026 | C15: El repositorio de GitHub está público y contiene datos del cliente | D15: Fernando Istaña | E15: Scrum Master | F15: Repositorio xteban-sp/sevens-sigro | G15: Pasarlo a privado e invitar al docente como lector (T-237) | H15: Auditoría de coherencia, 22/10
B16: 22/10/2026 | C16: El microservicio de integraciones no autenticaba a quien lo llamaba | D16: Fernando Istaña | E16: Developer (integraciones) | F16: integraciones/main.py | G16: Token de servicio X-Servicio-Token obligatorio cuando se configura | H16: Revisión del avance de Adiel, 22/10
B17: 22/10/2026 | C17: Sin Docker en el equipo de desarrollo: docker compose sin construir ni desplegar | D17: Víctor Adiel Luján | E17: Product Owner / backend | F17: docker-compose.yml | G17: Fernando asume el despliegue del ambiente de pruebas (T-233) | H17: Avance de Adiel, 22/10
B18: 22/10/2026 | C18: uvicorn no se encontraba en el PATH de Windows al levantar el microservicio | D18: Fernando Istaña | E18: Developer (integraciones) | F18: integraciones/ | G18: Se levanta con «py -m uvicorn main:app --port 8001 --env-file .env» | H18: integraciones/LEEME.md
B19: 22/10/2026 | C19: Aviso de seguridad: certificados de una autoridad comprometida en certifi | D19: Fernando Istaña | E19: Developer (integraciones) | F19: integraciones/requirements.txt | G19: Se exige certifi>=2026.10.19 | H19: Aviso de seguridad de octubre de 2026
... B24: 22/10/2026 | C24: Cambio de reparto: Henry pasa a la web y Adiel toma todo el backend | D24: Henry Ticona | E24: Developer | F24: equipo/henry.md y CLAUDE.md | G24: Guía de arranque de Henry y tablero con responsables actualizados | H24: Rama scrum-tablero-sprint-1

Sheet Bitácora de trabajo
B3: Nombre del proyecto | C3: SIGRO · Sistema de Gestión de Recursos de Obra
B4: Organización | C4: SEVENS INGENIEROS SAC (RUC 20606456892)
B5: Solución | C5: Web de oficina (React), app Android del almacenero que registra sin señal, API FastAPI + PostgreSQL y microservicios de Integraciones (S10, SUNAT, RENIEC) y Notificaciones
B6: Objetivo del proyecto | C6: Mejorar el control operativo de los recursos de obra —materiales, herramientas y horas hombre— de SEVENS INGENIEROS SAC, para reducir las interrupciones de obra por falta de material y el capital inmovilizado en material que sobra
B7: |No. sprint | C7: 1 | D7: Objetivo del Sprint | E7: El objetivo del primer sprint es poder controlar los recursos de la obra: desde lo que pide el S10 hasta lo que se compra, se consume y cuesta.
B9: Día del proyecto | C9: Fecha | D9: Colaborador | E9: Rol | F9: Hora | G9: Descripción de la actividad | H9: Tarea
B10: Día 1 | C10: 15/10/2026 | D10: Equipo Scrum | E10: Scrum Team | G10: Sprint Planning: objetivo del Sprint 1 y selección de 29 historias | H10: Sprint Backlog
B11: Día 2 | C11: 16/10/2026 | D11: Fernando Istaña | E11: Scrum Master | G11: Incorporar la mano de obra al Product Backlog (épica E7) | H11: HU-62 a HU-65
B12: Día 7 | C12: 21/10/2026 | D12: Equipo Scrum | E12: Scrum Team | G12: Planning Poker: estimación de las historias con el voto de los cuatro integrantes | H12: Puntuación de las HU
B13: Día 7 | C13: 21/10/2026 | D13: Fernando Istaña | E13: Scrum Master / Developer | G13: Recibir los reportes del S10 y extraer el análisis de precios unitarios (6 902 filas, 1 217 partidas) | H13: T-069
B14: Día 7 | C14: 21/10/2026 | D14: Nicolás Pachamora | E14: Developer | G14: Diagramas de actividades del negocio (A1 a A4) y de estados (E1 a E3) | H14: T-259
B15: Día 7 | C15: 21/10/2026 | D15: Fernando Istaña | E15: Scrum Master | F15: 19:02 | G15: Subir al repositorio el contexto del proyecto, las historias del Sprint 1 y 2 y las reglas de dominio (commit) | H15: CLAUDE.md, docs/
B16: Día 7 | C16: 21/10/2026 | D16: Fernando Istaña | E16: Scrum Master | F16: 20:33 | G16: Subir las pantallas del Sprint 1, la estimación del equipo y los entregables (commit) | H16: Diseño UI
B17: Día 8 | C17: 22/10/2026 | D17: Fernando Istaña | E17: Developer (web e integraciones) | F17: 09:30 | G17: Web de oficina (pantallas e importador del S10), microservicio de integraciones (RUC, DNI, S10: 284 insumos, 0 fallidos), semillas reales del cliente y documentos Scrum (commit) | H17: T-023
B18: Día 8 | C18: 22/10/2026 | D18: Víctor Adiel Luján | E18: Product Owner / backend | F18: 10:21 | G18: API de obra, compras y tareo (629 pruebas) y microservicio de Notificaciones con outbox; PR #1 fusionado | H18: HU-01, 12–15, 29, 30, 32, 62, 63
B19: Día 8 | C19: 22/10/2026 | D19: Víctor Adiel Luján | E19: Product Owner / backend | F19: 10:35 | G19: Diagramas físico (con outbox), entidad-relación y esquema de microservicios (commit) | H19: Base de datos
B20: Día 8 | C20: 22/10/2026 | D20: Víctor Adiel Luján | E20: Product Owner / backend | F20: 12:07 | G20: Proveedor nuevo con RUC o DNI (decisión D-C5) y decisiones de la API ratificadas (commit) | H20: HU-30
B21: Día 8 | C21: 22/10/2026 | D21: Víctor Adiel Luján | E21: Product Owner / backend | F21: 15:07 | G21: Diagramas en draw.io editable; PR #2 fusionado a main | H21: Base de datos
B22: Día 8 | C22: 22/10/2026 | D22: Equipo Scrum | E22: Scrum Team | G22: Presentación al docente: puntuación de las HU, objetivo del sprint y tarjetas DoR y DoD; se recibe su retroalimentación | H22: Product Backlog y Sprint Backlog
B23: Día 8 | C23: 22/10/2026 | D23: Fernando Istaña | E23: Scrum Master | G23: Auditoría de coherencia y SWEBOK; corrección de 7 errores en los diagramas | H23: Modelado UML
B24: Día 8 | C24: 22/10/2026 | D24: Fernando Istaña | E24: Scrum Master | F24: 22:08 | G24: Tablero Scrum con las tareas por HU y guía de arranque de Henry en la web (commit en la rama scrum-tablero-sprint-1) | H24: T-253
B25: Día 8 | C25: 22/10/2026 | D25: Fernando Istaña | E25: Scrum Master | F25: 22:30 | G25: Tareas con el modelo del docente, registro de incidencias, bitácora e historias técnicas HT-01 a HT-08 (commit) | H25: T-253
B42: Horas tomadas de los commits del repositorio; donde está vacía la completa el colaborador. Del 23/10 en adelante, una fila por actividad: fecha · hora · colaborador · qué hizo · T-xxx.

Sheet Tablero (To Do · Doing · Done)
B2: Registro de tareas · Sprint 1 · To Do → Doing → Done
B3: Al mover una tarjeta se anota la fecha y se confirma el criterio. To Do → Doing: la HU cumple la DoR (L1–L12). Doing → Done: se cumple el criterio de la tarea; la HU queda Done solo cuando su «Aceptación» cumple la DoD (T1–T10 + condiciones finales). Máximo 2 tareas en Doing por persona. Lunes 27/10: todo en Done.
B5: ID | C5: HU | D5: Historia | E5: Fase | F5: Tarea | G5: Responsable | H5: Horas | I5: Límite | J5: Depende de | K5: Estado | L5: ¿DoR de la HU? | M5: Fecha a Doing | N5: Criterio para Done | O5: ¿Criterio cumplido? | P5: Fecha a Done | Q5: Evidencia (PR / enlace) | R5: Control | S5: n.º To Do | T5: n.º Doing | U5: n.º Done
B6: T-001 | C6: HU-01 | D6: Crear proyecto | E6: Diseño UI | F6: Diseñar la interfaz de usuario de HU-01: pantalla 9 · Crear la obra | G6: Fernando | H6: 1 | I6: 23/10 | K6: Done | L6: Sí | M6: 22/10/2026 | N6: Mockup en el lienzo, revisado por el equipo | O6: Sí | P6: 22/10/2026 | Q6: Lienzo «SIGRO · Pantallas y diagramas del Sprint 1» | R6: =IF(AND(K6<>"To Do",L6<>"Sí"),"⚠ pasó a Doing sin DoR",IF(AND(K6="Done",O6<>"Sí"),"⚠ Done sin criterio cumplido",IF(AND(K6="Doing",COUNTIFS($G$6:$G$266,G6,$K$6:$K$266,"Doing",$E$6:$E$266,"<>Scrum")>2,E6<>"Scrum"),"⚠ más de 2 en Doing","ok"))) | S6: =IF($K6="To Do",COUNTIF($K$6:$K6,"To Do"),"") | T6: =IF($K6="Doing",COUNTIF($K$6:$K6,"Doing"),"") | U6: =IF($K6="Done",COUNTIF($K$6:$K6,"Done"),"")
B7: T-002 | C7: HU-01 | D7: Crear proyecto | E7: Modelado UML | F7: Modelar la funcionalidad de HU-01 con el diagrama UML de estados de la obra (en ejecución → ampliada → cerrada) | G7: Fernando | H7: 1 | I7: 24/10 | J7: T-001 | K7: To Do | N7: Diagrama publicado en el repo o el lienzo | R7: =IF(AND(K7<>"To Do",L7<>"Sí"),"⚠ pasó a Doing sin DoR",IF(AND(K7="Done",O7<>"Sí"),"⚠ Done sin criterio cumplido",IF(AND(K7="Doing",COUNTIFS($G$6:$G$266,G7,$K$6:$K$266,"Doing",$E$6:$E$266,"<>Scrum")>2,E7<>"Scrum"),"⚠ más de 2 en Doing","ok"))) | S7: =IF($K7="To Do",COUNTIF($K$6:$K7,"To Do"),"") | T7: =IF($K7="Doing",COUNTIF($K$6:$K7,"Doing"),"") | U7: =IF($K7="Done",COUNTIF($K$6:$K7,"Done"),"")
B8: T-003 | C8: HU-01 | D8: Crear proyecto | E8: Base de datos | F8: Implementar las tablas asociadas a HU-01: proyecto, proyecto_plazo_historial | G8: Adiel | H8: 1 | I8: 24/10 | K8: Done | L8: Sí | M8: 22/10/2026 | N8: Migración fusionada, corre en base limpia y con datos, y se revierte | O8: Sí | P8: 22/10/2026 | Q8: PR #1 de Adiel (22/10) | R8: =IF(AND(K8<>"To Do",L8<>"Sí"),"⚠ pasó a Doing sin DoR",IF(AND(K8="Done",O8<>"Sí"),"⚠ Done sin criterio cumplido",IF(AND(K8="Doing",COUNTIFS($G$6:$G$266,G8,$K$6:$K$266,"Doing",$E$6:$E$266,"<>Scrum")>2,E8<>"Scrum"),"⚠ más de 2 en Doing","ok"))) | S8: =IF($K8="To Do",COUNTIF($K$6:$K8,"To Do"),"") | T8: =IF($K8="Doing",COUNTIF($K$6:$K8,"Doing"),"") | U8: =IF($K8="Done",COUNTIF($K$6:$K8,"Done"),"")
B9: T-004 | C9: HU-01 | D9: Crear proyecto | E9: Backend | F9: Programar el back-end de HU-01 (entidad, repositorio, servicio y controlador): el endpoint para crear la obra, validando nombre y plazo obligatorios, fin ≥ inicio y estado inicial «en ejecución» | G9: Adiel | H9: 2 | I9: 25/10 | K9: Done | L9: Sí | M9: 22/10/2026 | N9: PR fusionado con sus pruebas automáticas en verde y el endpoint documentado | O9: Sí | P9: 22/10/2026 | Q9: PR #1 y #2 de Adiel (22/10) | R9: =IF(AND(K9<>"To Do",L9<>"Sí"),"⚠ pasó a Doing sin DoR",IF(AND(K9="Done",O9<>"Sí"),"⚠ Done sin criterio cumplido",IF(AND(K9="Doing",COUNTIFS($G$6:$G$266,G9,$K$6:$K$266,"Doing",$E$6:$E$266,"<>Scrum")>2,E9<>"Scrum"),"⚠ más de 2 en Doing","ok"))) | S9: =IF($K9="To Do",COUNTIF($K$6:$K9,"To Do"),"") | T9: =IF($K9="Doing",COUNTIF($K$6:$K9,"Doing"),"") | U9: =IF($K9="Done",COUNTIF($K$6:$K9,"Done"),"")
B10: T-005 | C10: HU-01 | D10: Crear proyecto | E10: Triggers y funciones | F10: Implementar el CHECK de fecha de fin ≥ inicio en proyecto (HU-01) | G10: Adiel | H10: 1 | I10: 25/10 | J10: T-003 | K10: To Do | N10: Regla en la base con su prueba, en un PR fusionado | R10: =IF(AND(K10<>"To Do",L10<>"Sí"),"⚠ pasó a Doing sin DoR",IF(AND(K10="Done",O10<>"Sí"),"⚠ Done sin criterio cumplido",IF(AND(K10="Doing",COUNTIFS($G$6:$G$266,G10,$K$6:$K$266,"Doing",$E$6:$E$266,"<>Scrum")>2,E10<>"Scrum"),"⚠ más de 2 en Doing","ok"))) | S10: =IF($K10="To Do",COUNTIF($K$6:$K10,"To Do"),"") | T10: =IF($K10="Doing",COUNTIF($K$6:$K10,"Doing"),"") | U10: =IF($K10="Done",COUNTIF($K$6:$K10,"Done"),"")
B11: T-006 | C11: HU-01 | D11: Crear proyecto | E11: Front-end web | F11: Programar la pantalla web para crear la obra | G11: Fernando | H11: 2 | I11: 26/10 | K11: Done | L11: Sí | M11: 22/10/2026 | N11: PR fusionado, build sin errores, modo claro/oscuro y escala 125 % | O11: Sí | P11: 22/10/2026 | Q11: Commit del 22/10 09:30 (datos simulados) | R11: =IF(AND(K11<>"To Do",L11<>"Sí"),"⚠ pasó a Doing sin DoR",IF(AND(K11="Done",O11<>"Sí"),"⚠ Done sin criterio cumplido",IF(AND(K11="Doing",COUNTIFS($G$6:$G$266,G11,$K$6:$K$266,"Doing",$E$6:$E$266,"<>Scrum")>2,E11<>"Scrum"),"⚠ más de 2 en Doing","ok"))) | S11: =IF($K11="To Do",COUNTIF($K$6:$K11,"To Do"),"") | T11: =IF($K11="Doing",COUNTIF($K$6:$K11,"Doing"),"") | U11: =IF($K11="Done",COUNTIF($K$6:$K11,"Done"),"")
B12: T-007 | C12: HU-01 | D12: Crear proyecto | E12: Conexión API | F12: Conectar la pantalla «Crear la obra» con el endpoint real de la API | G12: Fernando | H12: 2 | I12: 26/10 | J12: T-004, T-006, T-240 | K12: To Do | N12: La pantalla muestra los datos reales del servidor y sus errores | R12: =IF(AND(K12<>"To Do",L12<>"Sí"),"⚠ pasó a Doing sin DoR",IF(AND(K12="Done",O12<>"Sí"),"⚠ Done sin criterio cumplido",IF(AND(K12="Doing",COUNTIFS($G$6:$G$266,G12,$K$6:$K$266,"Doing",$E$6:$E$266,"<>Scrum")>2,E12<>"Scrum"),"⚠ más de 2 en Doing","ok"))) | S12: =IF($K12="To Do",COUNTIF($K$6:$K12,"To Do"),"") | T12: =IF($K12="Doing",COUNTIF($K$6:$K12,"Doing"),"") | U12: =IF($K12="Done",COUNTIF($K$6:$K12,"Done"),"")
B13: T-008 | C13: HU-01 | D13: Crear proyecto | E13: Pruebas | F13: Probar la funcionalidad de HU-01 (la API con Postman y la pantalla web) contra cada condición final y aprobar su PR | G13: Henry | H13: 1 | I13: 27/10 | J13: T-003, T-004, T-005, T-006, T-007, T-233 | K13: To Do | N13: Cada condición final verificada con Postman y en la interfaz; PR aprobado por alguien distinto del autor | R13: =IF(AND(K13<>"To Do",L13<>"Sí"),"⚠ pasó a Doing sin DoR",IF(AND(K13="Done",O13<>"Sí"),"⚠ Done sin criterio cumplido",IF(AND(K13="Doing",COUNTIFS($G$6:$G$266,G13,$K$6:$K$266,"Doing",$E$6:$E$266,"<>Scrum")>2,E13<>"Scrum"),"⚠ más de 2 en Doing","ok"))) | S13: =IF($K13="To Do",COUNTIF($K$6:$K13,"To Do"),"") | T13: =IF($K13="Doing",COUNTIF($K$6:$K13,"Doing"),"") | U13: =IF($K13="Done",COUNTIF($K$6:$K13,"Done"),"")
B14: T-009 | C14: HU-01 | D14: Crear proyecto | E14: Aceptación | F14: Aceptar HU-01 como Product Owner desde la interfaz y moverla a Done | G14: Adiel | H14: 0.5 | I14: 27/10 | J14: T-008 | K14: To Do | N14: DoD T1–T10 + condiciones finales aceptadas por el PO → la HU pasa a Done | R14: =IF(AND(K14<>"To Do",L14<>"Sí"),"⚠ pasó a Doing sin DoR",IF(AND(K14="Done",O14<>"Sí"),"⚠ Done sin criterio cumplido",IF(AND(K14="Doing",COUNTIFS($G$6:$G$266,G14,$K$6:$K$266,"Doing",$E$6:$E$266,"<>Scrum")>2,E14<>"Scrum"),"⚠ más de 2 en Doing","ok"))) | S14: =IF($K14="To Do",COUNTIF($K$6:$K14,"To Do"),"") | T14: =IF($K14="Doing",COUNTIF($K$6:$K14,"Doing"),"") | U14: =IF($K14="Done",COUNTIF($K$6:$K14,"Done"),"")
B15: T-010 | C15: HU-03 | D15: Reportar la obra en semanas | E15: Diseño UI | F15: Diseñar la interfaz de usuario de HU-03: pantalla 9 · Crear la obra y 22 · Detalle de la obra | G15: Fernando | H15: 1 | I15: 23/10 | K15: Done | L15: Sí | M15: 22/10/2026 | N15: Mockup en el lienzo, revisado por el equipo | O15: Sí | P15: 22/10/2026 | Q15: Lienzo «SIGRO · Pantallas y diagramas del Sprint 1» | R15: =IF(AND(K15<>"To Do",L15<>"Sí"),"⚠ pasó a Doing sin DoR",IF(AND(K15="Done",O15<>"Sí"),"⚠ Done sin criterio cumplido",IF(AND(K15="Doing",COUNTIFS($G$6:$G$266,G15,$K$6:$K$266,"Doing",$E$6:$E$266,"<>Scrum")>2,E15<>"Scrum"),"⚠ más de 2 en Doing","ok"))) | S15: =IF($K15="To Do",COUNTIF($K$6:$K15,"To Do"),"") | T15: =IF($K15="Doing",COUNTIF($K$6:$K15,"Doing"),"") | U15: =IF($K15="Done",COUNTIF($K$6:$K15,"Done"),"")
B16: T-011 | C16: HU-03 | D16: Reportar la obra en semanas | E16: Modelado UML | F16: Modelar la funcionalidad de HU-03 con el diagrama UML de actividades de la generación de semanas | G16: Fernando | H16: 1 | I16: 24/10 | J16: T-010 | K16: To Do | N16: Diagrama publicado en el repo o el lienzo | R16: =IF(AND(K16<>"To Do",L16<>"Sí"),"⚠ pasó a Doing sin DoR",IF(AND(K16="Done",O16<>"Sí"),"⚠ Done sin criterio cumplido",IF(AND(K16="Doing",COUNTIFS($G$6:$G$266,G16,$K$6:$K$266,"Doing",$E$6:$E$266,"<>Scrum")>2,E16<>"Scrum"),"⚠ más de 2 en Doing","ok"))) | S16: =IF($K16="To Do",COUNTIF($K$6:$K16,"To Do"),"") | T16: =IF($K16="Doing",COUNTIF($K$6:$K16,"Doing"),"") | U16: =IF($K16="Done",COUNTIF($K$6:$K16,"Done"),"")
B17: T-012 | C17: HU-03 | D17: Reportar la obra en semanas | E17: Base de datos | F17: Implementar las tablas asociadas a HU-03: periodo | G17: Adiel | H17: 1 | I17: 24/10 | K17: Done | L17: Sí | M17: 22/10/2026 | N17: Migración fusionada, corre en base limpia y con datos, y se revierte | O17: Sí | P17: 22/10/2026 | Q17: PR #1 de Adiel (22/10) | R17: =IF(AND(K17<>"To Do",L17<>"Sí"),"⚠ pasó a Doing sin DoR",IF(AND(K17="Done",O17<>"Sí"),"⚠ Done sin criterio cumplido",IF(AND(K17="Doing",COUNTIFS($G$6:$G$266,G17,$K$6:$K$266,"Doing",$E$6:$E$266,"<>Scrum")>2,E17<>"Scrum"),"⚠ más de 2 en Doing","ok"))) | S17: =IF($K17="To Do",COUNTIF($K$6:$K17,"To Do"),"") | T17: =IF($K17="Doing",COUNTIF($K$6:$K17,"Doing"),"") | U17: =IF($K17="Done",COUNTIF($K$6:$K17,"Done"),"")
B18: T-013 | C18: HU-03 | D18: Reportar la obra en semanas | E18: Backend | F18: Programar el back-end de HU-03 (entidad, repositorio, servicio y controlador): la generación automática de semanas al crear la obra y al ampliar el plazo, con sus pruebas | G18: Adiel | H18: 2 | I18: 25/10 | K18: Done | L18: Sí | M18: 22/10/2026 | N18: PR fusionado con sus pruebas automáticas en verde y el endpoint documentado | O18: Sí | P18: 22/10/2026 | Q18: PR #1 y #2 de Adiel (22/10) | R18: =IF(AND(K18<>"To Do",L18<>"Sí"),"⚠ pasó a Doing sin DoR",IF(AND(K18="Done",O18<>"Sí"),"⚠ Done sin criterio cumplido",IF(AND(K18="Doing",COUNTIFS($G$6:$G$266,G18,$K$6:$K$266,"Doing",$E$6:$E$266,"<>Scrum")>2,E18<>"Scrum"),"⚠ más de 2 en Doing","ok"))) | S18: =IF($K18="To Do",COUNTIF($K$6:$K18,"To Do"),"") | T18: =IF($K18="Doing",COUNTIF($K$6:$K18,"Doing"),"") | U18: =IF($K18="Done",COUNTIF($K$6:$K18,"Done"),"")
B19: T-014 | C19: HU-03 | D19: Reportar la obra en semanas | E19: Front-end web | F19: Programar la tira de semanas en la web (cerrada, en curso, por venir) | G19: Fernando | H19: 2 | I19: 26/10 | K19: Done | L19: Sí | M19: 22/10/2026 | N19: PR fusionado, build sin errores, modo claro/oscuro y escala 125 % | O19: Sí | P19: 22/10/2026 | Q19: Commit del 22/10 09:30 (datos simulados) | R19: =IF(AND(K19<>"To Do",L19<>"Sí"),"⚠ pasó a Doing sin DoR",IF(AND(K19="Done",O19<>"Sí"),"⚠ Done sin criterio cumplido",IF(AND(K19="Doing",COUNTIFS($G$6:$G$266,G19,$K$6:$K$266,"Doing",$E$6:$E$266,"<>Scrum")>2,E19<>"Scrum"),"⚠ más de 2 en Doing","ok"))) | S19: =IF($K19="To Do",COUNTIF($K$6:$K19,"To Do"),"") | T19: =IF($K19="Doing",COUNTIF($K$6:$K19,"Doing"),"") | U19: =IF($K19="Done",COUNTIF($K$6:$K19,"Done"),"")
B20: T-015 | C20: HU-03 | D20: Reportar la obra en semanas | E20: Conexión API | F20: Conectar la tira de semanas con la API real | G20: Fernando | H20: 2 | I20: 26/10 | J20: T-013, T-014, T-240 | K20: To Do | N20: La pantalla muestra los datos reales del servidor y sus errores | R20: =IF(AND(K20<>"To Do",L20<>"Sí"),"⚠ pasó a Doing sin DoR",IF(AND(K20="Done",O20<>"Sí"),"⚠ Done sin criterio cumplido",IF(AND(K20="Doing",COUNTIFS($G$6:$G$266,G20,$K$6:$K$266,"Doing",$E$6:$E$266,"<>Scrum")>2,E20<>"Scrum"),"⚠ más de 2 en Doing","ok"))) | S20: =IF($K20="To Do",COUNTIF($K$6:$K20,"To Do"),"") | T20: =IF($K20="Doing",COUNTIF($K$6:$K20,"Doing"),"") | U20: =IF($K20="Done",COUNTIF($K$6:$K20,"Done"),"")
B21: T-016 | C21: HU-03 | D21: Reportar la obra en semanas | E21: Pruebas | F21: Probar la funcionalidad de HU-03 (la API con Postman y la pantalla web) contra cada condición final y aprobar su PR | G21: Henry | H21: 1 | I21: 27/10 | J21: T-012, T-013, T-014, T-015, T-233 | K21: To Do | N21: Cada condición final verificada con Postman y en la interfaz; PR aprobado por alguien distinto del autor | R21: =IF(AND(K21<>"To Do",L21<>"Sí"),"⚠ pasó a Doing sin DoR",IF(AND(K21="Done",O21<>"Sí"),"⚠ Done sin criterio cumplido",IF(AND(K21="Doing",COUNTIFS($G$6:$G$266,G21,$K$6:$K$266,"Doing",$E$6:$E$266,"<>Scrum")>2,E21<>"Scrum"),"⚠ más de 2 en Doing","ok"))) | S21: =IF($K21="To Do",COUNTIF($K$6:$K21,"To Do"),"") | T21: =IF($K21="Doing",COUNTIF($K$6:$K21,"Doing"),"") | U21: =IF($K21="Done",COUNTIF($K$6:$K21,"Done"),"")
B22: T-017 | C22: HU-03 | D22: Reportar la obra en semanas | E22: Aceptación | F22: Aceptar HU-03 como Product Owner desde la interfaz y moverla a Done | G22: Adiel | H22: 0.5 | I22: 27/10 | J22: T-016 | K22: To Do | N22: DoD T1–T10 + condiciones finales aceptadas por el PO → la HU pasa a Done | R22: =IF(AND(K22<>"To Do",L22<>"Sí"),"⚠ pasó a Doing sin DoR",IF(AND(K22="Done",O22<>"Sí"),"⚠ Done sin criterio cumplido",IF(AND(K22="Doing",COUNTIFS($G$6:$G$266,G22,$K$6:$K$266,"Doing",$E$6:$E$266,"<>Scrum")>2,E22<>"Scrum"),"⚠ más de 2 en Doing","ok"))) | S22: =IF($K22="To Do",COUNTIF($K$6:$K22,"To Do"),"") | T22: =IF($K22="Doing",COUNTIF($K$6:$K22,"Doing"),"") | U22: =IF($K22="Done",COUNTIF($K$6:$K22,"Done"),"")
B23: T-018 | C23: HU-07 | D23: Importar catálogo de insumos del S10 | E23: Diseño UI | F23: Diseñar la interfaz de usuario de HU-07: pantalla 11 · Importar el catálogo del S10 | G23: Fernando | H23: 1 | I23: 23/10 | K23: Done | L23: Sí | M23: 22/10/2026 | N23: Mockup en el lienzo, revisado por el equipo | O23: Sí | P23: 22/10/2026 | Q23: Lienzo «SIGRO · Pantallas y diagramas del Sprint 1» | R23: =IF(AND(K23<>"To Do",L23<>"Sí"),"⚠ pasó a Doing sin DoR",IF(AND(K23="Done",O23<>"Sí"),"⚠ Done sin criterio cumplido",IF(AND(K23="Doing",COUNTIFS($G$6:$G$266,G23,$K$6:$K$266,"Doing",$E$6:$E$266,"<>Scrum")>2,E23<>"Scrum"),"⚠ más de 2 en Doing","ok"))) | S23: =IF($K23="To Do",COUNTIF($K$6:$K23,"To Do"),"") | T23: =IF($K23="Doing",COUNTIF($K$6:$K23,"Doing"),"") | U23: =IF($K23="Done",COUNTIF($K$6:$K23,"Done"),"")
B24: T-019 | C24: HU-07 | D24: Importar catálogo de insumos del S10 | E24: Modelado UML | F24: Modelar la funcionalidad de HU-07 con el diagrama UML de secuencia de la importación del S10 por el microservicio | G24: Fernando | H24: 1 | I24: 24/10 | K24: Done | L24: Sí | M24: 22/10/2026 | N24: Diagrama publicado en el repo o el lienzo | O24: Sí | P24: 22/10/2026 | Q24: Lienzo del Sprint 1 | R24: =IF(AND(K24<>"To Do",L24<>"Sí"),"⚠ pasó a Doing sin DoR",IF(AND(K24="Done",O24<>"Sí"),"⚠ Done sin criterio cumplido",IF(AND(K24="Doing",COUNTIFS($G$6:$G$266,G24,$K$6:$K$266,"Doing",$E$6:$E$266,"<>Scrum")>2,E24<>"Scrum"),"⚠ más de 2 en Doing","ok"))) | S24: =IF($K24="To Do",COUNTIF($K$6:$K24,"To Do"),"") | T24: =IF($K24="Doing",COUNTIF($K$6:$K24,"Doing"),"") | U24: =IF($K24="Done",COUNTIF($K$6:$K24,"Done"),"")
B25: T-020 | C25: HU-07 | D25: Importar catálogo de insumos del S10 | E25: Base de datos | F25: Implementar las tablas asociadas a HU-07: insumo (crear/actualizar por código) | G25: Adiel | H25: 1 | I25: 24/10 | J25: T-019 | K25: To Do | N25: Migración fusionada, corre en base limpia y con datos, y se revierte | R25: =IF(AND(K25<>"To Do",L25<>"Sí"),"⚠ pasó a Doing sin DoR",IF(AND(K25="Done",O25<>"Sí"),"⚠ Done sin criterio cumplido",IF(AND(K25="Doing",COUNTIFS($G$6:$G$266,G25,$K$6:$K$266,"Doing",$E$6:$E$266,"<>Scrum")>2,E25<>"Scrum"),"⚠ más de 2 en Doing","ok"))) | S25: =IF($K25="To Do",COUNTIF($K$6:$K25,"To Do"),"") | T25: =IF($K25="Doing",COUNTIF($K$6:$K25,"Doing"),"") | U25: =IF($K25="Done",COUNTIF($K$6:$K25,"Done"),"")
B26: T-021 | C26: HU-07 | D26: Importar catálogo de insumos del S10 | E26: Backend | F26: Programar el back-end de HU-07 (entidad, repositorio, servicio y controlador): el endpoint que aplica la importación: crear o actualizar insumos por código sin tocar saldos | G26: Adiel | H26: 4 | I26: 25/10 | J26: T-020 | K26: To Do | N26: PR fusionado con sus pruebas automáticas en verde y el endpoint documentado | R26: =IF(AND(K26<>"To Do",L26<>"Sí"),"⚠ pasó a Doing sin DoR",IF(AND(K26="Done",O26<>"Sí"),"⚠ Done sin criterio cumplido",IF(AND(K26="Doing",COUNTIFS($G$6:$G$266,G26,$K$6:$K$266,"Doing",$E$6:$E$266,"<>Scrum")>2,E26<>"Scrum"),"⚠ más de 2 en Doing","ok"))) | S26: =IF($K26="To Do",COUNTIF($K$6:$K26,"To Do"),"") | T26: =IF($K26="Doing",COUNTIF($K$6:$K26,"Doing"),"") | U26: =IF($K26="Done",COUNTIF($K$6:$K26,"Done"),"")
B27: T-022 | C27: HU-07 | D27: Importar catálogo de insumos del S10 | E27: Backend | F27: Configurar la llamada de la API a Integraciones con el token de servicio en docker compose | G27: Adiel | H27: 4 | I27: 25/10 | J27: T-020 | K27: To Do | N27: PR fusionado con sus pruebas automáticas en verde y el endpoint documentado | R27: =IF(AND(K27<>"To Do",L27<>"Sí"),"⚠ pasó a Doing sin DoR",IF(AND(K27="Done",O27<>"Sí"),"⚠ Done sin criterio cumplido",IF(AND(K27="Doing",COUNTIFS($G$6:$G$266,G27,$K$6:$K$266,"Doing",$E$6:$E$266,"<>Scrum")>2,E27<>"Scrum"),"⚠ más de 2 en Doing","ok"))) | S27: =IF($K27="To Do",COUNTIF($K$6:$K27,"To Do"),"") | T27: =IF($K27="Doing",COUNTIF($K$6:$K27,"Doing"),"") | U27: =IF($K27="Done",COUNTIF($K$6:$K27,"Done"),"")
B28: T-023 | C28: HU-07 | D28: Importar catálogo de insumos del S10 | E28: Integración | F28: Programar el lector del PDF «Relación de insumos» del S10 en el microservicio — integración con S10 (relación de insumos) | G28: Fernando | H28: 4 | I28: 25/10 | K28: Done | L28: Sí | M28: 22/10/2026 | N28: Probado con el archivo o servicio real, PR fusionado | O28: Sí | P28: 22/10/2026 | Q28: Commit del 22/10 09:30 | R28: =IF(AND(K28<>"To Do",L28<>"Sí"),"⚠ pasó a Doing sin DoR",IF(AND(K28="Done",O28<>"Sí"),"⚠ Done sin criterio cumplido",IF(AND(K28="Doing",COUNTIFS($G$6:$G$266,G28,$K$6:$K$266,"Doing",$E$6:$E$266,"<>Scrum")>2,E28<>"Scrum"),"⚠ más de 2 en Doing","ok"))) | S28: =IF($K28="To Do",COUNTIF($K$6:$K28,"To Do"),"") | T28: =IF($K28="Doing",COUNTIF($K$6:$K28,"Doing"),"") | U28: =IF($K28="Done",COUNTIF($K$6:$K28,"Done"),"")
B29: T-024 | C29: HU-07 | D29: Importar catálogo de insumos del S10 | E29: Front-end web | F29: Programar la pantalla web «Importar del S10» con el resumen de creados, actualizados y fallidos | G29: Fernando | H29: 4 | I29: 26/10 | K29: Done | L29: Sí | M29: 22/10/2026 | N29: PR fusionado, build sin errores, modo claro/oscuro y escala 125 % | O29: Sí | P29: 22/10/2026 | Q29: Commit del 22/10 09:30 | R29: =IF(AND(K29<>"To Do",L29<>"Sí"),"⚠ pasó a Doing sin DoR",IF(AND(K29="Done",O29<>"Sí"),"⚠ Done sin criterio cumplido",IF(AND(K29="Doing",COUNTIFS($G$6:$G$266,G29,$K$6:$K$266,"Doing",$E$6:$E$266,"<>Scrum")>2,E29<>"Scrum"),"⚠ más de 2 en Doing","ok"))) | S29: =IF($K29="To Do",COUNTIF($K$6:$K29,"To Do"),"") | T29: =IF($K29="Doing",COUNTIF($K$6:$K29,"Doing"),"") | U29: =IF($K29="Done",COUNTIF($K$6:$K29,"Done"),"")
B30: T-025 | C30: HU-07 | D30: Importar catálogo de insumos del S10 | E30: Pruebas | F30: Probar la funcionalidad de HU-07 (la API con Postman y la pantalla web) contra cada condición final y aprobar su PR | G30: Henry | H30: 1 | I30: 27/10 | J30: T-020, T-021, T-022, T-023, T-024, T-233 | K30: To Do | N30: Cada condición final verificada con Postman y en la interfaz; PR aprobado por alguien distinto del autor | R30: =IF(AND(K30<>"To Do",L30<>"Sí"),"⚠ pasó a Doing sin DoR",IF(AND(K30="Done",O30<>"Sí"),"⚠ Done sin criterio cumplido",IF(AND(K30="Doing",COUNTIFS($G$6:$G$266,G30,$K$6:$K$266,"Doing",$E$6:$E$266,"<>Scrum")>2,E30<>"Scrum"),"⚠ más de 2 en Doing","ok"))) | S30: =IF($K30="To Do",COUNTIF($K$6:$K30,"To Do"),"") | T30: =IF($K30="Doing",COUNTIF($K$6:$K30,"Doing"),"") | U30: =IF($K30="Done",COUNTIF($K$6:$K30,"Done"),"")
B31: T-026 | C31: HU-07 | D31: Importar catálogo de insumos del S10 | E31: Aceptación | F31: Aceptar HU-07 como Product Owner desde la interfaz y moverla a Done | G31: Adiel | H31: 0.5 | I31: 27/10 | J31: T-025 | K31: To Do | N31: DoD T1–T10 + condiciones finales aceptadas por el PO → la HU pasa a Done | R31: =IF(AND(K31<>"To Do",L31<>"Sí"),"⚠ pasó a Doing sin DoR",IF(AND(K31="Done",O31<>"Sí"),"⚠ Done sin criterio cumplido",IF(AND(K31="Doing",COUNTIFS($G$6:$G$266,G31,$K$6:$K$266,"Doing",$E$6:$E$266,"<>Scrum")>2,E31<>"Scrum"),"⚠ más de 2 en Doing","ok"))) | S31: =IF($K31="To Do",COUNTIF($K$6:$K31,"To Do"),"") | T31: =IF($K31="Doing",COUNTIF($K$6:$K31,"Doing"),"") | U31: =IF($K31="Done",COUNTIF($K$6:$K31,"Done"),"")
B32: T-027 | C32: HU-08 | D32: Registrar insumos | E32: Diseño UI | F32: Diseñar la interfaz de usuario de HU-08: pantalla 16 · Catálogo e insumo | G32: Fernando | H32: 1 | I32: 23/10 | K32: Done | L32: Sí | M32: 22/10/2026 | N32: Mockup en el lienzo, revisado por el equipo | O32: Sí | P32: 22/10/2026 | Q32: Lienzo «SIGRO · Pantallas y diagramas del Sprint 1» | R32: =IF(AND(K32<>"To Do",L32<>"Sí"),"⚠ pasó a Doing sin DoR",IF(AND(K32="Done",O32<>"Sí"),"⚠ Done sin criterio cumplido",IF(AND(K32="Doing",COUNTIFS($G$6:$G$266,G32,$K$6:$K$266,"Doing",$E$6:$E$266,"<>Scrum")>2,E32<>"Scrum"),"⚠ más de 2 en Doing","ok"))) | S32: =IF($K32="To Do",COUNTIF($K$6:$K32,"To Do"),"") | T32: =IF($K32="Doing",COUNTIF($K$6:$K32,"Doing"),"") | U32: =IF($K32="Done",COUNTIF($K$6:$K32,"Done"),"")
B33: T-028 | C33: HU-08 | D33: Registrar insumos | E33: Modelado UML | F33: Modelar la funcionalidad de HU-08 con el diagrama UML de secuencia del alta de insumo con verificación de duplicado | G33: Fernando | H33: 1 | I33: 24/10 | J33: T-027 | K33: To Do | N33: Diagrama publicado en el repo o el lienzo | R33: =IF(AND(K33<>"To Do",L33<>"Sí"),"⚠ pasó a Doing sin DoR",IF(AND(K33="Done",O33<>"Sí"),"⚠ Done sin criterio cumplido",IF(AND(K33="Doing",COUNTIFS($G$6:$G$266,G33,$K$6:$K$266,"Doing",$E$6:$E$266,"<>Scrum")>2,E33<>"Scrum"),"⚠ más de 2 en Doing","ok"))) | S33: =IF($K33="To Do",COUNTIF($K$6:$K33,"To Do"),"") | T33: =IF($K33="Doing",COUNTIF($K$6:$K33,"Doing"),"") | U33: =IF($K33="Done",COUNTIF($K$6:$K33,"Done"),"")
B34: T-029 | C34: HU-08 | D34: Registrar insumos | E34: Base de datos | F34: Implementar las tablas asociadas a HU-08: insumo, insumo_nombre_comercial | G34: Adiel | H34: 1 | I34: 24/10 | J34: T-028 | K34: To Do | N34: Migración fusionada, corre en base limpia y con datos, y se revierte | R34: =IF(AND(K34<>"To Do",L34<>"Sí"),"⚠ pasó a Doing sin DoR",IF(AND(K34="Done",O34<>"Sí"),"⚠ Done sin criterio cumplido",IF(AND(K34="Doing",COUNTIFS($G$6:$G$266,G34,$K$6:$K$266,"Doing",$E$6:$E$266,"<>Scrum")>2,E34<>"Scrum"),"⚠ más de 2 en Doing","ok"))) | S34: =IF($K34="To Do",COUNTIF($K$6:$K34,"To Do"),"") | T34: =IF($K34="Doing",COUNTIF($K$6:$K34,"Doing"),"") | U34: =IF($K34="Done",COUNTIF($K$6:$K34,"Done"),"")
B35: T-030 | C35: HU-08 | D35: Registrar insumos | E35: Backend | F35: Programar el back-end de HU-08 (entidad, repositorio, servicio y controlador): el endpoint del catálogo: generar código único, rechazar duplicados y marcar «por verificar» | G35: Adiel | H35: 3 | I35: 25/10 | J35: T-029 | K35: To Do | N35: PR fusionado con sus pruebas automáticas en verde y el endpoint documentado | R35: =IF(AND(K35<>"To Do",L35<>"Sí"),"⚠ pasó a Doing sin DoR",IF(AND(K35="Done",O35<>"Sí"),"⚠ Done sin criterio cumplido",IF(AND(K35="Doing",COUNTIFS($G$6:$G$266,G35,$K$6:$K$266,"Doing",$E$6:$E$266,"<>Scrum")>2,E35<>"Scrum"),"⚠ más de 2 en Doing","ok"))) | S35: =IF($K35="To Do",COUNTIF($K$6:$K35,"To Do"),"") | T35: =IF($K35="Doing",COUNTIF($K$6:$K35,"Doing"),"") | U35: =IF($K35="Done",COUNTIF($K$6:$K35,"Done"),"")
B36: T-031 | C36: HU-08 | D36: Registrar insumos | E36: Front-end web | F36: Programar la pantalla web del catálogo para ver, dar de alta y editar insumos | G36: Fernando | H36: 3 | I36: 26/10 | K36: Done | L36: Sí | M36: 22/10/2026 | N36: PR fusionado, build sin errores, modo claro/oscuro y escala 125 % | O36: Sí | P36: 22/10/2026 | Q36: Commit del 22/10 09:30 (datos simulados) | R36: =IF(AND(K36<>"To Do",L36<>"Sí"),"⚠ pasó a Doing sin DoR",IF(AND(K36="Done",O36<>"Sí"),"⚠ Done sin criterio cumplido",IF(AND(K36="Doing",COUNTIFS($G$6:$G$266,G36,$K$6:$K$266,"Doing",$E$6:$E$266,"<>Scrum")>2,E36<>"Scrum"),"⚠ más de 2 en Doing","ok"))) | S36: =IF($K36="To Do",COUNTIF($K$6:$K36,"To Do"),"") | T36: =IF($K36="Doing",COUNTIF($K$6:$K36,"Doing"),"") | U36: =IF($K36="Done",COUNTIF($K$6:$K36,"Done"),"")
B37: T-032 | C37: HU-08 | D37: Registrar insumos | E37: Conexión API | F37: Conectar la pantalla del catálogo con la API real | G37: Fernando | H37: 3 | I37: 26/10 | J37: T-030, T-031, T-240 | K37: To Do | N37: La pantalla muestra los datos reales del servidor y sus errores | R37: =IF(AND(K37<>"To Do",L37<>"Sí"),"⚠ pasó a Doing sin DoR",IF(AND(K37="Done",O37<>"Sí"),"⚠ Done sin criterio cumplido",IF(AND(K37="Doing",COUNTIFS($G$6:$G$266,G37,$K$6:$K$266,"Doing",$E$6:$E$266,"<>Scrum")>2,E37<>"Scrum"),"⚠ más de 2 en Doing","ok"))) | S37: =IF($K37="To Do",COUNTIF($K$6:$K37,"To Do"),"") | T37: =IF($K37="Doing",COUNTIF($K$6:$K37,"Doing"),"") | U37: =IF($K37="Done",COUNTIF($K$6:$K37,"Done"),"")
B38: T-033 | C38: HU-08 | D38: Registrar insumos | E38: Pruebas | F38: Probar la funcionalidad de HU-08 (la API con Postman y la pantalla web) contra cada condición final y aprobar su PR | G38: Henry | H38: 1 | I38: 27/10 | J38: T-029, T-030, T-031, T-032, T-233 | K38: To Do | N38: Cada condición final verificada con Postman y en la interfaz; PR aprobado por alguien distinto del autor | R38: =IF(AND(K38<>"To Do",L38<>"Sí"),"⚠ pasó a Doing sin DoR",IF(AND(K38="Done",O38<>"Sí"),"⚠ Done sin criterio cumplido",IF(AND(K38="Doing",COUNTIFS($G$6:$G$266,G38,$K$6:$K$266,"Doing",$E$6:$E$266,"<>Scrum")>2,E38<>"Scrum"),"⚠ más de 2 en Doing","ok"))) | S38: =IF($K38="To Do",COUNTIF($K$6:$K38,"To Do"),"") | T38: =IF($K38="Doing",COUNTIF($K$6:$K38,"Doing"),"") | U38: =IF($K38="Done",COUNTIF($K$6:$K38,"Done"),"")
B39: T-034 | C39: HU-08 | D39: Registrar insumos | E39: Aceptación | F39: Aceptar HU-08 como Product Owner desde la interfaz y moverla a Done | G39: Adiel | H39: 0.5 | I39: 27/10 | J39: T-033 | K39: To Do | N39: DoD T1–T10 + condiciones finales aceptadas por el PO → la HU pasa a Done | R39: =IF(AND(K39<>"To Do",L39<>"Sí"),"⚠ pasó a Doing sin DoR",IF(AND(K39="Done",O39<>"Sí"),"⚠ Done sin criterio cumplido",IF(AND(K39="Doing",COUNTIFS($G$6:$G$266,G39,$K$6:$K$266,"Doing",$E$6:$E$266,"<>Scrum")>2,E39<>"Scrum"),"⚠ más de 2 en Doing","ok"))) | S39: =IF($K39="To Do",COUNTIF($K$6:$K39,"To Do"),"") | T39: =IF($K39="Doing",COUNTIF($K$6:$K39,"Doing"),"") | U39: =IF($K39="Done",COUNTIF($K$6:$K39,"Done"),"")
B40: T-035 | C40: HU-12 | D40: Loguear usuario | E40: Diseño UI | F40: Diseñar la interfaz de usuario de HU-12: pantalla 1 (app) y 20 (web) · Login | G40: Fernando | H40: 1 | I40: 23/10 | K40: Done | L40: Sí | M40: 22/10/2026 | N40: Mockup en el lienzo, revisado por el equipo | O40: Sí | P40: 22/10/2026 | Q40: Lienzo «SIGRO · Pantallas y diagramas del Sprint 1» | R40: =IF(AND(K40<>"To Do",L40<>"Sí"),"⚠ pasó a Doing sin DoR",IF(AND(K40="Done",O40<>"Sí"),"⚠ Done sin criterio cumplido",IF(AND(K40="Doing",COUNTIFS($G$6:$G$266,G40,$K$6:$K$266,"Doing",$E$6:$E$266,"<>Scrum")>2,E40<>"Scrum"),"⚠ más de 2 en Doing","ok"))) | S40: =IF($K40="To Do",COUNTIF($K$6:$K40,"To Do"),"") | T40: =IF($K40="Doing",COUNTIF($K$6:$K40,"Doing"),"") | U40: =IF($K40="Done",COUNTIF($K$6:$K40,"Done"),"")
B41: T-036 | C41: HU-12 | D41: Loguear usuario | E41: Modelado UML | F41: Modelar la funcionalidad de HU-12 con el diagrama UML de secuencia del login y la renovación de la sesión | G41: Nicolás | H41: 1 | I41: 24/10 | J41: T-035 | K41: To Do | N41: Diagrama publicado en el repo o el lienzo | R41: =IF(AND(K41<>"To Do",L41<>"Sí"),"⚠ pasó a Doing sin DoR",IF(AND(K41="Done",O41<>"Sí"),"⚠ Done sin criterio cumplido",IF(AND(K41="Doing",COUNTIFS($G$6:$G$266,G41,$K$6:$K$266,"Doing",$E$6:$E$266,"<>Scrum")>2,E41<>"Scrum"),"⚠ más de 2 en Doing","ok"))) | S41: =IF($K41="To Do",COUNTIF($K$6:$K41,"To Do"),"") | T41: =IF($K41="Doing",COUNTIF($K$6:$K41,"Doing"),"") | U41: =IF($K41="Done",COUNTIF($K$6:$K41,"Done"),"")
B42: T-037 | C42: HU-12 | D42: Loguear usuario | E42: Base de datos | F42: Implementar las tablas asociadas a HU-12: usuario (hash de la clave, intentos, estado) | G42: Adiel | H42: 1 | I42: 24/10 | K42: Done | L42: Sí | M42: 22/10/2026 | N42: Migración fusionada, corre en base limpia y con datos, y se revierte | O42: Sí | P42: 22/10/2026 | Q42: PR #1 de Adiel (22/10) | R42: =IF(AND(K42<>"To Do",L42<>"Sí"),"⚠ pasó a Doing sin DoR",IF(AND(K42="Done",O42<>"Sí"),"⚠ Done sin criterio cumplido",IF(AND(K42="Doing",COUNTIFS($G$6:$G$266,G42,$K$6:$K$266,"Doing",$E$6:$E$266,"<>Scrum")>2,E42<>"Scrum"),"⚠ más de 2 en Doing","ok"))) | S42: =IF($K42="To Do",COUNTIF($K$6:$K42,"To Do"),"") | T42: =IF($K42="Doing",COUNTIF($K$6:$K42,"Doing"),"") | U42: =IF($K42="Done",COUNTIF($K$6:$K42,"Done"),"")
B43: T-038 | C43: HU-12 | D43: Loguear usuario | E43: Backend | F43: Programar el back-end de HU-12 (entidad, repositorio, servicio y controlador): el login con Argon2id, sesión que caduca y se renueva, y bloqueo por intentos fallidos | G43: Adiel | H43: 3 | I43: 25/10 | K43: Done | L43: Sí | M43: 22/10/2026 | N43: PR fusionado con sus pruebas automáticas en verde y el endpoint documentado | O43: Sí | P43: 22/10/2026 | Q43: PR #1 y #2 de Adiel (22/10) | R43: =IF(AND(K43<>"To Do",L43<>"Sí"),"⚠ pasó a Doing sin DoR",IF(AND(K43="Done",O43<>"Sí"),"⚠ Done sin criterio cumplido",IF(AND(K43="Doing",COUNTIFS($G$6:$G$266,G43,$K$6:$K$266,"Doing",$E$6:$E$266,"<>Scrum")>2,E43<>"Scrum"),"⚠ más de 2 en Doing","ok"))) | S43: =IF($K43="To Do",COUNTIF($K$6:$K43,"To Do"),"") | T43: =IF($K43="Doing",COUNTIF($K$6:$K43,"Doing"),"") | U43: =IF($K43="Done",COUNTIF($K$6:$K43,"Done"),"")
B44: T-039 | C44: HU-12 | D44: Loguear usuario | E44: Front-end web | F44: Programar la pantalla web de login y el manejo de la sesión | G44: Henry | H44: 3 | I44: 26/10 | J44: T-035 | K44: To Do | N44: PR fusionado, build sin errores, modo claro/oscuro y escala 125 % | R44: =IF(AND(K44<>"To Do",L44<>"Sí"),"⚠ pasó a Doing sin DoR",IF(AND(K44="Done",O44<>"Sí"),"⚠ Done sin criterio cumplido",IF(AND(K44="Doing",COUNTIFS($G$6:$G$266,G44,$K$6:$K$266,"Doing",$E$6:$E$266,"<>Scrum")>2,E44<>"Scrum"),"⚠ más de 2 en Doing","ok"))) | S44: =IF($K44="To Do",COUNTIF($K$6:$K44,"To Do"),"") | T44: =IF($K44="Doing",COUNTIF($K$6:$K44,"Doing"),"") | U44: =IF($K44="Done",COUNTIF($K$6:$K44,"Done"),"")
B45: T-040 | C45: HU-12 | D45: Loguear usuario | E45: Front-end app | F45: Programar el login en la app del almacenero | G45: Nicolás | H45: 3 | I45: 26/10 | J45: T-035, T-242 | K45: To Do | N45: PR fusionado; lo que registra movimientos probado en modo avión | R45: =IF(AND(K45<>"To Do",L45<>"Sí"),"⚠ pasó a Doing sin DoR",IF(AND(K45="Done",O45<>"Sí"),"⚠ Done sin criterio cumplido",IF(AND(K45="Doing",COUNTIFS($G$6:$G$266,G45,$K$6:$K$266,"Doing",$E$6:$E$266,"<>Scrum")>2,E45<>"Scrum"),"⚠ más de 2 en Doing","ok"))) | S45: =IF($K45="To Do",COUNTIF($K$6:$K45,"To Do"),"") | T45: =IF($K45="Doing",COUNTIF($K$6:$K45,"Doing"),"") | U45: =IF($K45="Done",COUNTIF($K$6:$K45,"Done"),"")
B46: T-041 | C46: HU-12 | D46: Loguear usuario | E46: Pruebas | F46: Probar la funcionalidad de HU-12 (la API con Postman, la pantalla web y la app) contra cada condición final y aprobar su PR | G46: Fernando | H46: 1 | I46: 27/10 | J46: T-037, T-038, T-039, T-040, T-233 | K46: To Do | N46: Cada condición final verificada con Postman y en la interfaz; PR aprobado por alguien distinto del autor | R46: =IF(AND(K46<>"To Do",L46<>"Sí"),"⚠ pasó a Doing sin DoR",IF(AND(K46="Done",O46<>"Sí"),"⚠ Done sin criterio cumplido",IF(AND(K46="Doing",COUNTIFS($G$6:$G$266,G46,$K$6:$K$266,"Doing",$E$6:$E$266,"<>Scrum")>2,E46<>"Scrum"),"⚠ más de 2 en Doing","ok"))) | S46: =IF($K46="To Do",COUNTIF($K$6:$K46,"To Do"),"") | T46: =IF($K46="Doing",COUNTIF($K$6:$K46,"Doing"),"") | U46: =IF($K46="Done",COUNTIF($K$6:$K46,"Done"),"")
B47: T-042 | C47: HU-12 | D47: Loguear usuario | E47: Aceptación | F47: Aceptar HU-12 como Product Owner desde la interfaz y moverla a Done | G47: Adiel | H47: 0.5 | I47: 27/10 | J47: T-041 | K47: To Do | N47: DoD T1–T10 + condiciones finales aceptadas por el PO → la HU pasa a Done | R47: =IF(AND(K47<>"To Do",L47<>"Sí"),"⚠ pasó a Doing sin DoR",IF(AND(K47="Done",O47<>"Sí"),"⚠ Done sin criterio cumplido",IF(AND(K47="Doing",COUNTIFS($G$6:$G$266,G47,$K$6:$K$266,"Doing",$E$6:$E$266,"<>Scrum")>2,E47<>"Scrum"),"⚠ más de 2 en Doing","ok"))) | S47: =IF($K47="To Do",COUNTIF($K$6:$K47,"To Do"),"") | T47: =IF($K47="Doing",COUNTIF($K$6:$K47,"Doing"),"") | U47: =IF($K47="Done",COUNTIF($K$6:$K47,"Done"),"")
B48: T-043 | C48: HU-13 | D48: Asignar roles | E48: Diseño UI | F48: Diseñar la interfaz de usuario de HU-13: pantalla 10 · Usuarios, roles y dispositivos | G48: Fernando | H48: 1 | I48: 23/10 | K48: Done | L48: Sí | M48: 22/10/2026 | N48: Mockup en el lienzo, revisado por el equipo | O48: Sí | P48: 22/10/2026 | Q48: Lienzo «SIGRO · Pantallas y diagramas del Sprint 1» | R48: =IF(AND(K48<>"To Do",L48<>"Sí"),"⚠ pasó a Doing sin DoR",IF(AND(K48="Done",O48<>"Sí"),"⚠ Done sin criterio cumplido",IF(AND(K48="Doing",COUNTIFS($G$6:$G$266,G48,$K$6:$K$266,"Doing",$E$6:$E$266,"<>Scrum")>2,E48<>"Scrum"),"⚠ más de 2 en Doing","ok"))) | S48: =IF($K48="To Do",COUNTIF($K$6:$K48,"To Do"),"") | T48: =IF($K48="Doing",COUNTIF($K$6:$K48,"Doing"),"") | U48: =IF($K48="Done",COUNTIF($K$6:$K48,"Done"),"")
B49: T-044 | C49: HU-13 | D49: Asignar roles | E49: Modelado UML | F49: Modelar la funcionalidad de HU-13 con el diagrama UML de secuencia de la verificación del permiso en el servidor | G49: Henry | H49: 1 | I49: 24/10 | J49: T-043 | K49: To Do | N49: Diagrama publicado en el repo o el lienzo | R49: =IF(AND(K49<>"To Do",L49<>"Sí"),"⚠ pasó a Doing sin DoR",IF(AND(K49="Done",O49<>"Sí"),"⚠ Done sin criterio cumplido",IF(AND(K49="Doing",COUNTIFS($G$6:$G$266,G49,$K$6:$K$266,"Doing",$E$6:$E$266,"<>Scrum")>2,E49<>"Scrum"),"⚠ más de 2 en Doing","ok"))) | S49: =IF($K49="To Do",COUNTIF($K$6:$K49,"To Do"),"") | T49: =IF($K49="Doing",COUNTIF($K$6:$K49,"Doing"),"") | U49: =IF($K49="Done",COUNTIF($K$6:$K49,"Done"),"")
B50: T-045 | C50: HU-13 | D50: Asignar roles | E50: Base de datos | F50: Implementar las tablas asociadas a HU-13: asignacion (el rol vive aquí, por obra) | G50: Adiel | H50: 1 | I50: 24/10 | K50: Done | L50: Sí | M50: 22/10/2026 | N50: Migración fusionada, corre en base limpia y con datos, y se revierte | O50: Sí | P50: 22/10/2026 | Q50: PR #1 de Adiel (22/10) | R50: =IF(AND(K50<>"To Do",L50<>"Sí"),"⚠ pasó a Doing sin DoR",IF(AND(K50="Done",O50<>"Sí"),"⚠ Done sin criterio cumplido",IF(AND(K50="Doing",COUNTIFS($G$6:$G$266,G50,$K$6:$K$266,"Doing",$E$6:$E$266,"<>Scrum")>2,E50<>"Scrum"),"⚠ más de 2 en Doing","ok"))) | S50: =IF($K50="To Do",COUNTIF($K$6:$K50,"To Do"),"") | T50: =IF($K50="Doing",COUNTIF($K$6:$K50,"Doing"),"") | U50: =IF($K50="Done",COUNTIF($K$6:$K50,"Done"),"")
B51: T-046 | C51: HU-13 | D51: Asignar roles | E51: Backend | F51: Programar el back-end de HU-13 (entidad, repositorio, servicio y controlador): los roles y verificar sus permisos en el servidor | G51: Adiel | H51: 4 | I51: 25/10 | K51: Done | L51: Sí | M51: 22/10/2026 | N51: PR fusionado con sus pruebas automáticas en verde y el endpoint documentado | O51: Sí | P51: 22/10/2026 | Q51: PR #1 y #2 de Adiel (22/10) | R51: =IF(AND(K51<>"To Do",L51<>"Sí"),"⚠ pasó a Doing sin DoR",IF(AND(K51="Done",O51<>"Sí"),"⚠ Done sin criterio cumplido",IF(AND(K51="Doing",COUNTIFS($G$6:$G$266,G51,$K$6:$K$266,"Doing",$E$6:$E$266,"<>Scrum")>2,E51<>"Scrum"),"⚠ más de 2 en Doing","ok"))) | S51: =IF($K51="To Do",COUNTIF($K$6:$K51,"To Do"),"") | T51: =IF($K51="Doing",COUNTIF($K$6:$K51,"Doing"),"") | U51: =IF($K51="Done",COUNTIF($K$6:$K51,"Done"),"")
B52: T-047 | C52: HU-13 | D52: Asignar roles | E52: Front-end web | F52: Programar la pantalla web para crear usuarios, asignar su rol y darlos de baja | G52: Henry | H52: 4 | I52: 26/10 | J52: T-043 | K52: To Do | N52: PR fusionado, build sin errores, modo claro/oscuro y escala 125 % | R52: =IF(AND(K52<>"To Do",L52<>"Sí"),"⚠ pasó a Doing sin DoR",IF(AND(K52="Done",O52<>"Sí"),"⚠ Done sin criterio cumplido",IF(AND(K52="Doing",COUNTIFS($G$6:$G$266,G52,$K$6:$K$266,"Doing",$E$6:$E$266,"<>Scrum")>2,E52<>"Scrum"),"⚠ más de 2 en Doing","ok"))) | S52: =IF($K52="To Do",COUNTIF($K$6:$K52,"To Do"),"") | T52: =IF($K52="Doing",COUNTIF($K$6:$K52,"Doing"),"") | U52: =IF($K52="Done",COUNTIF($K$6:$K52,"Done"),"")
B53: T-048 | C53: HU-13 | D53: Asignar roles | E53: Pruebas | F53: Probar la funcionalidad de HU-13 (la API con Postman y la pantalla web) contra cada condición final y aprobar su PR | G53: Fernando | H53: 1 | I53: 27/10 | J53: T-045, T-046, T-047, T-233 | K53: To Do | N53: Cada condición final verificada con Postman y en la interfaz; PR aprobado por alguien distinto del autor | R53: =IF(AND(K53<>"To Do",L53<>"Sí"),"⚠ pasó a Doing sin DoR",IF(AND(K53="Done",O53<>"Sí"),"⚠ Done sin criterio cumplido",IF(AND(K53="Doing",COUNTIFS($G$6:$G$266,G53,$K$6:$K$266,"Doing",$E$6:$E$266,"<>Scrum")>2,E53<>"Scrum"),"⚠ más de 2 en Doing","ok"))) | S53: =IF($K53="To Do",COUNTIF($K$6:$K53,"To Do"),"") | T53: =IF($K53="Doing",COUNTIF($K$6:$K53,"Doing"),"") | U53: =IF($K53="Done",COUNTIF($K$6:$K53,"Done"),"")
B54: T-049 | C54: HU-13 | D54: Asignar roles | E54: Aceptación | F54: Aceptar HU-13 como Product Owner desde la interfaz y moverla a Done | G54: Adiel | H54: 0.5 | I54: 27/10 | J54: T-048 | K54: To Do | N54: DoD T1–T10 + condiciones finales aceptadas por el PO → la HU pasa a Done | R54: =IF(AND(K54<>"To Do",L54<>"Sí"),"⚠ pasó a Doing sin DoR",IF(AND(K54="Done",O54<>"Sí"),"⚠ Done sin criterio cumplido",IF(AND(K54="Doing",COUNTIFS($G$6:$G$266,G54,$K$6:$K$266,"Doing",$E$6:$E$266,"<>Scrum")>2,E54<>"Scrum"),"⚠ más de 2 en Doing","ok"))) | S54: =IF($K54="To Do",COUNTIF($K$6:$K54,"To Do"),"") | T54: =IF($K54="Doing",COUNTIF($K$6:$K54,"Doing"),"") | U54: =IF($K54="Done",COUNTIF($K$6:$K54,"Done"),"")
B55: T-050 | C55: HU-14 | D55: Asignar usuarios a obras | E55: Diseño UI | F55: Diseñar la interfaz de usuario de HU-14: pantalla 10 · Usuarios, roles y dispositivos | G55: Fernando | H55: 1 | I55: 23/10 | K55: Done | L55: Sí | M55: 22/10/2026 | N55: Mockup en el lienzo, revisado por el equipo | O55: Sí | P55: 22/10/2026 | Q55: Lienzo «SIGRO · Pantallas y diagramas del Sprint 1» | R55: =IF(AND(K55<>"To Do",L55<>"Sí"),"⚠ pasó a Doing sin DoR",IF(AND(K55="Done",O55<>"Sí"),"⚠ Done sin criterio cumplido",IF(AND(K55="Doing",COUNTIFS($G$6:$G$266,G55,$K$6:$K$266,"Doing",$E$6:$E$266,"<>Scrum")>2,E55<>"Scrum"),"⚠ más de 2 en Doing","ok"))) | S55: =IF($K55="To Do",COUNTIF($K$6:$K55,"To Do"),"") | T55: =IF($K55="Doing",COUNTIF($K$6:$K55,"Doing"),"") | U55: =IF($K55="Done",COUNTIF($K$6:$K55,"Done"),"")
B56: T-051 | C56: HU-14 | D56: Asignar usuarios a obras | E56: Modelado UML | F56: Modelar la funcionalidad de HU-14 con el diagrama UML de secuencia de la asignación de usuario a obra | G56: Henry | H56: 1 | I56: 24/10 | J56: T-050 | K56: To Do | N56: Diagrama publicado en el repo o el lienzo | R56: =IF(AND(K56<>"To Do",L56<>"Sí"),"⚠ pasó a Doing sin DoR",IF(AND(K56="Done",O56<>"Sí"),"⚠ Done sin criterio cumplido",IF(AND(K56="Doing",COUNTIFS($G$6:$G$266,G56,$K$6:$K$266,"Doing",$E$6:$E$266,"<>Scrum")>2,E56<>"Scrum"),"⚠ más de 2 en Doing","ok"))) | S56: =IF($K56="To Do",COUNTIF($K$6:$K56,"To Do"),"") | T56: =IF($K56="Doing",COUNTIF($K$6:$K56,"Doing"),"") | U56: =IF($K56="Done",COUNTIF($K$6:$K56,"Done"),"")
B57: T-052 | C57: HU-14 | D57: Asignar usuarios a obras | E57: Base de datos | F57: Implementar las tablas asociadas a HU-14: asignacion | G57: Adiel | H57: 1 | I57: 24/10 | K57: Done | L57: Sí | M57: 22/10/2026 | N57: Migración fusionada, corre en base limpia y con datos, y se revierte | O57: Sí | P57: 22/10/2026 | Q57: PR #1 de Adiel (22/10) | R57: =IF(AND(K57<>"To Do",L57<>"Sí"),"⚠ pasó a Doing sin DoR",IF(AND(K57="Done",O57<>"Sí"),"⚠ Done sin criterio cumplido",IF(AND(K57="Doing",COUNTIFS($G$6:$G$266,G57,$K$6:$K$266,"Doing",$E$6:$E$266,"<>Scrum")>2,E57<>"Scrum"),"⚠ más de 2 en Doing","ok"))) | S57: =IF($K57="To Do",COUNTIF($K$6:$K57,"To Do"),"") | T57: =IF($K57="Doing",COUNTIF($K$6:$K57,"Doing"),"") | U57: =IF($K57="Done",COUNTIF($K$6:$K57,"Done"),"")
B58: T-053 | C58: HU-14 | D58: Asignar usuarios a obras | E58: Backend | F58: Programar el back-end de HU-14 (entidad, repositorio, servicio y controlador): el endpoint para asignar usuarios a obras | G58: Adiel | H58: 2 | I58: 25/10 | K58: Done | L58: Sí | M58: 22/10/2026 | N58: PR fusionado con sus pruebas automáticas en verde y el endpoint documentado | O58: Sí | P58: 22/10/2026 | Q58: PR #1 y #2 de Adiel (22/10) | R58: =IF(AND(K58<>"To Do",L58<>"Sí"),"⚠ pasó a Doing sin DoR",IF(AND(K58="Done",O58<>"Sí"),"⚠ Done sin criterio cumplido",IF(AND(K58="Doing",COUNTIFS($G$6:$G$266,G58,$K$6:$K$266,"Doing",$E$6:$E$266,"<>Scrum")>2,E58<>"Scrum"),"⚠ más de 2 en Doing","ok"))) | S58: =IF($K58="To Do",COUNTIF($K$6:$K58,"To Do"),"") | T58: =IF($K58="Doing",COUNTIF($K$6:$K58,"Doing"),"") | U58: =IF($K58="Done",COUNTIF($K$6:$K58,"Done"),"")
B59: T-054 | C59: HU-14 | D59: Asignar usuarios a obras | E59: Front-end web | F59: Programar la pantalla web para asignar usuarios a obras | G59: Henry | H59: 2 | I59: 26/10 | J59: T-050 | K59: To Do | N59: PR fusionado, build sin errores, modo claro/oscuro y escala 125 % | R59: =IF(AND(K59<>"To Do",L59<>"Sí"),"⚠ pasó a Doing sin DoR",IF(AND(K59="Done",O59<>"Sí"),"⚠ Done sin criterio cumplido",IF(AND(K59="Doing",COUNTIFS($G$6:$G$266,G59,$K$6:$K$266,"Doing",$E$6:$E$266,"<>Scrum")>2,E59<>"Scrum"),"⚠ más de 2 en Doing","ok"))) | S59: =IF($K59="To Do",COUNTIF($K$6:$K59,"To Do"),"") | T59: =IF($K59="Doing",COUNTIF($K$6:$K59,"Doing"),"") | U59: =IF($K59="Done",COUNTIF($K$6:$K59,"Done"),"")
B60: T-055 | C60: HU-14 | D60: Asignar usuarios a obras | E60: Pruebas | F60: Probar la funcionalidad de HU-14 (la API con Postman y la pantalla web) contra cada condición final y aprobar su PR | G60: Fernando | H60: 1 | I60: 27/10 | J60: T-052, T-053, T-054, T-233 | K60: To Do | N60: Cada condición final verificada con Postman y en la interfaz; PR aprobado por alguien distinto del autor | R60: =IF(AND(K60<>"To Do",L60<>"Sí"),"⚠ pasó a Doing sin DoR",IF(AND(K60="Done",O60<>"Sí"),"⚠ Done sin criterio cumplido",IF(AND(K60="Doing",COUNTIFS($G$6:$G$266,G60,$K$6:$K$266,"Doing",$E$6:$E$266,"<>Scrum")>2,E60<>"Scrum"),"⚠ más de 2 en Doing","ok"))) | S60: =IF($K60="To Do",COUNTIF($K$6:$K60,"To Do"),"") | T60: =IF($K60="Doing",COUNTIF($K$6:$K60,"Doing"),"") | U60: =IF($K60="Done",COUNTIF($K$6:$K60,"Done"),"")
B61: T-056 | C61: HU-14 | D61: Asignar usuarios a obras | E61: Aceptación | F61: Aceptar HU-14 como Product Owner desde la interfaz y moverla a Done | G61: Adiel | H61: 0.5 | I61: 27/10 | J61: T-055 | K61: To Do | N61: DoD T1–T10 + condiciones finales aceptadas por el PO → la HU pasa a Done | R61: =IF(AND(K61<>"To Do",L61<>"Sí"),"⚠ pasó a Doing sin DoR",IF(AND(K61="Done",O61<>"Sí"),"⚠ Done sin criterio cumplido",IF(AND(K61="Doing",COUNTIFS($G$6:$G$266,G61,$K$6:$K$266,"Doing",$E$6:$E$266,"<>Scrum")>2,E61<>"Scrum"),"⚠ más de 2 en Doing","ok"))) | S61: =IF($K61="To Do",COUNTIF($K$6:$K61,"To Do"),"") | T61: =IF($K61="Doing",COUNTIF($K$6:$K61,"Doing"),"") | U61: =IF($K61="Done",COUNTIF($K$6:$K61,"Done"),"")
B62: T-057 | C62: HU-15 | D62: Autorizar celular de la obra | E62: Diseño UI | F62: Diseñar la interfaz de usuario de HU-15: pantalla 10 · Usuarios, roles y dispositivos | G62: Fernando | H62: 1 | I62: 23/10 | K62: Done | L62: Sí | M62: 22/10/2026 | N62: Mockup en el lienzo, revisado por el equipo | O62: Sí | P62: 22/10/2026 | Q62: Lienzo «SIGRO · Pantallas y diagramas del Sprint 1» | R62: =IF(AND(K62<>"To Do",L62<>"Sí"),"⚠ pasó a Doing sin DoR",IF(AND(K62="Done",O62<>"Sí"),"⚠ Done sin criterio cumplido",IF(AND(K62="Doing",COUNTIFS($G$6:$G$266,G62,$K$6:$K$266,"Doing",$E$6:$E$266,"<>Scrum")>2,E62<>"Scrum"),"⚠ más de 2 en Doing","ok"))) | S62: =IF($K62="To Do",COUNTIF($K$6:$K62,"To Do"),"") | T62: =IF($K62="Doing",COUNTIF($K$6:$K62,"Doing"),"") | U62: =IF($K62="Done",COUNTIF($K$6:$K62,"Done"),"")
B63: T-058 | C63: HU-15 | D63: Autorizar celular de la obra | E63: Modelado UML | F63: Modelar la funcionalidad de HU-15 con el diagrama UML de secuencia del registro desde un dispositivo no autorizado | G63: Nicolás | H63: 1 | I63: 24/10 | J63: T-057 | K63: To Do | N63: Diagrama publicado en el repo o el lienzo | R63: =IF(AND(K63<>"To Do",L63<>"Sí"),"⚠ pasó a Doing sin DoR",IF(AND(K63="Done",O63<>"Sí"),"⚠ Done sin criterio cumplido",IF(AND(K63="Doing",COUNTIFS($G$6:$G$266,G63,$K$6:$K$266,"Doing",$E$6:$E$266,"<>Scrum")>2,E63<>"Scrum"),"⚠ más de 2 en Doing","ok"))) | S63: =IF($K63="To Do",COUNTIF($K$6:$K63,"To Do"),"") | T63: =IF($K63="Doing",COUNTIF($K$6:$K63,"Doing"),"") | U63: =IF($K63="Done",COUNTIF($K$6:$K63,"Done"),"")
B64: T-059 | C64: HU-15 | D64: Autorizar celular de la obra | E64: Base de datos | F64: Implementar las tablas asociadas a HU-15: dispositivo (máximo dos activos por obra) | G64: Adiel | H64: 1 | I64: 24/10 | K64: Done | L64: Sí | M64: 22/10/2026 | N64: Migración fusionada, corre en base limpia y con datos, y se revierte | O64: Sí | P64: 22/10/2026 | Q64: PR #1 de Adiel (22/10) | R64: =IF(AND(K64<>"To Do",L64<>"Sí"),"⚠ pasó a Doing sin DoR",IF(AND(K64="Done",O64<>"Sí"),"⚠ Done sin criterio cumplido",IF(AND(K64="Doing",COUNTIFS($G$6:$G$266,G64,$K$6:$K$266,"Doing",$E$6:$E$266,"<>Scrum")>2,E64<>"Scrum"),"⚠ más de 2 en Doing","ok"))) | S64: =IF($K64="To Do",COUNTIF($K$6:$K64,"To Do"),"") | T64: =IF($K64="Doing",COUNTIF($K$6:$K64,"Doing"),"") | U64: =IF($K64="Done",COUNTIF($K$6:$K64,"Done"),"")
B65: T-060 | C65: HU-15 | D65: Autorizar celular de la obra | E65: Backend | F65: Programar el back-end de HU-15 (entidad, repositorio, servicio y controlador): el registro de dispositivos autorizados por obra (máximo dos) y el rechazo del no autorizado | G65: Adiel | H65: 3 | I65: 25/10 | K65: Done | L65: Sí | M65: 22/10/2026 | N65: PR fusionado con sus pruebas automáticas en verde y el endpoint documentado | O65: Sí | P65: 22/10/2026 | Q65: PR #1 y #2 de Adiel (22/10) | R65: =IF(AND(K65<>"To Do",L65<>"Sí"),"⚠ pasó a Doing sin DoR",IF(AND(K65="Done",O65<>"Sí"),"⚠ Done sin criterio cumplido",IF(AND(K65="Doing",COUNTIFS($G$6:$G$266,G65,$K$6:$K$266,"Doing",$E$6:$E$266,"<>Scrum")>2,E65<>"Scrum"),"⚠ más de 2 en Doing","ok"))) | S65: =IF($K65="To Do",COUNTIF($K$6:$K65,"To Do"),"") | T65: =IF($K65="Doing",COUNTIF($K$6:$K65,"Doing"),"") | U65: =IF($K65="Done",COUNTIF($K$6:$K65,"Done"),"")
B66: T-061 | C66: HU-15 | D66: Autorizar celular de la obra | E66: Front-end app | F66: Programar en la app la generación del código del dispositivo en la primera instalación | G66: Nicolás | H66: 3 | I66: 26/10 | J66: T-057, T-242 | K66: To Do | N66: PR fusionado; lo que registra movimientos probado en modo avión | R66: =IF(AND(K66<>"To Do",L66<>"Sí"),"⚠ pasó a Doing sin DoR",IF(AND(K66="Done",O66<>"Sí"),"⚠ Done sin criterio cumplido",IF(AND(K66="Doing",COUNTIFS($G$6:$G$266,G66,$K$6:$K$266,"Doing",$E$6:$E$266,"<>Scrum")>2,E66<>"Scrum"),"⚠ más de 2 en Doing","ok"))) | S66: =IF($K66="To Do",COUNTIF($K$6:$K66,"To Do"),"") | T66: =IF($K66="Doing",COUNTIF($K$6:$K66,"Doing"),"") | U66: =IF($K66="Done",COUNTIF($K$6:$K66,"Done"),"")
B67: T-062 | C67: HU-15 | D67: Autorizar celular de la obra | E67: Front-end web | F67: Programar la pantalla web para autorizar o cambiar el celular de la obra | G67: Henry | H67: 3 | I67: 26/10 | J67: T-057 | K67: To Do | N67: PR fusionado, build sin errores, modo claro/oscuro y escala 125 % | R67: =IF(AND(K67<>"To Do",L67<>"Sí"),"⚠ pasó a Doing sin DoR",IF(AND(K67="Done",O67<>"Sí"),"⚠ Done sin criterio cumplido",IF(AND(K67="Doing",COUNTIFS($G$6:$G$266,G67,$K$6:$K$266,"Doing",$E$6:$E$266,"<>Scrum")>2,E67<>"Scrum"),"⚠ más de 2 en Doing","ok"))) | S67: =IF($K67="To Do",COUNTIF($K$6:$K67,"To Do"),"") | T67: =IF($K67="Doing",COUNTIF($K$6:$K67,"Doing"),"") | U67: =IF($K67="Done",COUNTIF($K$6:$K67,"Done"),"")
B68: T-063 | C68: HU-15 | D68: Autorizar celular de la obra | E68: Pruebas | F68: Probar la funcionalidad de HU-15 (la API con Postman, la pantalla web y la app) contra cada condición final y aprobar su PR | G68: Fernando | H68: 1 | I68: 27/10 | J68: T-059, T-060, T-061, T-062, T-233 | K68: To Do | N68: Cada condición final verificada con Postman y en la interfaz; PR aprobado por alguien distinto del autor | R68: =IF(AND(K68<>"To Do",L68<>"Sí"),"⚠ pasó a Doing sin DoR",IF(AND(K68="Done",O68<>"Sí"),"⚠ Done sin criterio cumplido",IF(AND(K68="Doing",COUNTIFS($G$6:$G$266,G68,$K$6:$K$266,"Doing",$E$6:$E$266,"<>Scrum")>2,E68<>"Scrum"),"⚠ más de 2 en Doing","ok"))) | S68: =IF($K68="To Do",COUNTIF($K$6:$K68,"To Do"),"") | T68: =IF($K68="Doing",COUNTIF($K$6:$K68,"Doing"),"") | U68: =IF($K68="Done",COUNTIF($K$6:$K68,"Done"),"")
B69: T-064 | C69: HU-15 | D69: Autorizar celular de la obra | E69: Aceptación | F69: Aceptar HU-15 como Product Owner desde la interfaz y moverla a Done | G69: Adiel | H69: 0.5 | I69: 27/10 | J69: T-063 | K69: To Do | N69: DoD T1–T10 + condiciones finales aceptadas por el PO → la HU pasa a Done | R69: =IF(AND(K69<>"To Do",L69<>"Sí"),"⚠ pasó a Doing sin DoR",IF(AND(K69="Done",O69<>"Sí"),"⚠ Done sin criterio cumplido",IF(AND(K69="Doing",COUNTIFS($G$6:$G$266,G69,$K$6:$K$266,"Doing",$E$6:$E$266,"<>Scrum")>2,E69<>"Scrum"),"⚠ más de 2 en Doing","ok"))) | S69: =IF($K69="To Do",COUNTIF($K$6:$K69,"To Do"),"") | T69: =IF($K69="Doing",COUNTIF($K$6:$K69,"Doing"),"") | U69: =IF($K69="Done",COUNTIF($K$6:$K69,"Done"),"")
B70: T-065 | C70: HU-16 | D70: Importar precios unitarios | E70: Diseño UI | F70: Diseñar la interfaz de usuario de HU-16: pantalla 19 · Importar APU y requerimiento | G70: Fernando | H70: 1 | I70: 23/10 | K70: Done | L70: Sí | M70: 22/10/2026 | N70: Mockup en el lienzo, revisado por el equipo | O70: Sí | P70: 22/10/2026 | Q70: Lienzo «SIGRO · Pantallas y diagramas del Sprint 1» | R70: =IF(AND(K70<>"To Do",L70<>"Sí"),"⚠ pasó a Doing sin DoR",IF(AND(K70="Done",O70<>"Sí"),"⚠ Done sin criterio cumplido",IF(AND(K70="Doing",COUNTIFS($G$6:$G$266,G70,$K$6:$K$266,"Doing",$E$6:$E$266,"<>Scrum")>2,E70<>"Scrum"),"⚠ más de 2 en Doing","ok"))) | S70: =IF($K70="To Do",COUNTIF($K$6:$K70,"To Do"),"") | T70: =IF($K70="Doing",COUNTIF($K$6:$K70,"Doing"),"") | U70: =IF($K70="Done",COUNTIF($K$6:$K70,"Done"),"")
B71: T-066 | C71: HU-16 | D71: Importar precios unitarios | E71: Modelado UML | F71: Modelar la funcionalidad de HU-16 con el diagrama UML de actividades de la lectura del APU | G71: Fernando | H71: 1 | I71: 24/10 | J71: T-065 | K71: To Do | N71: Diagrama publicado en el repo o el lienzo | R71: =IF(AND(K71<>"To Do",L71<>"Sí"),"⚠ pasó a Doing sin DoR",IF(AND(K71="Done",O71<>"Sí"),"⚠ Done sin criterio cumplido",IF(AND(K71="Doing",COUNTIFS($G$6:$G$266,G71,$K$6:$K$266,"Doing",$E$6:$E$266,"<>Scrum")>2,E71<>"Scrum"),"⚠ más de 2 en Doing","ok"))) | S71: =IF($K71="To Do",COUNTIF($K$6:$K71,"To Do"),"") | T71: =IF($K71="Doing",COUNTIF($K$6:$K71,"Doing"),"") | U71: =IF($K71="Done",COUNTIF($K$6:$K71,"Done"),"")
B72: T-067 | C72: HU-16 | D72: Importar precios unitarios | E72: Base de datos | F72: Implementar las tablas asociadas a HU-16: partida, partida_recurso | G72: Adiel | H72: 1 | I72: 24/10 | J72: T-066 | K72: To Do | N72: Migración fusionada, corre en base limpia y con datos, y se revierte | R72: =IF(AND(K72<>"To Do",L72<>"Sí"),"⚠ pasó a Doing sin DoR",IF(AND(K72="Done",O72<>"Sí"),"⚠ Done sin criterio cumplido",IF(AND(K72="Doing",COUNTIFS($G$6:$G$266,G72,$K$6:$K$266,"Doing",$E$6:$E$266,"<>Scrum")>2,E72<>"Scrum"),"⚠ más de 2 en Doing","ok"))) | S72: =IF($K72="To Do",COUNTIF($K$6:$K72,"To Do"),"") | T72: =IF($K72="Doing",COUNTIF($K$6:$K72,"Doing"),"") | U72: =IF($K72="Done",COUNTIF($K$6:$K72,"Done"),"")
B73: T-068 | C73: HU-16 | D73: Importar precios unitarios | E73: Backend | F73: Crear la tabla partida–recurso y programar el endpoint que la guarda | G73: Adiel | H73: 5 | I73: 25/10 | J73: T-067 | K73: To Do | N73: PR fusionado con sus pruebas automáticas en verde y el endpoint documentado | R73: =IF(AND(K73<>"To Do",L73<>"Sí"),"⚠ pasó a Doing sin DoR",IF(AND(K73="Done",O73<>"Sí"),"⚠ Done sin criterio cumplido",IF(AND(K73="Doing",COUNTIFS($G$6:$G$266,G73,$K$6:$K$266,"Doing",$E$6:$E$266,"<>Scrum")>2,E73<>"Scrum"),"⚠ más de 2 en Doing","ok"))) | S73: =IF($K73="To Do",COUNTIF($K$6:$K73,"To Do"),"") | T73: =IF($K73="Doing",COUNTIF($K$6:$K73,"Doing"),"") | U73: =IF($K73="Done",COUNTIF($K$6:$K73,"Done"),"")
B74: T-069 | C74: HU-16 | D74: Importar precios unitarios | E74: Integración | F74: Programar el lector del PDF del APU (371 páginas), identificando la partida por código y descripción — integración con S10 (análisis de precios unitarios) | G74: Fernando | H74: 5 | I74: 25/10 | J74: T-066 | K74: Doing | L74: Sí | M74: 22/10/2026 | N74: Probado con el archivo o servicio real, PR fusionado | Q74: Registro del 22/10 | R74: =IF(AND(K74<>"To Do",L74<>"Sí"),"⚠ pasó a Doing sin DoR",IF(AND(K74="Done",O74<>"Sí"),"⚠ Done sin criterio cumplido",IF(AND(K74="Doing",COUNTIFS($G$6:$G$266,G74,$K$6:$K$266,"Doing",$E$6:$E$266,"<>Scrum")>2,E74<>"Scrum"),"⚠ más de 2 en Doing","ok"))) | S74: =IF($K74="To Do",COUNTIF($K$6:$K74,"To Do"),"") | T74: =IF($K74="Doing",COUNTIF($K$6:$K74,"Doing"),"") | U74: =IF($K74="Done",COUNTIF($K$6:$K74,"Done"),"")
B75: T-070 | C75: HU-16 | D75: Importar precios unitarios | E75: Front-end web | F75: Programar la pantalla web para importar el APU | G75: Fernando | H75: 5 | I75: 26/10 | J75: T-065 | K75: To Do | N75: PR fusionado, build sin errores, modo claro/oscuro y escala 125 % | R75: =IF(AND(K75<>"To Do",L75<>"Sí"),"⚠ pasó a Doing sin DoR",IF(AND(K75="Done",O75<>"Sí"),"⚠ Done sin criterio cumplido",IF(AND(K75="Doing",COUNTIFS($G$6:$G$266,G75,$K$6:$K$266,"Doing",$E$6:$E$266,"<>Scrum")>2,E75<>"Scrum"),"⚠ más de 2 en Doing","ok"))) | S75: =IF($K75="To Do",COUNTIF($K$6:$K75,"To Do"),"") | T75: =IF($K75="Doing",COUNTIF($K$6:$K75,"Doing"),"") | U75: =IF($K75="Done",COUNTIF($K$6:$K75,"Done"),"")
B76: T-071 | C76: HU-16 | D76: Importar precios unitarios | E76: Pruebas | F76: Probar la funcionalidad de HU-16 (la API con Postman y la pantalla web) contra cada condición final y aprobar su PR | G76: Henry | H76: 1 | I76: 27/10 | J76: T-067, T-068, T-069, T-070, T-233 | K76: To Do | N76: Cada condición final verificada con Postman y en la interfaz; PR aprobado por alguien distinto del autor | R76: =IF(AND(K76<>"To Do",L76<>"Sí"),"⚠ pasó a Doing sin DoR",IF(AND(K76="Done",O76<>"Sí"),"⚠ Done sin criterio cumplido",IF(AND(K76="Doing",COUNTIFS($G$6:$G$266,G76,$K$6:$K$266,"Doing",$E$6:$E$266,"<>Scrum")>2,E76<>"Scrum"),"⚠ más de 2 en Doing","ok"))) | S76: =IF($K76="To Do",COUNTIF($K$6:$K76,"To Do"),"") | T76: =IF($K76="Doing",COUNTIF($K$6:$K76,"Doing"),"") | U76: =IF($K76="Done",COUNTIF($K$6:$K76,"Done"),"")
B77: T-072 | C77: HU-16 | D77: Importar precios unitarios | E77: Aceptación | F77: Aceptar HU-16 como Product Owner desde la interfaz y moverla a Done | G77: Adiel | H77: 0.5 | I77: 27/10 | J77: T-071 | K77: To Do | N77: DoD T1–T10 + condiciones finales aceptadas por el PO → la HU pasa a Done | R77: =IF(AND(K77<>"To Do",L77<>"Sí"),"⚠ pasó a Doing sin DoR",IF(AND(K77="Done",O77<>"Sí"),"⚠ Done sin criterio cumplido",IF(AND(K77="Doing",COUNTIFS($G$6:$G$266,G77,$K$6:$K$266,"Doing",$E$6:$E$266,"<>Scrum")>2,E77<>"Scrum"),"⚠ más de 2 en Doing","ok"))) | S77: =IF($K77="To Do",COUNTIF($K$6:$K77,"To Do"),"") | T77: =IF($K77="Doing",COUNTIF($K$6:$K77,"Doing"),"") | U77: =IF($K77="Done",COUNTIF($K$6:$K77,"Done"),"")
B78: T-073 | C78: HU-17 | D78: Convertir unidades (kg a varillas) | E78: Diseño UI | F78: Diseñar la interfaz de usuario de HU-17: pantalla 16 · Catálogo e insumo | G78: Fernando | H78: 1 | I78: 23/10 | K78: Done | L78: Sí | M78: 22/10/2026 | N78: Mockup en el lienzo, revisado por el equipo | O78: Sí | P78: 22/10/2026 | Q78: Lienzo «SIGRO · Pantallas y diagramas del Sprint 1» | R78: =IF(AND(K78<>"To Do",L78<>"Sí"),"⚠ pasó a Doing sin DoR",IF(AND(K78="Done",O78<>"Sí"),"⚠ Done sin criterio cumplido",IF(AND(K78="Doing",COUNTIFS($G$6:$G$266,G78,$K$6:$K$266,"Doing",$E$6:$E$266,"<>Scrum")>2,E78<>"Scrum"),"⚠ más de 2 en Doing","ok"))) | S78: =IF($K78="To Do",COUNTIF($K$6:$K78,"To Do"),"") | T78: =IF($K78="Doing",COUNTIF($K$6:$K78,"Doing"),"") | U78: =IF($K78="Done",COUNTIF($K$6:$K78,"Done"),"")
B79: T-074 | C79: HU-17 | D79: Convertir unidades (kg a varillas) | E79: Modelado UML | F79: Modelar la funcionalidad de HU-17 con el diagrama UML de secuencia de la conversión kg ↔ varillas | G79: Fernando | H79: 1 | I79: 24/10 | J79: T-073 | K79: To Do | N79: Diagrama publicado en el repo o el lienzo | R79: =IF(AND(K79<>"To Do",L79<>"Sí"),"⚠ pasó a Doing sin DoR",IF(AND(K79="Done",O79<>"Sí"),"⚠ Done sin criterio cumplido",IF(AND(K79="Doing",COUNTIFS($G$6:$G$266,G79,$K$6:$K$266,"Doing",$E$6:$E$266,"<>Scrum")>2,E79<>"Scrum"),"⚠ más de 2 en Doing","ok"))) | S79: =IF($K79="To Do",COUNTIF($K$6:$K79,"To Do"),"") | T79: =IF($K79="Doing",COUNTIF($K$6:$K79,"Doing"),"") | U79: =IF($K79="Done",COUNTIF($K$6:$K79,"Done"),"")
B80: T-075 | C80: HU-17 | D80: Convertir unidades (kg a varillas) | E80: Base de datos | F80: Implementar las tablas asociadas a HU-17: insumo.factor_conversion con su histórico | G80: Adiel | H80: 1 | I80: 24/10 | J80: T-074 | K80: To Do | N80: Migración fusionada, corre en base limpia y con datos, y se revierte | R80: =IF(AND(K80<>"To Do",L80<>"Sí"),"⚠ pasó a Doing sin DoR",IF(AND(K80="Done",O80<>"Sí"),"⚠ Done sin criterio cumplido",IF(AND(K80="Doing",COUNTIFS($G$6:$G$266,G80,$K$6:$K$266,"Doing",$E$6:$E$266,"<>Scrum")>2,E80<>"Scrum"),"⚠ más de 2 en Doing","ok"))) | S80: =IF($K80="To Do",COUNTIF($K$6:$K80,"To Do"),"") | T80: =IF($K80="Doing",COUNTIF($K$6:$K80,"Doing"),"") | U80: =IF($K80="Done",COUNTIF($K$6:$K80,"Done"),"")
B81: T-076 | C81: HU-17 | D81: Convertir unidades (kg a varillas) | E81: Backend | F81: Programar el back-end de HU-17 (entidad, repositorio, servicio y controlador): el registro del factor de conversión con su fecha y su usuario | G81: Adiel | H81: 2 | I81: 25/10 | J81: T-075 | K81: To Do | N81: PR fusionado con sus pruebas automáticas en verde y el endpoint documentado | R81: =IF(AND(K81<>"To Do",L81<>"Sí"),"⚠ pasó a Doing sin DoR",IF(AND(K81="Done",O81<>"Sí"),"⚠ Done sin criterio cumplido",IF(AND(K81="Doing",COUNTIFS($G$6:$G$266,G81,$K$6:$K$266,"Doing",$E$6:$E$266,"<>Scrum")>2,E81<>"Scrum"),"⚠ más de 2 en Doing","ok"))) | S81: =IF($K81="To Do",COUNTIF($K$6:$K81,"To Do"),"") | T81: =IF($K81="Doing",COUNTIF($K$6:$K81,"Doing"),"") | U81: =IF($K81="Done",COUNTIF($K$6:$K81,"Done"),"")
B82: T-077 | C82: HU-17 | D82: Convertir unidades (kg a varillas) | E82: Front-end web | F82: Programar el formulario web del factor de conversión (kg ↔ varillas) | G82: Fernando | H82: 2 | I82: 26/10 | J82: T-073 | K82: To Do | N82: PR fusionado, build sin errores, modo claro/oscuro y escala 125 % | R82: =IF(AND(K82<>"To Do",L82<>"Sí"),"⚠ pasó a Doing sin DoR",IF(AND(K82="Done",O82<>"Sí"),"⚠ Done sin criterio cumplido",IF(AND(K82="Doing",COUNTIFS($G$6:$G$266,G82,$K$6:$K$266,"Doing",$E$6:$E$266,"<>Scrum")>2,E82<>"Scrum"),"⚠ más de 2 en Doing","ok"))) | S82: =IF($K82="To Do",COUNTIF($K$6:$K82,"To Do"),"") | T82: =IF($K82="Doing",COUNTIF($K$6:$K82,"Doing"),"") | U82: =IF($K82="Done",COUNTIF($K$6:$K82,"Done"),"")
B83: T-078 | C83: HU-17 | D83: Convertir unidades (kg a varillas) | E83: Pruebas | F83: Probar la funcionalidad de HU-17 (la API con Postman y la pantalla web) contra cada condición final y aprobar su PR | G83: Henry | H83: 1 | I83: 27/10 | J83: T-075, T-076, T-077, T-233 | K83: To Do | N83: Cada condición final verificada con Postman y en la interfaz; PR aprobado por alguien distinto del autor | R83: =IF(AND(K83<>"To Do",L83<>"Sí"),"⚠ pasó a Doing sin DoR",IF(AND(K83="Done",O83<>"Sí"),"⚠ Done sin criterio cumplido",IF(AND(K83="Doing",COUNTIFS($G$6:$G$266,G83,$K$6:$K$266,"Doing",$E$6:$E$266,"<>Scrum")>2,E83<>"Scrum"),"⚠ más de 2 en Doing","ok"))) | S83: =IF($K83="To Do",COUNTIF($K$6:$K83,"To Do"),"") | T83: =IF($K83="Doing",COUNTIF($K$6:$K83,"Doing"),"") | U83: =IF($K83="Done",COUNTIF($K$6:$K83,"Done"),"")
B84: T-079 | C84: HU-17 | D84: Convertir unidades (kg a varillas) | E84: Aceptación | F84: Aceptar HU-17 como Product Owner desde la interfaz y moverla a Done | G84: Adiel | H84: 0.5 | I84: 27/10 | J84: T-078 | K84: To Do | N84: DoD T1–T10 + condiciones finales aceptadas por el PO → la HU pasa a Done | R84: =IF(AND(K84<>"To Do",L84<>"Sí"),"⚠ pasó a Doing sin DoR",IF(AND(K84="Done",O84<>"Sí"),"⚠ Done sin criterio cumplido",IF(AND(K84="Doing",COUNTIFS($G$6:$G$266,G84,$K$6:$K$266,"Doing",$E$6:$E$266,"<>Scrum")>2,E84<>"Scrum"),"⚠ más de 2 en Doing","ok"))) | S84: =IF($K84="To Do",COUNTIF($K$6:$K84,"To Do"),"") | T84: =IF($K84="Doing",COUNTIF($K$6:$K84,"Doing"),"") | U84: =IF($K84="Done",COUNTIF($K$6:$K84,"Done"),"")
B85: T-080 | C85: HU-19 | D85: Importar requerimiento de la obra | E85: Diseño UI | F85: Diseñar la interfaz de usuario de HU-19: pantalla 19 · Importar APU y requerimiento | G85: Fernando | H85: 1 | I85: 23/10 | K85: Done | L85: Sí | M85: 22/10/2026 | N85: Mockup en el lienzo, revisado por el equipo | O85: Sí | P85: 22/10/2026 | Q85: Lienzo «SIGRO · Pantallas y diagramas del Sprint 1» | R85: =IF(AND(K85<>"To Do",L85<>"Sí"),"⚠ pasó a Doing sin DoR",IF(AND(K85="Done",O85<>"Sí"),"⚠ Done sin criterio cumplido",IF(AND(K85="Doing",COUNTIFS($G$6:$G$266,G85,$K$6:$K$266,"Doing",$E$6:$E$266,"<>Scrum")>2,E85<>"Scrum"),"⚠ más de 2 en Doing","ok"))) | S85: =IF($K85="To Do",COUNTIF($K$6:$K85,"To Do"),"") | T85: =IF($K85="Doing",COUNTIF($K$6:$K85,"Doing"),"") | U85: =IF($K85="Done",COUNTIF($K$6:$K85,"Done"),"")
B86: T-081 | C86: HU-19 | D86: Importar requerimiento de la obra | E86: Modelado UML | F86: Modelar la funcionalidad de HU-19 con el diagrama UML de actividades de la importación del requerimiento total | G86: Fernando | H86: 1 | I86: 24/10 | J86: T-080 | K86: To Do | N86: Diagrama publicado en el repo o el lienzo | R86: =IF(AND(K86<>"To Do",L86<>"Sí"),"⚠ pasó a Doing sin DoR",IF(AND(K86="Done",O86<>"Sí"),"⚠ Done sin criterio cumplido",IF(AND(K86="Doing",COUNTIFS($G$6:$G$266,G86,$K$6:$K$266,"Doing",$E$6:$E$266,"<>Scrum")>2,E86<>"Scrum"),"⚠ más de 2 en Doing","ok"))) | S86: =IF($K86="To Do",COUNTIF($K$6:$K86,"To Do"),"") | T86: =IF($K86="Doing",COUNTIF($K$6:$K86,"Doing"),"") | U86: =IF($K86="Done",COUNTIF($K$6:$K86,"Done"),"")
B87: T-082 | C87: HU-19 | D87: Importar requerimiento de la obra | E87: Base de datos | F87: Implementar las tablas asociadas a HU-19: requerimiento (cantidad y costo planificados, ajuste con motivo) | G87: Adiel | H87: 1 | I87: 24/10 | J87: T-081 | K87: To Do | N87: Migración fusionada, corre en base limpia y con datos, y se revierte | R87: =IF(AND(K87<>"To Do",L87<>"Sí"),"⚠ pasó a Doing sin DoR",IF(AND(K87="Done",O87<>"Sí"),"⚠ Done sin criterio cumplido",IF(AND(K87="Doing",COUNTIFS($G$6:$G$266,G87,$K$6:$K$266,"Doing",$E$6:$E$266,"<>Scrum")>2,E87<>"Scrum"),"⚠ más de 2 en Doing","ok"))) | S87: =IF($K87="To Do",COUNTIF($K$6:$K87,"To Do"),"") | T87: =IF($K87="Doing",COUNTIF($K$6:$K87,"Doing"),"") | U87: =IF($K87="Done",COUNTIF($K$6:$K87,"Done"),"")
B88: T-083 | C88: HU-19 | D88: Importar requerimiento de la obra | E88: Backend | F88: Programar el back-end de HU-19 (entidad, repositorio, servicio y controlador): el guardado del requerimiento total y de sus ajustes con motivo | G88: Adiel | H88: 3 | I88: 25/10 | J88: T-082 | K88: To Do | N88: PR fusionado con sus pruebas automáticas en verde y el endpoint documentado | R88: =IF(AND(K88<>"To Do",L88<>"Sí"),"⚠ pasó a Doing sin DoR",IF(AND(K88="Done",O88<>"Sí"),"⚠ Done sin criterio cumplido",IF(AND(K88="Doing",COUNTIFS($G$6:$G$266,G88,$K$6:$K$266,"Doing",$E$6:$E$266,"<>Scrum")>2,E88<>"Scrum"),"⚠ más de 2 en Doing","ok"))) | S88: =IF($K88="To Do",COUNTIF($K$6:$K88,"To Do"),"") | T88: =IF($K88="Doing",COUNTIF($K$6:$K88,"Doing"),"") | U88: =IF($K88="Done",COUNTIF($K$6:$K88,"Done"),"")
B89: T-084 | C89: HU-19 | D89: Importar requerimiento de la obra | E89: Integración | F89: Adaptar el lector de la Relación de insumos para obtener el requerimiento total — integración con S10 (relación de insumos) | G89: Fernando | H89: 3 | I89: 25/10 | J89: T-081 | K89: To Do | N89: Probado con el archivo o servicio real, PR fusionado | R89: =IF(AND(K89<>"To Do",L89<>"Sí"),"⚠ pasó a Doing sin DoR",IF(AND(K89="Done",O89<>"Sí"),"⚠ Done sin criterio cumplido",IF(AND(K89="Doing",COUNTIFS($G$6:$G$266,G89,$K$6:$K$266,"Doing",$E$6:$E$266,"<>Scrum")>2,E89<>"Scrum"),"⚠ más de 2 en Doing","ok"))) | S89: =IF($K89="To Do",COUNTIF($K$6:$K89,"To Do"),"") | T89: =IF($K89="Doing",COUNTIF($K$6:$K89,"Doing"),"") | U89: =IF($K89="Done",COUNTIF($K$6:$K89,"Done"),"")
B90: T-085 | C90: HU-19 | D90: Importar requerimiento de la obra | E90: Front-end web | F90: Programar la pantalla web del requerimiento total | G90: Fernando | H90: 3 | I90: 26/10 | J90: T-080 | K90: To Do | N90: PR fusionado, build sin errores, modo claro/oscuro y escala 125 % | R90: =IF(AND(K90<>"To Do",L90<>"Sí"),"⚠ pasó a Doing sin DoR",IF(AND(K90="Done",O90<>"Sí"),"⚠ Done sin criterio cumplido",IF(AND(K90="Doing",COUNTIFS($G$6:$G$266,G90,$K$6:$K$266,"Doing",$E$6:$E$266,"<>Scrum")>2,E90<>"Scrum"),"⚠ más de 2 en Doing","ok"))) | S90: =IF($K90="To Do",COUNTIF($K$6:$K90,"To Do"),"") | T90: =IF($K90="Doing",COUNTIF($K$6:$K90,"Doing"),"") | U90: =IF($K90="Done",COUNTIF($K$6:$K90,"Done"),"")
B91: T-086 | C91: HU-19 | D91: Importar requerimiento de la obra | E91: Pruebas | F91: Probar la funcionalidad de HU-19 (la API con Postman y la pantalla web) contra cada condición final y aprobar su PR | G91: Henry | H91: 1 | I91: 27/10 | J91: T-082, T-083, T-084, T-085, T-233 | K91: To Do | N91: Cada condición final verificada con Postman y en la interfaz; PR aprobado por alguien distinto del autor | R91: =IF(AND(K91<>"To Do",L91<>"Sí"),"⚠ pasó a Doing sin DoR",IF(AND(K91="Done",O91<>"Sí"),"⚠ Done sin criterio cumplido",IF(AND(K91="Doing",COUNTIFS($G$6:$G$266,G91,$K$6:$K$266,"Doing",$E$6:$E$266,"<>Scrum")>2,E91<>"Scrum"),"⚠ más de 2 en Doing","ok"))) | S91: =IF($K91="To Do",COUNTIF($K$6:$K91,"To Do"),"") | T91: =IF($K91="Doing",COUNTIF($K$6:$K91,"Doing"),"") | U91: =IF($K91="Done",COUNTIF($K$6:$K91,"Done"),"")
B92: T-087 | C92: HU-19 | D92: Importar requerimiento de la obra | E92: Aceptación | F92: Aceptar HU-19 como Product Owner desde la interfaz y moverla a Done | G92: Adiel | H92: 0.5 | I92: 27/10 | J92: T-086 | K92: To Do | N92: DoD T1–T10 + condiciones finales aceptadas por el PO → la HU pasa a Done | R92: =IF(AND(K92<>"To Do",L92<>"Sí"),"⚠ pasó a Doing sin DoR",IF(AND(K92="Done",O92<>"Sí"),"⚠ Done sin criterio cumplido",IF(AND(K92="Doing",COUNTIFS($G$6:$G$266,G92,$K$6:$K$266,"Doing",$E$6:$E$266,"<>Scrum")>2,E92<>"Scrum"),"⚠ más de 2 en Doing","ok"))) | S92: =IF($K92="To Do",COUNTIF($K$6:$K92,"To Do"),"") | T92: =IF($K92="Doing",COUNTIF($K$6:$K92,"Doing"),"") | U92: =IF($K92="Done",COUNTIF($K$6:$K92,"Done"),"")
B93: T-088 | C93: HU-23 | D93: Consultar cuánto se compró y consumió | E93: Diseño UI | F93: Diseñar la interfaz de usuario de HU-23: pantalla 13 · Gasto en recursos | G93: Fernando | H93: 1 | I93: 23/10 | K93: Done | L93: Sí | M93: 22/10/2026 | N93: Mockup en el lienzo, revisado por el equipo | O93: Sí | P93: 22/10/2026 | Q93: Lienzo «SIGRO · Pantallas y diagramas del Sprint 1» | R93: =IF(AND(K93<>"To Do",L93<>"Sí"),"⚠ pasó a Doing sin DoR",IF(AND(K93="Done",O93<>"Sí"),"⚠ Done sin criterio cumplido",IF(AND(K93="Doing",COUNTIFS($G$6:$G$266,G93,$K$6:$K$266,"Doing",$E$6:$E$266,"<>Scrum")>2,E93<>"Scrum"),"⚠ más de 2 en Doing","ok"))) | S93: =IF($K93="To Do",COUNTIF($K$6:$K93,"To Do"),"") | T93: =IF($K93="Doing",COUNTIF($K$6:$K93,"Doing"),"") | U93: =IF($K93="Done",COUNTIF($K$6:$K93,"Done"),"")
B94: T-089 | C94: HU-23 | D94: Consultar cuánto se compró y consumió | E94: Modelado UML | F94: Modelar la funcionalidad de HU-23 con el diagrama UML de secuencia del cálculo del avance | G94: Fernando | H94: 1 | I94: 24/10 | J94: T-088 | K94: To Do | N94: Diagrama publicado en el repo o el lienzo | R94: =IF(AND(K94<>"To Do",L94<>"Sí"),"⚠ pasó a Doing sin DoR",IF(AND(K94="Done",O94<>"Sí"),"⚠ Done sin criterio cumplido",IF(AND(K94="Doing",COUNTIFS($G$6:$G$266,G94,$K$6:$K$266,"Doing",$E$6:$E$266,"<>Scrum")>2,E94<>"Scrum"),"⚠ más de 2 en Doing","ok"))) | S94: =IF($K94="To Do",COUNTIF($K$6:$K94,"To Do"),"") | T94: =IF($K94="Doing",COUNTIF($K$6:$K94,"Doing"),"") | U94: =IF($K94="Done",COUNTIF($K$6:$K94,"Done"),"")
B95: T-090 | C95: HU-23 | D95: Consultar cuánto se compró y consumió | E95: Base de datos | F95: Implementar las tablas asociadas a HU-23: vista de avance sobre requerimiento, compra_detalle y movimiento | G95: Adiel | H95: 1 | I95: 24/10 | J95: T-089 | K95: To Do | N95: Migración fusionada, corre en base limpia y con datos, y se revierte | R95: =IF(AND(K95<>"To Do",L95<>"Sí"),"⚠ pasó a Doing sin DoR",IF(AND(K95="Done",O95<>"Sí"),"⚠ Done sin criterio cumplido",IF(AND(K95="Doing",COUNTIFS($G$6:$G$266,G95,$K$6:$K$266,"Doing",$E$6:$E$266,"<>Scrum")>2,E95<>"Scrum"),"⚠ más de 2 en Doing","ok"))) | S95: =IF($K95="To Do",COUNTIF($K$6:$K95,"To Do"),"") | T95: =IF($K95="Doing",COUNTIF($K$6:$K95,"Doing"),"") | U95: =IF($K95="Done",COUNTIF($K$6:$K95,"Done"),"")
B96: T-091 | C96: HU-23 | D96: Consultar cuánto se compró y consumió | E96: Backend | F96: Programar el back-end de HU-23 (entidad, repositorio, servicio y controlador): la consulta de avance: requerido, comprado, recibido y consumido por insumo | G96: Adiel | H96: 3 | I96: 25/10 | J96: T-090 | K96: To Do | N96: PR fusionado con sus pruebas automáticas en verde y el endpoint documentado | R96: =IF(AND(K96<>"To Do",L96<>"Sí"),"⚠ pasó a Doing sin DoR",IF(AND(K96="Done",O96<>"Sí"),"⚠ Done sin criterio cumplido",IF(AND(K96="Doing",COUNTIFS($G$6:$G$266,G96,$K$6:$K$266,"Doing",$E$6:$E$266,"<>Scrum")>2,E96<>"Scrum"),"⚠ más de 2 en Doing","ok"))) | S96: =IF($K96="To Do",COUNTIF($K$6:$K96,"To Do"),"") | T96: =IF($K96="Doing",COUNTIF($K$6:$K96,"Doing"),"") | U96: =IF($K96="Done",COUNTIF($K$6:$K96,"Done"),"")
B97: T-092 | C97: HU-23 | D97: Consultar cuánto se compró y consumió | E97: Front-end web | F97: Programar la pantalla web de avance de compra y consumo | G97: Fernando | H97: 3 | I97: 26/10 | K97: Done | L97: Sí | M97: 22/10/2026 | N97: PR fusionado, build sin errores, modo claro/oscuro y escala 125 % | O97: Sí | P97: 22/10/2026 | Q97: Commit del 22/10 09:30 (datos simulados) | R97: =IF(AND(K97<>"To Do",L97<>"Sí"),"⚠ pasó a Doing sin DoR",IF(AND(K97="Done",O97<>"Sí"),"⚠ Done sin criterio cumplido",IF(AND(K97="Doing",COUNTIFS($G$6:$G$266,G97,$K$6:$K$266,"Doing",$E$6:$E$266,"<>Scrum")>2,E97<>"Scrum"),"⚠ más de 2 en Doing","ok"))) | S97: =IF($K97="To Do",COUNTIF($K$6:$K97,"To Do"),"") | T97: =IF($K97="Doing",COUNTIF($K$6:$K97,"Doing"),"") | U97: =IF($K97="Done",COUNTIF($K$6:$K97,"Done"),"")
B98: T-093 | C98: HU-23 | D98: Consultar cuánto se compró y consumió | E98: Conexión API | F98: Conectar la pantalla de avance con la API real | G98: Fernando | H98: 3 | I98: 26/10 | J98: T-091, T-092, T-240 | K98: To Do | N98: La pantalla muestra los datos reales del servidor y sus errores | R98: =IF(AND(K98<>"To Do",L98<>"Sí"),"⚠ pasó a Doing sin DoR",IF(AND(K98="Done",O98<>"Sí"),"⚠ Done sin criterio cumplido",IF(AND(K98="Doing",COUNTIFS($G$6:$G$266,G98,$K$6:$K$266,"Doing",$E$6:$E$266,"<>Scrum")>2,E98<>"Scrum"),"⚠ más de 2 en Doing","ok"))) | S98: =IF($K98="To Do",COUNTIF($K$6:$K98,"To Do"),"") | T98: =IF($K98="Doing",COUNTIF($K$6:$K98,"Doing"),"") | U98: =IF($K98="Done",COUNTIF($K$6:$K98,"Done"),"")
B99: T-094 | C99: HU-23 | D99: Consultar cuánto se compró y consumió | E99: Pruebas | F99: Probar la funcionalidad de HU-23 (la API con Postman y la pantalla web) contra cada condición final y aprobar su PR | G99: Henry | H99: 1 | I99: 27/10 | J99: T-090, T-091, T-092, T-093, T-233 | K99: To Do | N99: Cada condición final verificada con Postman y en la interfaz; PR aprobado por alguien distinto del autor | R99: =IF(AND(K99<>"To Do",L99<>"Sí"),"⚠ pasó a Doing sin DoR",IF(AND(K99="Done",O99<>"Sí"),"⚠ Done sin criterio cumplido",IF(AND(K99="Doing",COUNTIFS($G$6:$G$266,G99,$K$6:$K$266,"Doing",$E$6:$E$266,"<>Scrum")>2,E99<>"Scrum"),"⚠ más de 2 en Doing","ok"))) | S99: =IF($K99="To Do",COUNTIF($K$6:$K99,"To Do"),"") | T99: =IF($K99="Doing",COUNTIF($K$6:$K99,"Doing"),"") | U99: =IF($K99="Done",COUNTIF($K$6:$K99,"Done"),"")
B100: T-095 | C100: HU-23 | D100: Consultar cuánto se compró y consumió | E100: Aceptación | F100: Aceptar HU-23 como Product Owner desde la interfaz y moverla a Done | G100: Adiel | H100: 0.5 | I100: 27/10 | J100: T-094 | K100: To Do | N100: DoD T1–T10 + condiciones finales aceptadas por el PO → la HU pasa a Done | R100: =IF(AND(K100<>"To Do",L100<>"Sí"),"⚠ pasó a Doing sin DoR",IF(AND(K100="Done",O100<>"Sí"),"⚠ Done sin criterio cumplido",IF(AND(K100="Doing",COUNTIFS($G$6:$G$266,G100,$K$6:$K$266,"Doing",$E$6:$E$266,"<>Scrum")>2,E100<>"Scrum"),"⚠ más de 2 en Doing","ok"))) | S100: =IF($K100="To Do",COUNTIF($K$6:$K100,"To Do"),"") | T100: =IF($K100="Doing",COUNTIF($K$6:$K100,"Doing"),"") | U100: =IF($K100="Done",COUNTIF($K$6:$K100,"Done"),"")
B101: T-096 | C101: HU-24 | D101: Consultar cuánto falta comprar | E101: Diseño UI | F101: Diseñar la interfaz de usuario de HU-24: pantalla 8 · Reposición | G101: Fernando | H101: 1 | I101: 23/10 | K101: Done | L101: Sí | M101: 22/10/2026 | N101: Mockup en el lienzo, revisado por el equipo | O101: Sí | P101: 22/10/2026 | Q101: Lienzo «SIGRO · Pantallas y diagramas del Sprint 1» | R101: =IF(AND(K101<>"To Do",L101<>"Sí"),"⚠ pasó a Doing sin DoR",IF(AND(K101="Done",O101<>"Sí"),"⚠ Done sin criterio cumplido",IF(AND(K101="Doing",COUNTIFS($G$6:$G$266,G101,$K$6:$K$266,"Doing",$E$6:$E$266,"<>Scrum")>2,E101<>"Scrum"),"⚠ más de 2 en Doing","ok"))) | S101: =IF($K101="To Do",COUNTIF($K$6:$K101,"To Do"),"") | T101: =IF($K101="Doing",COUNTIF($K$6:$K101,"Doing"),"") | U101: =IF($K101="Done",COUNTIF($K$6:$K101,"Done"),"")
B102: T-097 | C102: HU-24 | D102: Consultar cuánto falta comprar | E102: Modelado UML | F102: Modelar la funcionalidad de HU-24 con el diagrama UML de secuencia de la consulta de lo que falta comprar | G102: Fernando | H102: 1 | I102: 24/10 | J102: T-096 | K102: To Do | N102: Diagrama publicado en el repo o el lienzo | R102: =IF(AND(K102<>"To Do",L102<>"Sí"),"⚠ pasó a Doing sin DoR",IF(AND(K102="Done",O102<>"Sí"),"⚠ Done sin criterio cumplido",IF(AND(K102="Doing",COUNTIFS($G$6:$G$266,G102,$K$6:$K$266,"Doing",$E$6:$E$266,"<>Scrum")>2,E102<>"Scrum"),"⚠ más de 2 en Doing","ok"))) | S102: =IF($K102="To Do",COUNTIF($K$6:$K102,"To Do"),"") | T102: =IF($K102="Doing",COUNTIF($K$6:$K102,"Doing"),"") | U102: =IF($K102="Done",COUNTIF($K$6:$K102,"Done"),"")
...

Sheet Vista del tablero
B2: Vista del tablero · se actualiza sola al cambiar el estado en el registro
B4: =CONCATENATE("To Do · ",COUNTIF('Tablero (To Do · Doing · Done)'!$K$6:$K$266,"To Do")) | E4: =CONCATENATE("Doing · ",COUNTIF('Tablero (To Do · Doing · Done)'!$K$6:$K$266,"Doing")) | H4: =CONCATENATE("Done · ",COUNTIF('Tablero (To Do · Doing · Done)'!$K$6:$K$266,"Done"))
B5: ID | C5: Tarea · responsable | E5: ID | F5: Tarea · responsable | H5: ID | I5: Tarea · responsable
B6: =IFERROR(INDEX('Tablero (To Do · Doing · Done)'!$B$6:$B$266,MATCH(1,'Tablero (To Do · Doing · Done)'!$S$6:$S$266,0)),"") | C6: =IFERROR(INDEX('Tablero (To Do · Doing · Done)'!$F$6:$F$266,MATCH(1,'Tablero (To Do · Doing · Done)'!$S$6:$S$266,0))&" · "&INDEX('Tablero (To Do · Doing · Done)'!$G$6:$G$266,MATCH(1,'Tablero (To Do · Doing · Done)'!$S$6:$S$266,0)),"") | E6: =IFERROR(INDEX('Tablero (To Do · Doing · Done)'!$B$6:$B$266,MATCH(1,'Tablero (To Do · Doing · Done)'!$T$6:$T$266,0)),"") | F6: =IFERROR(INDEX('Tablero (To Do · Doing · Done)'!$F$6:$F$266,MATCH(1,'Tablero (To Do · Doing · Done)'!$T$6:$T$266,0))&" · "&INDEX('Tablero (To Do · Doing · Done)'!$G$6:$G$266,MATCH(1,'Tablero (To Do · Doing · Done)'!$T$6:$T$266,0)),"") | H6: =IFERROR(INDEX('Tablero (To Do · Doing · Done)'!$B$6:$B$266,MATCH(1,'Tablero (To Do · Doing · Done)'!$U$6:$U$266,0)),"") | I6: =IFERROR(INDEX('Tablero (To Do · Doing · Done)'!$F$6:$F$266,MATCH(1,'Tablero (To Do · Doing · Done)'!$U$6:$U$266,0))&" · "&INDEX('Tablero (To Do · Doing · Done)'!$G$6:$G$266,MATCH(1,'Tablero (To Do · Doing · Done)'!$U$6:$U$266,0)),"")
B7: =IFERROR(INDEX('Tablero (To Do · Doing · Done)'!$B$6:$B$266,MATCH(2,'Tablero (To Do · Doing · Done)'!$S$6:$S$266,0)),"") | C7: =IFERROR(INDEX('Tablero (To Do · Doing · Done)'!$F$6:$F$266,MATCH(2,'Tablero (To Do · Doing · Done)'!$S$6:$S$266,0))&" · "&INDEX('Tablero (To Do · Doing · Done)'!$G$6:$G$266,MATCH(2,'Tablero (To Do · Doing · Done)'!$S$6:$S$266,0)),"") | E7: =IFERROR(INDEX('Tablero (To Do · Doing · Done)'!$B$6:$B$266,MATCH(2,'Tablero (To Do · Doing · Done)'!$T$6:$T$266,0)),"") | F7: =IFERROR(INDEX('Tablero (To Do · Doing · Done)'!$F$6:$F$266,MATCH(2,'Tablero (To Do · Doing · Done)'!$T$6:$T$266,0))&" · "&INDEX('Tablero (To Do · Doing · Done)'!$G$6:$G$266,MATCH(2,'Tablero (To Do · Doing · Done)'!$T$6:$T$266,0)),"") | H7: =IFERROR(INDEX('Tablero (To Do · Doing · Done)'!$B$6:$B$266,MATCH(2,'Tablero (To Do · Doing · Done)'!$U$6:$U$266,0)),"") | I7: =IFERROR(INDEX('Tablero (To Do · Doing · Done)'!$F$6:$F$266,MATCH(2,'Tablero (To Do · Doing · Done)'!$U$6:$U$266,0))&" · "&INDEX('Tablero (To Do · Doing · Done)'!$G$6:$G$266,MATCH(2,'Tablero (To Do · Doing · Done)'!$U$6:$U$266,0)),"")
B8: =IFERROR(INDEX('Tablero (To Do · Doing · Done)'!$B$6:$B$266,MATCH(3,'Tablero (To Do · Doing · Done)'!$S$6:$S$266,0)),"") | C8: =IFERROR(INDEX('Tablero (To Do · Doing · Done)'!$F$6:$F$266,MATCH(3,'Tablero (To Do · Doing · Done)'!$S$6:$S$266,0))&" · "&INDEX('Tablero (To Do · Doing · Done)'!$G$6:$G$266,MATCH(3,'Tablero (To Do · Doing · Done)'!$S$6:$S$266,0)),"") | E8: =IFERROR(INDEX('Tablero (To Do · Doing · Done)'!$B$6:$B$266,MATCH(3,'Tablero (To Do · Doing · Done)'!$T$6:$T$266,0)),"") | F8: =IFERROR(INDEX('Tablero (To Do · Doing · Done)'!$F$6:$F$266,MATCH(3,'Tablero (To Do · Doing · Done)'!$T$6:$T$266,0))&" · "&INDEX('Tablero (To Do · Doing · Done)'!$G$6:$G$266,MATCH(3,'Tablero (To Do · Doing · Done)'!$T$6:$T$266,0)),"") | H8: =IFERROR(INDEX('Tablero (To Do · Doing · Done)'!$B$6:$B$266,MATCH(3,'Tablero (To Do · Doing · Done)'!$U$6:$U$266,0)),"") | I8: =IFERROR(INDEX('Tablero (To Do · Doing · Done)'!$F$6:$F$266,MATCH(3,'Tablero (To Do · Doing · Done)'!$U$6:$U$266,0))&" · "&INDEX('Tablero (To Do · Doing · Done)'!$G$6:$G$266,MATCH(3,'Tablero (To Do · Doing · Done)'!$U$6:$U$266,0)),"")
B9: =IFERROR(INDEX('Tablero (To Do · Doing · Done)'!$B$6:$B$266,MATCH(4,'Tablero (To Do · Doing · Done)'!$S$6:$S$266,0)),"") | C9: =IFERROR(INDEX('Tablero (To Do · Doing · Done)'!$F$6:$F$266,MATCH(4,'Tablero (To Do · Doing · Done)'!$S$6:$S$266,0))&" · "&INDEX('Tablero (To Do · Doing · Done)'!$G$6:$G$266,MATCH(4,'Tablero (To Do · Doing · Done)'!$S$6:$S$266,0)),"") | E9: =IFERROR(INDEX('Tablero (To Do · Doing · Done)'!$B$6:$B$266,MATCH(4,'Tablero (To Do · Doing · Done)'!$T$6:$T$266,0)),"") | F9: =IFERROR(INDEX('Tablero (To Do · Doing · Done)'!$F$6:$F$266,MATCH(4,'Tablero (To Do · Doing · Done)'!$T$6:$T$266,0))&" · "&INDEX('Tablero (To Do · Doing · Done)'!$G$6:$G$266,MATCH(4,'Tablero (To Do · Doing · Done)'!$T$6:$T$266,0)),"") | H9: =IFERROR(INDEX('Tablero (To Do · Doing · Done)'!$B$6:$B$266,MATCH(4,'Tablero (To Do · Doing · Done)'!$U$6:$U$266,0)),"") | I9: =IFERROR(INDEX('Tablero (To Do · Doing · Done)'!$F$6:$F$266,MATCH(4,'Tablero (To Do · Doing · Done)'!$U$6:$U$266,0))&" · "&INDEX('Tablero (To Do · Doing · Done)'!$G$6:$G$266,MATCH(4,'Tablero (To Do · Doing · Done)'!$U$6:$U$266,0)),"")
B10: =IFERROR(INDEX('Tablero (To Do · Doing · Done)'!$B$6:$B$266,MATCH(5,'Tablero (To Do · Doing · Done)'!$S$6:$S$266,0)),"") | C10: =IFERROR(INDEX('Tablero (To Do · Doing · Done)'!$F$6:$F$266,MATCH(5,'Tablero (To Do · Doing · Done)'!$S$6:$S$266,0))&" · "&INDEX('Tablero (To Do · Doing · Done)'!$G$6:$G$266,MATCH(5,'Tablero (To Do · Doing · Done)'!$S$6:$S$266,0)),"") | E10: =IFERROR(INDEX('Tablero (To Do · Doing · Done)'!$B$6:$B$266,MATCH(5,'Tablero (To Do · Doing · Done)'!$T$6:$T$266,0)),"") | F10: =IFERROR(INDEX('Tablero (To Do · Doing · Done)'!$F$6:$F$266,MATCH(5,'Tablero (To Do · Doing · Done)'!$T$6:$T$266,0))&" · "&INDEX('Tablero (To Do · Doing · Done)'!$G$6:$G$266,MATCH(5,'Tablero (To Do · Doing · Done)'!$T$6:$T$266,0)),"") | H10: =IFERROR(INDEX('Tablero (To Do · Doing · Done)'!$B$6:$B$266,MATCH(5,'Tablero (To Do · Doing · Done)'!$U$6:$U$266,0)),"") | I10: =IFERROR(INDEX('Tablero (To Do · Doing · Done)'!$F$6:$F$266,MATCH(5,'Tablero (To Do · Doing · Done)'!$U$6:$U$266,0))&" · "&INDEX('Tablero (To Do · Doing · Done)'!$G$6:$G$266,MATCH(5,'Tablero (To Do · Doing · Done)'!$U$6:$U$266,0)),"")
B11: =IFERROR(INDEX('Tablero (To Do · Doing · Done)'!$B$6:$B$266,MATCH(6,'Tablero (To Do · Doing · Done)'!$S$6:$S$266,0)),"") | C11: =IFERROR(INDEX('Tablero (To Do · Doing · Done)'!$F$6:$F$266,MATCH(6,'Tablero (To Do · Doing · Done)'!$S$6:$S$266,0))&" · "&INDEX('Tablero (To Do · Doing · Done)'!$G$6:$G$266,MATCH(6,'Tablero (To Do · Doing · Done)'!$S$6:$S$266,0)),"") | E11: =IFERROR(INDEX('Tablero (To Do · Doing · Done)'!$B$6:$B$266,MATCH(6,'Tablero (To Do · Doing · Done)'!$T$6:$T$266,0)),"") | F11: =IFERROR(INDEX('Tablero (To Do · Doing · Done)'!$F$6:$F$266,MATCH(6,'Tablero (To Do · Doing · Done)'!$T$6:$T$266,0))&" · "&INDEX('Tablero (To Do · Doing · Done)'!$G$6:$G$266,MATCH(6,'Tablero (To Do · Doing · Done)'!$T$6:$T$266,0)),"") | H11: =IFERROR(INDEX('Tablero (To Do · Doing · Done)'!$B$6:$B$266,MATCH(6,'Tablero (To Do · Doing · Done)'!$U$6:$U$266,0)),"") | I11: =IFERROR(INDEX('Tablero (To Do · Doing · Done)'!$F$6:$F$266,MATCH(6,'Tablero (To Do · Doing · Done)'!$U$6:$U$266,0))&" · "&INDEX('Tablero (To Do · Doing · Done)'!$G$6:$G$266,MATCH(6,'Tablero (To Do · Doing · Done)'!$U$6:$U$266,0)),"")
B12: =IFERROR(INDEX('Tablero (To Do · Doing · Done)'!$B$6:$B$266,MATCH(7,'Tablero (To Do · Doing · Done)'!$S$6:$S$266,0)),"") | C12: =IFERROR(INDEX('Tablero (To Do · Doing · Done)'!$F$6:$F$266,MATCH(7,'Tablero (To Do · Doing · Done)'!$S$6:$S$266,0))&" · "&INDEX('Tablero (To Do · Doing · Done)'!$G$6:$G$266,MATCH(7,'Tablero (To Do · Doing · Done)'!$S$6:$S$266,0)),"") | E12: =IFERROR(INDEX('Tablero (To Do · Doing · Done)'!$B$6:$B$266,MATCH(7,'Tablero (To Do · Doing · Done)'!$T$6:$T$266,0)),"") | F12: =IFERROR(INDEX('Tablero (To Do · Doing · Done)'!$F$6:$F$266,MATCH(7,'Tablero (To Do · Doing · Done)'!$T$6:$T$266,0))&" · "&INDEX('Tablero (To Do · Doing · Done)'!$G$6:$G$266,MATCH(7,'Tablero (To Do · Doing · Done)'!$T$6:$T$266,0)),"") | H12: =IFERROR(INDEX('Tablero (To Do · Doing · Done)'!$B$6:$B$266,MATCH(7,'Tablero (To Do · Doing · Done)'!$U$6:$U$266,0)),"") | I12: =IFERROR(INDEX('Tablero (To Do · Doing · Done)'!$F$6:$F$266,MATCH(7,'Tablero (To Do · Doing · Done)'!$U$6:$U$266,0))&" · "&INDEX('Tablero (To Do · Doing · Done)'!$G$6:$G$266,MATCH(7,'Tablero (To Do · Doing · Done)'!$U$6:$U$266,0)),"")
B13: =IFERROR(INDEX('Tablero (To Do · Doing · Done)'!$B$6:$B$266,MATCH(8,'Tablero (To Do · Doing · Done)'!$S$6:$S$266,0)),"") | C13: =IFERROR(INDEX('Tablero (To Do · Doing · Done)'!$F$6:$F$266,MATCH(8,'Tablero (To Do · Doing · Done)'!$S$6:$S$266,0))&" · "&INDEX('Tablero (To Do · Doing · Done)'!$G$6:$G$266,MATCH(8,'Tablero (To Do · Doing · Done)'!$S$6:$S$266,0)),"") | E13: =IFERROR(INDEX('Tablero (To Do · Doing · Done)'!$B$6:$B$266,MATCH(8,'Tablero (To Do · Doing · Done)'!$T$6:$T$266,0)),"") | F13: =IFERROR(INDEX('Tablero (To Do · Doing · Done)'!$F$6:$F$266,MATCH(8,'Tablero (To Do · Doing · Done)'!$T$6:$T$266,0))&" · "&INDEX('Tablero (To Do · Doing · Done)'!$G$6:$G$266,MATCH(8,'Tablero (To Do · Doing · Done)'!$T$6:$T$266,0)),"") | H13: =IFERROR(INDEX('Tablero (To Do · Doing · Done)'!$B$6:$B$266,MATCH(8,'Tablero (To Do · Doing · Done)'!$U$6:$U$266,0)),"") | I13: =IFERROR(INDEX('Tablero (To Do · Doing · Done)'!$F$6:$F$266,MATCH(8,'Tablero (To Do · Doing · Done)'!$U$6:$U$266,0))&" · "&INDEX('Tablero (To Do · Doing · Done)'!$G$6:$G$266,MATCH(8,'Tablero (To Do · Doing · Done)'!$U$6:$U$266,0)),"")
B14: =IFERROR(INDEX('Tablero (To Do · Doing · Done)'!$B$6:$B$266,MATCH(9,'Tablero (To Do · Doing · Done)'!$S$6:$S$266,0)),"") | C14: =IFERROR(INDEX('Tablero (To Do · Doing · Done)'!$F$6:$F$266,MATCH(9,'Tablero (To Do · Doing · Done)'!$S$6:$S$266,0))&" · "&INDEX('Tablero (To Do · Doing · Done)'!$G$6:$G$266,MATCH(9,'Tablero (To Do · Doing · Done)'!$S$6:$S$266,0)),"") | E14: =IFERROR(INDEX('Tablero (To Do · Doing · Done)'!$B$6:$B$266,MATCH(9,'Tablero (To Do · Doing · Done)'!$T$6:$T$266,0)),"") | F14: =IFERROR(INDEX('Tablero (To Do · Doing · Done)'!$F$6:$F$266,MATCH(9,'Tablero (To Do · Doing · Done)'!$T$6:$T$266,0))&" · "&INDEX('Tablero (To Do · Doing · Done)'!$G$6:$G$266,MATCH(9,'Tablero (To Do · Doing · Done)'!$T$6:$T$266,0)),"") | H14: =IFERROR(INDEX('Tablero (To Do · Doing · Done)'!$B$6:$B$266,MATCH(9,'Tablero (To Do · Doing · Done)'!$U$6:$U$266,0)),"") | I14: =IFERROR(INDEX('Tablero (To Do · Doing · Done)'!$F$6:$F$266,MATCH(9,'Tablero (To Do · Doing · Done)'!$U$6:$U$266,0))&" · "&INDEX('Tablero (To Do · Doing · Done)'!$G$6:$G$266,MATCH(9,'Tablero (To Do · Doing · Done)'!$U$6:$U$266,0)),"")
B15: =IFERROR(INDEX('Tablero (To Do · Doing · Done)'!$B$6:$B$266,MATCH(10,'Tablero (To Do · Doing · Done)'!$S$6:$S$266,0)),"") | C15: =IFERROR(INDEX('Tablero (To Do · Doing · Done)'!$F$6:$F$266,MATCH(10,'Tablero (To Do · Doing · Done)'!$S$6:$S$266,0))&" · "&INDEX('Tablero (To Do · Doing · Done)'!$G$6:$G$266,MATCH(10,'Tablero (To Do · Doing · Done)'!$S$6:$S$266,0)),"") | E15: =IFERROR(INDEX('Tablero (To Do · Doing · Done)'!$B$6:$B$266,MATCH(10,'Tablero (To Do · Doing · Done)'!$T$6:$T$266,0)),"") | F15: =IFERROR(INDEX('Tablero (To Do · Doing · Done)'!$F$6:$F$266,MATCH(10,'Tablero (To Do · Doing · Done)'!$T$6:$T$266,0))&" · "&INDEX('Tablero (To Do · Doing · Done)'!$G$6:$G$266,MATCH(10,'Tablero (To Do · Doing · Done)'!$T$6:$T$266,0)),"") | H15: =IFERROR(INDEX('Tablero (To Do · Doing · Done)'!$B$6:$B$266,MATCH(10,'Tablero (To Do · Doing · Done)'!$U$6:$U$266,0)),"") | I15: =IFERROR(INDEX('Tablero (To Do · Doing · Done)'!$F$6:$F$266,MATCH(10,'Tablero (To Do · Doing · Done)'!$U$6:$U$266,0))&" · "&INDEX('Tablero (To Do · Doing · Done)'!$G$6:$G$266,MATCH(10,'Tablero (To Do · Doing · Done)'!$U$6:$U$266,0)),"")
B16: =IFERROR(INDEX('Tablero (To Do · Doing · Done)'!$B$6:$B$266,MATCH(11,'Tablero (To Do · Doing · Done)'!$S$6:$S$266,0)),"") | C16: =IFERROR(INDEX('Tablero (To Do · Doing · Done)'!$F$6:$F$266,MATCH(11,'Tablero (To Do · Doing · Done)'!$S$6:$S$266,0))&" · "&INDEX('Tablero (To Do · Doing · Done)'!$G$6:$G$266,MATCH(11,'Tablero (To Do · Doing · Done)'!$S$6:$S$266,0)),"") | E16: =IFERROR(INDEX('Tablero (To Do · Doing · Done)'!$B$6:$B$266,MATCH(11,'Tablero (To Do · Doing · Done)'!$T$6:$T$266,0)),"") | F16: =IFERROR(INDEX('Tablero (To Do · Doing · Done)'!$F$6:$F$266,MATCH(11,'Tablero (To Do · Doing · Done)'!$T$6:$T$266,0))&" · "&INDEX('Tablero (To Do · Doing · Done)'!$G$6:$G$266,MATCH(11,'Tablero (To Do · Doing · Done)'!$T$6:$T$266,0)),"") | H16: =IFERROR(INDEX('Tablero (To Do · Doing · Done)'!$B$6:$B$266,MATCH(11,'Tablero (To Do · Doing · Done)'!$U$6:$U$266,0)),"") | I16: =IFERROR(INDEX('Tablero (To Do · Doing · Done)'!$F$6:$F$266,MATCH(11,'Tablero (To Do · Doing · Done)'!$U$6:$U$266,0))&" · "&INDEX('Tablero (To Do · Doing · Done)'!$G$6:$G$266,MATCH(11,'Tablero (To Do · Doing · Done)'!$U$6:$U$266,0)),"")
B17: =IFERROR(INDEX('Tablero (To Do · Doing · Done)'!$B$6:$B$266,MATCH(12,'Tablero (To Do · Doing · Done)'!$S$6:$S$266,0)),"") | C17: =IFERROR(INDEX('Tablero (To Do · Doing · Done)'!$F$6:$F$266,MATCH(12,'Tablero (To Do · Doing · Done)'!$S$6:$S$266,0))&" · "&INDEX('Tablero (To Do · Doing · Done)'!$G$6:$G$266,MATCH(12,'Tablero (To Do · Doing · Done)'!$S$6:$S$266,0)),"") | E17: =IFERROR(INDEX('Tablero (To Do · Doing · Done)'!$B$6:$B$266,MATCH(12,'Tablero (To Do · Doing · Done)'!$T$6:$T$266,0)),"") | F17: =IFERROR(INDEX('Tablero (To Do · Doing · Done)'!$F$6:$F$266,MATCH(12,'Tablero (To Do · Doing · Done)'!$T$6:$T$266,0))&" · "&INDEX('Tablero (To Do · Doing · Done)'!$G$6:$G$266,MATCH(12,'Tablero (To Do · Doing · Done)'!$T$6:$T$266,0)),"") | H17: =IFERROR(INDEX('Tablero (To Do · Doing · Done)'!$B$6:$B$266,MATCH(12,'Tablero (To Do · Doing · Done)'!$U$6:$U$266,0)),"") | I17: =IFERROR(INDEX('Tablero (To Do · Doing · Done)'!$F$6:$F$266,MATCH(12,'Tablero (To Do · Doing · Done)'!$U$6:$U$266,0))&" · "&INDEX('Tablero (To Do · Doing · Done)'!$G$6:$G$266,MATCH(12,'Tablero (To Do · Doing · Done)'!$U$6:$U$266,0)),"")
B18: =IFERROR(INDEX('Tablero (To Do · Doing · Done)'!$B$6:$B$266,MATCH(13,'Tablero (To Do · Doing · Done)'!$S$6:$S$266,0)),"") | C18: =IFERROR(INDEX('Tablero (To Do · Doing · Done)'!$F$6:$F$266,MATCH(13,'Tablero (To Do · Doing · Done)'!$S$6:$S$266,0))&" · "&INDEX('Tablero (To Do · Doing · Done)'!$G$6:$G$266,MATCH(13,'Tablero (To Do · Doing · Done)'!$S$6:$S$266,0)),"") | E18: =IFERROR(INDEX('Tablero (To Do · Doing · Done)'!$B$6:$B$266,MATCH(13,'Tablero (To Do · Doing · Done)'!$T$6:$T$266,0)),"") | F18: =IFERROR(INDEX('Tablero (To Do · Doing · Done)'!$F$6:$F$266,MATCH(13,'Tablero (To Do · Doing · Done)'!$T$6:$T$266,0))&" · "&INDEX('Tablero (To Do · Doing · Done)'!$G$6:$G$266,MATCH(13,'Tablero (To Do · Doing · Done)'!$T$6:$T$266,0)),"") | H18: =IFERROR(INDEX('Tablero (To Do · Doing · Done)'!$B$6:$B$266,MATCH(13,'Tablero (To Do · Doing · Done)'!$U$6:$U$266,0)),"") | I18: =IFERROR(INDEX('Tablero (To Do · Doing · Done)'!$F$6:$F$266,MATCH(13,'Tablero (To Do · Doing · Done)'!$U$6:$U$266,0))&" · "&INDEX('Tablero (To Do · Doing · Done)'!$G$6:$G$266,MATCH(13,'Tablero (To Do · Doing · Done)'!$U$6:$U$266,0)),"")
B19: =IFERROR(INDEX('Tablero (To Do · Doing · Done)'!$B$6:$B$266,MATCH(14,'Tablero (To Do · Doing · Done)'!$S$6:$S$266,0)),"") | C19: =IFERROR(INDEX('Tablero (To Do · Doing · Done)'!$F$6:$F$266,MATCH(14,'Tablero (To Do · Doing · Done)'!$S$6:$S$266,0))&" · "&INDEX('Tablero (To Do · Doing · Done)'!$G$6:$G$266,MATCH(14,'Tablero (To Do · Doing · Done)'!$S$6:$S$266,0)),"") | E19: =IFERROR(INDEX('Tablero (To Do · Doing · Done)'!$B$6:$B$266,MATCH(14,'Tablero (To Do · Doing · Done)'!$T$6:$T$266,0)),"") | F19: =IFERROR(INDEX('Tablero (To Do · Doing · Done)'!$F$6:$F$266,MATCH(14,'Tablero (To Do · Doing · Done)'!$T$6:$T$266,0))&" · "&INDEX('Tablero (To Do · Doing · Done)'!$G$6:$G$266,MATCH(14,'Tablero (To Do · Doing · Done)'!$T$6:$T$266,0)),"") | H19: =IFERROR(INDEX('Tablero (To Do · Doing · Done)'!$B$6:$B$266,MATCH(14,'Tablero (To Do · Doing · Done)'!$U$6:$U$266,0)),"") | I19: =IFERROR(INDEX('Tablero (To Do · Doing · Done)'!$F$6:$F$266,MATCH(14,'Tablero (To Do · Doing · Done)'!$U$6:$U$266,0))&" · "&INDEX('Tablero (To Do · Doing · Done)'!$G$6:$G$266,MATCH(14,'Tablero (To Do · Doing · Done)'!$U$6:$U$266,0)),"")
B20: =IFERROR(INDEX('Tablero (To Do · Doing · Done)'!$B$6:$B$266,MATCH(15,'Tablero (To Do · Doing · Done)'!$S$6:$S$266,0)),"") | C20: =IFERROR(INDEX('Tablero (To Do · Doing · Done)'!$F$6:$F$266,MATCH(15,'Tablero (To Do · Doing · Done)'!$S$6:$S$266,0))&" · "&INDEX('Tablero (To Do · Doing · Done)'!$G$6:$G$266,MATCH(15,'Tablero (To Do · Doing · Done)'!$S$6:$S$266,0)),"") | E20: =IFERROR(INDEX('Tablero (To Do · Doing · Done)'!$B$6:$B$266,MATCH(15,'Tablero (To Do · Doing · Done)'!$T$6:$T$266,0)),"") | F20: =IFERROR(INDEX('Tablero (To Do · Doing · Done)'!$F$6:$F$266,MATCH(15,'Tablero (To Do · Doing · Done)'!$T$6:$T$266,0))&" · "&INDEX('Tablero (To Do · Doing · Done)'!$G$6:$G$266,MATCH(15,'Tablero (To Do · Doing · Done)'!$T$6:$T$266,0)),"") | H20: =IFERROR(INDEX('Tablero (To Do · Doing · Done)'!$B$6:$B$266,MATCH(15,'Tablero (To Do · Doing · Done)'!$U$6:$U$266,0)),"") | I20: =IFERROR(INDEX('Tablero (To Do · Doing · Done)'!$F$6:$F$266,MATCH(15,'Tablero (To Do · Doing · Done)'!$U$6:$U$266,0))&" · "&INDEX('Tablero (To Do · Doing · Done)'!$G$6:$G$266,MATCH(15,'Tablero (To Do · Doing · Done)'!$U$6:$U$266,0)),"")
B21: =IFERROR(INDEX('Tablero (To Do · Doing · Done)'!$B$6:$B$266,MATCH(16,'Tablero (To Do · Doing · Done)'!$S$6:$S$266,0)),"") | C21: =IFERROR(INDEX('Tablero (To Do · Doing · Done)'!$F$6:$F$266,MATCH(16,'Tablero (To Do · Doing · Done)'!$S$6:$S$266,0))&" · "&INDEX('Tablero (To Do · Doing · Done)'!$G$6:$G$266,MATCH(16,'Tablero (To Do · Doing · Done)'!$S$6:$S$266,0)),"") | E21: =IFERROR(INDEX('Tablero (To Do · Doing · Done)'!$B$6:$B$266,MATCH(16,'Tablero (To Do · Doing · Done)'!$T$6:$T$266,0)),"") | F21: =IFERROR(INDEX('Tablero (To Do · Doing · Done)'!$F$6:$F$266,MATCH(16,'Tablero (To Do · Doing · Done)'!$T$6:$T$266,0))&" · "&INDEX('Tablero (To Do · Doing · Done)'!$G$6:$G$266,MATCH(16,'Tablero (To Do · Doing · Done)'!$T$6:$T$266,0)),"") | H21: =IFERROR(INDEX('Tablero (To Do · Doing · Done)'!$B$6:$B$266,MATCH(16,'Tablero (To Do · Doing · Done)'!$U$6:$U$266,0)),"") | I21: =IFERROR(INDEX('Tablero (To Do · Doing · Done)'!$F$6:$F$266,MATCH(16,'Tablero (To Do · Doing · Done)'!$U$6:$U$266,0))&" · "&INDEX('Tablero (To Do · Doing · Done)'!$G$6:$G$266,MATCH(16,'Tablero (To Do · Doing · Done)'!$U$6:$U$266,0)),"")
B22: =IFERROR(INDEX('Tablero (To Do · Doing · Done)'!$B$6:$B$266,MATCH(17,'Tablero (To Do · Doing · Done)'!$S$6:$S$266,0)),"") | C22: =IFERROR(INDEX('Tablero (To Do · Doing · Done)'!$F$6:$F$266,MATCH(17,'Tablero (To Do · Doing · Done)'!$S$6:$S$266,0))&" · "&INDEX('Tablero (To Do · Doing · Done)'!$G$6:$G$266,MATCH(17,'Tablero (To Do · Doing · Done)'!$S$6:$S$266,0)),"") | E22: =IFERROR(INDEX('Tablero (To Do · Doing · Done)'!$B$6:$B$266,MATCH(17,'Tablero (To Do · Doing · Done)'!$T$6:$T$266,0)),"") | F22: =IFERROR(INDEX('Tablero (To Do · Doing · Done)'!$F$6:$F$266,MATCH(17,'Tablero (To Do · Doing · Done)'!$T$6:$T$266,0))&" · "&INDEX('Tablero (To Do · Doing · Done)'!$G$6:$G$266,MATCH(17,'Tablero (To Do · Doing · Done)'!$T$6:$T$266,0)),"") | H22: =IFERROR(INDEX('Tablero (To Do · Doing · Done)'!$B$6:$B$266,MATCH(17,'Tablero (To Do · Doing · Done)'!$U$6:$U$266,0)),"") | I22: =IFERROR(INDEX('Tablero (To Do · Doing · Done)'!$F$6:$F$266,MATCH(17,'Tablero (To Do · Doing · Done)'!$U$6:$U$266,0))&" · "&INDEX('Tablero (To Do · Doing · Done)'!$G$6:$G$266,MATCH(17,'Tablero (To Do · Doing · Done)'!$U$6:$U$266,0)),"")
B23: =IFERROR(INDEX('Tablero (To Do · Doing · Done)'!$B$6:$B$266,MATCH(18,'Tablero (To Do · Doing · Done)'!$S$6:$S$266,0)),"") | C23: =IFERROR(INDEX('Tablero (To Do · Doing · Done)'!$F$6:$F$266,MATCH(18,'Tablero (To Do · Doing · Done)'!$S$6:$S$266,0))&" · "&INDEX('Tablero (To Do · Doing · Done)'!$G$6:$G$266,MATCH(18,'Tablero (To Do · Doing · Done)'!$S$6:$S$266,0)),"") | E23: =IFERROR(INDEX('Tablero (To Do · Doing · Done)'!$B$6:$B$266,MATCH(18,'Tablero (To Do · Doing · Done)'!$T$6:$T$266,0)),"") | F23: =IFERROR(INDEX('Tablero (To Do · Doing · Done)'!$F$6:$F$266,MATCH(18,'Tablero (To Do · Doing · Done)'!$T$6:$T$266,0))&" · "&INDEX('Tablero (To Do · Doing · Done)'!$G$6:$G$266,MATCH(18,'Tablero (To Do · Doing · Done)'!$T$6:$T$266,0)),"") | H23: =IFERROR(INDEX('Tablero (To Do · Doing · Done)'!$B$6:$B$266,MATCH(18,'Tablero (To Do · Doing · Done)'!$U$6:$U$266,0)),"") | I23: =IFERROR(INDEX('Tablero (To Do · Doing · Done)'!$F$6:$F$266,MATCH(18,'Tablero (To Do · Doing · Done)'!$U$6:$U$266,0))&" · "&INDEX('Tablero (To Do · Doing · Done)'!$G$6:$G$266,MATCH(18,'Tablero (To Do · Doing · Done)'!$U$6:$U$266,0)),"")
B24: =IFERROR(INDEX('Tablero (To Do · Doing · Done)'!$B$6:$B$266,MATCH(19,'Tablero (To Do · Doing · Done)'!$S$6:$S$266,0)),"") | C24: =IFERROR(INDEX('Tablero (To Do · Doing · Done)'!$F$6:$F$266,MATCH(19,'Tablero (To Do · Doing · Done)'!$S$6:$S$266,0))&" · "&INDEX('Tablero (To Do · Doing · Done)'!$G$6:$G$266,MATCH(19,'Tablero (To Do · Doing · Done)'!$S$6:$S$266,0)),"") | E24: =IFERROR(INDEX('Tablero (To Do · Doing · Done)'!$B$6:$B$266,MATCH(19,'Tablero (To Do · Doing · Done)'!$T$6:$T$266,0)),"") | F24: =IFERROR(INDEX('Tablero (To Do · Doing · Done)'!$F$6:$F$266,MATCH(19,'Tablero (To Do · Doing · Done)'!$T$6:$T$266,0))&" · "&INDEX('Tablero (To Do · Doing · Done)'!$G$6:$G$266,MATCH(19,'Tablero (To Do · Doing · Done)'!$T$6:$T$266,0)),"") | H24: =IFERROR(INDEX('Tablero (To Do · Doing · Done)'!$B$6:$B$266,MATCH(19,'Tablero (To Do · Doing · Done)'!$U$6:$U$266,0)),"") | I24: =IFERROR(INDEX('Tablero (To Do · Doing · Done)'!$F$6:$F$266,MATCH(19,'Tablero (To Do · Doing · Done)'!$U$6:$U$266,0))&" · "&INDEX('Tablero (To Do · Doing · Done)'!$G$6:$G$266,MATCH(19,'Tablero (To Do · Doing · Done)'!$U$6:$U$266,0)),"")
B25: =IFERROR(INDEX('Tablero (To Do · Doing · Done)'!$B$6:$B$266,MATCH(20,'Tablero (To Do · Doing · Done)'!$S$6:$S$266,0)),"") | C25: =IFERROR(INDEX('Tablero (To Do · Doing · Done)'!$F$6:$F$266,MATCH(20,'Tablero (To Do · Doing · Done)'!$S$6:$S$266,0))&" · "&INDEX('Tablero (To Do · Doing · Done)'!$G$6:$G$266,MATCH(20,'Tablero (To Do · Doing · Done)'!$S$6:$S$266,0)),"") | E25: =IFERROR(INDEX('Tablero (To Do · Doing · Done)'!$B$6:$B$266,MATCH(20,'Tablero (To Do · Doing · Done)'!$T$6:$T$266,0)),"") | F25: =IFERROR(INDEX('Tablero (To Do · Doing · Done)'!$F$6:$F$266,MATCH(20,'Tablero (To Do · Doing · Done)'!$T$6:$T$266,0))&" · "&INDEX('Tablero (To Do · Doing · Done)'!$G$6:$G$266,MATCH(20,'Tablero (To Do · Doing · Done)'!$T$6:$T$266,0)),"") | H25: =IFERROR(INDEX('Tablero (To Do · Doing · Done)'!$B$6:$B$266,MATCH(20,'Tablero (To Do · Doing · Done)'!$U$6:$U$266,0)),"") | I25: =IFERROR(INDEX('Tablero (To Do · Doing · Done)'!$F$6:$F$266,MATCH(20,'Tablero (To Do · Doing · Done)'!$U$6:$U$266,0))&" · "&INDEX('Tablero (To Do · Doing · Done)'!$G$6:$G$266,MATCH(20,'Tablero (To Do · Doing · Done)'!$U$6:$U$266,0)),"")
B26: =IFERROR(INDEX('Tablero (To Do · Doing · Done)'!$B$6:$B$266,MATCH(21,'Tablero (To Do · Doing · Done)'!$S$6:$S$266,0)),"") | C26: =IFERROR(INDEX('Tablero (To Do · Doing · Done)'!$F$6:$F$266,MATCH(21,'Tablero (To Do · Doing · Done)'!$S$6:$S$266,0))&" · "&INDEX('Tablero (To Do · Doing · Done)'!$G$6:$G$266,MATCH(21,'Tablero (To Do · Doing · Done)'!$S$6:$S$266,0)),"") | E26: =IFERROR(INDEX('Tablero (To Do · Doing · Done)'!$B$6:$B$266,MATCH(21,'Tablero (To Do · Doing · Done)'!$T$6:$T$266,0)),"") | F26: =IFERROR(INDEX('Tablero (To Do · Doing · Done)'!$F$6:$F$266,MATCH(21,'Tablero (To Do · Doing · Done)'!$T$6:$T$266,0))&" · "&INDEX('Tablero (To Do · Doing · Done)'!$G$6:$G$266,MATCH(21,'Tablero (To Do · Doing · Done)'!$T$6:$T$266,0)),"") | H26: =IFERROR(INDEX('Tablero (To Do · Doing · Done)'!$B$6:$B$266,MATCH(21,'Tablero (To Do · Doing · Done)'!$U$6:$U$266,0)),"") | I26: =IFERROR(INDEX('Tablero (To Do · Doing · Done)'!$F$6:$F$266,MATCH(21,'Tablero (To Do · Doing · Done)'!$U$6:$U$266,0))&" · "&INDEX('Tablero (To Do · Doing · Done)'!$G$6:$G$266,MATCH(21,'Tablero (To Do · Doing · Done)'!$U$6:$U$266,0)),"")
B27: =IFERROR(INDEX('Tablero (To Do · Doing · Done)'!$B$6:$B$266,MATCH(22,'Tablero (To Do · Doing · Done)'!$S$6:$S$266,0)),"") | C27: =IFERROR(INDEX('Tablero (To Do · Doing · Done)'!$F$6:$F$266,MATCH(22,'Tablero (To Do · Doing · Done)'!$S$6:$S$266,0))&" · "&INDEX('Tablero (To Do · Doing · Done)'!$G$6:$G$266,MATCH(22,'Tablero (To Do · Doing · Done)'!$S$6:$S$266,0)),"") | E27: =IFERROR(INDEX('Tablero (To Do · Doing · Done)'!$B$6:$B$266,MATCH(22,'Tablero (To Do · Doing · Done)'!$T$6:$T$266,0)),"") | F27: =IFERROR(INDEX('Tablero (To Do · Doing · Done)'!$F$6:$F$266,MATCH(22,'Tablero (To Do · Doing · Done)'!$T$6:$T$266,0))&" · "&INDEX('Tablero (To Do · Doing · Done)'!$G$6:$G$266,MATCH(22,'Tablero (To Do · Doing · Done)'!$T$6:$T$266,0)),"") | H27: =IFERROR(INDEX('Tablero (To Do · Doing · Done)'!$B$6:$B$266,MATCH(22,'Tablero (To Do · Doing · Done)'!$U$6:$U$266,0)),"") | I27: =IFERROR(INDEX('Tablero (To Do · Doing · Done)'!$F$6:$F$266,MATCH(22,'Tablero (To Do · Doing · Done)'!$U$6:$U$266,0))&" · "&INDEX('Tablero (To Do · Doing · Done)'!$G$6:$G$266,MATCH(22,'Tablero (To Do · Doing · Done)'!$U$6:$U$266,0)),"")
B28: =IFERROR(INDEX('Tablero (To Do · Doing · Done)'!$B$6:$B$266,MATCH(23,'Tablero (To Do · Doing · Done)'!$S$6:$S$266,0)),"") | C28: =IFERROR(INDEX('Tablero (To Do · Doing · Done)'!$F$6:$F$266,MATCH(23,'Tablero (To Do · Doing · Done)'!$S$6:$S$266,0))&" · "&INDEX('Tablero (To Do · Doing · Done)'!$G$6:$G$266,MATCH(23,'Tablero (To Do · Doing · Done)'!$S$6:$S$266,0)),"") | E28: =IFERROR(INDEX('Tablero (To Do · Doing · Done)'!$B$6:$B$266,MATCH(23,'Tablero (To Do · Doing · Done)'!$T$6:$T$266,0)),"") | F28: =IFERROR(INDEX('Tablero (To Do · Doing · Done)'!$F$6:$F$266,MATCH(23,'Tablero (To Do · Doing · Done)'!$T$6:$T$266,0))&" · "&INDEX('Tablero (To Do · Doing · Done)'!$G$6:$G$266,MATCH(23,'Tablero (To Do · Doing · Done)'!$T$6:$T$266,0)),"") | H28: =IFERROR(INDEX('Tablero (To Do · Doing · Done)'!$B$6:$B$266,MATCH(23,'Tablero (To Do · Doing · Done)'!$U$6:$U$266,0)),"") | I28: =IFERROR(INDEX('Tablero (To Do · Doing · Done)'!$F$6:$F$266,MATCH(23,'Tablero (To Do · Doing · Done)'!$U$6:$U$266,0))&" · "&INDEX('Tablero (To Do · Doing · Done)'!$G$6:$G$266,MATCH(23,'Tablero (To Do · Doing · Done)'!$U$6:$U$266,0)),"")
B29: =IFERROR(INDEX('Tablero (To Do · Doing · Done)'!$B$6:$B$266,MATCH(24,'Tablero (To Do · Doing · Done)'!$S$6:$S$266,0)),"") | C29: =IFERROR(INDEX('Tablero (To Do · Doing · Done)'!$F$6:$F$266,MATCH(24,'Tablero (To Do · Doing · Done)'!$S$6:$S$266,0))&" · "&INDEX('Tablero (To Do · Doing · Done)'!$G$6:$G$266,MATCH(24,'Tablero (To Do · Doing · Done)'!$S$6:$S$266,0)),"") | E29: =IFERROR(INDEX('Tablero (To Do · Doing · Done)'!$B$6:$B$266,MATCH(24,'Tablero (To Do · Doing · Done)'!$T$6:$T$266,0)),"") | F29: =IFERROR(INDEX('Tablero (To Do · Doing · Done)'!$F$6:$F$266,MATCH(24,'Tablero (To Do · Doing · Done)'!$T$6:$T$266,0))&" · "&INDEX('Tablero (To Do · Doing · Done)'!$G$6:$G$266,MATCH(24,'Tablero (To Do · Doing · Done)'!$T$6:$T$266,0)),"") | H29: =IFERROR(INDEX('Tablero (To Do · Doing · Done)'!$B$6:$B$266,MATCH(24,'Tablero (To Do · Doing · Done)'!$U$6:$U$266,0)),"") | I29: =IFERROR(INDEX('Tablero (To Do · Doing · Done)'!$F$6:$F$266,MATCH(24,'Tablero (To Do · Doing · Done)'!$U$6:$U$266,0))&" · "&INDEX('Tablero (To Do · Doing · Done)'!$G$6:$G$266,MATCH(24,'Tablero (To Do · Doing · Done)'!$U$6:$U$266,0)),"")
B30: =IFERROR(INDEX('Tablero (To Do · Doing · Done)'!$B$6:$B$266,MATCH(25,'Tablero (To Do · Doing · Done)'!$S$6:$S$266,0)),"") | C30: =IFERROR(INDEX('Tablero (To Do · Doing · Done)'!$F$6:$F$266,MATCH(25,'Tablero (To Do · Doing · Done)'!$S$6:$S$266,0))&" · "&INDEX('Tablero (To Do · Doing · Done)'!$G$6:$G$266,MATCH(25,'Tablero (To Do · Doing · Done)'!$S$6:$S$266,0)),"") | E30: =IFERROR(INDEX('Tablero (To Do · Doing · Done)'!$B$6:$B$266,MATCH(25,'Tablero (To Do · Doing · Done)'!$T$6:$T$266,0)),"") | F30: =IFERROR(INDEX('Tablero (To Do · Doing · Done)'!$F$6:$F$266,MATCH(25,'Tablero (To Do · Doing · Done)'!$T$6:$T$266,0))&" · "&INDEX('Tablero (To Do · Doing · Done)'!$G$6:$G$266,MATCH(25,'Tablero (To Do · Doing · Done)'!$T$6:$T$266,0)),"") | H30: =IFERROR(INDEX('Tablero (To Do · Doing · Done)'!$B$6:$B$266,MATCH(25,'Tablero (To Do · Doing · Done)'!$U$6:$U$266,0)),"") | I30: =IFERROR(INDEX('Tablero (To Do · Doing · Done)'!$F$6:$F$266,MATCH(25,'Tablero (To Do · Doing · Done)'!$U$6:$U$266,0))&" · "&INDEX('Tablero (To Do · Doing · Done)'!$G$6:$G$266,MATCH(25,'Tablero (To Do · Doing · Done)'!$U$6:$U$266,0)),"")
B31: =IFERROR(INDEX('Tablero (To Do · Doing · Done)'!$B$6:$B$266,MATCH(26,'Tablero (To Do · Doing · Done)'!$S$6:$S$266,0)),"") | C31: =IFERROR(INDEX('Tablero (To Do · Doing · Done)'!$F$6:$F$266,MATCH(26,'Tablero (To Do · Doing · Done)'!$S$6:$S$266,0))&" · "&INDEX('Tablero (To Do · Doing · Done)'!$G$6:$G$266,MATCH(26,'Tablero (To Do · Doing · Done)'!$S$6:$S$266,0)),"") | E31: =IFERROR(INDEX('Tablero (To Do · Doing · Done)'!$B$6:$B$266,MATCH(26,'Tablero (To Do · Doing · Done)'!$T$6:$T$266,0)),"") | F31: =IFERROR(INDEX('Tablero (To Do · Doing · Done)'!$F$6:$F$266,MATCH(26,'Tablero (To Do · Doing · Done)'!$T$6:$T$266,0))&" · "&INDEX('Tablero (To Do · Doing · Done)'!$G$6:$G$266,MATCH(26,'Tablero (To Do · Doing · Done)'!$T$6:$T$266,0)),"") | H31: =IFERROR(INDEX('Tablero (To Do · Doing · Done)'!$B$6:$B$266,MATCH(26,'Tablero (To Do · Doing · Done)'!$U$6:$U$266,0)),"") | I31: =IFERROR(INDEX('Tablero (To Do · Doing · Done)'!$F$6:$F$266,MATCH(26,'Tablero (To Do · Doing · Done)'!$U$6:$U$266,0))&" · "&INDEX('Tablero (To Do · Doing · Done)'!$G$6:$G$266,MATCH(26,'Tablero (To Do · Doing · Done)'!$U$6:$U$266,0)),"")
B32: =IFERROR(INDEX('Tablero (To Do · Doing · Done)'!$B$6:$B$266,MATCH(27,'Tablero (To Do · Doing · Done)'!$S$6:$S$266,0)),"") | C32: =IFERROR(INDEX('Tablero (To Do · Doing · Done)'!$F$6:$F$266,MATCH(27,'Tablero (To Do · Doing · Done)'!$S$6:$S$266,0))&" · "&INDEX('Tablero (To Do · Doing · Done)'!$G$6:$G$266,MATCH(27,'Tablero (To Do · Doing · Done)'!$S$6:$S$266,0)),"") | E32: =IFERROR(INDEX('Tablero (To Do · Doing · Done)'!$B$6:$B$266,MATCH(27,'Tablero (To Do · Doing · Done)'!$T$6:$T$266,0)),"") | F32: =IFERROR(INDEX('Tablero (To Do · Doing · Done)'!$F$6:$F$266,MATCH(27,'Tablero (To Do · Doing · Done)'!$T$6:$T$266,0))&" · "&INDEX('Tablero (To Do · Doing · Done)'!$G$6:$G$266,MATCH(27,'Tablero (To Do · Doing · Done)'!$T$6:$T$266,0)),"") | H32: =IFERROR(INDEX('Tablero (To Do · Doing · Done)'!$B$6:$B$266,MATCH(27,'Tablero (To Do · Doing · Done)'!$U$6:$U$266,0)),"") | I32: =IFERROR(INDEX('Tablero (To Do · Doing · Done)'!$F$6:$F$266,MATCH(27,'Tablero (To Do · Doing · Done)'!$U$6:$U$266,0))&" · "&INDEX('Tablero (To Do · Doing · Done)'!$G$6:$G$266,MATCH(27,'Tablero (To Do · Doing · Done)'!$U$6:$U$266,0)),"")
B33: =IFERROR(INDEX('Tablero (To Do · Doing · Done)'!$B$6:$B$266,MATCH(28,'Tablero (To Do · Doing · Done)'!$S$6:$S$266,0)),"") | C33: =IFERROR(INDEX('Tablero (To Do · Doing · Done)'!$F$6:$F$266,MATCH(28,'Tablero (To Do · Doing · Done)'!$S$6:$S$266,0))&" · "&INDEX('Tablero (To Do · Doing · Done)'!$G$6:$G$266,MATCH(28,'Tablero (To Do · Doing · Done)'!$S$6:$S$266,0)),"") | E33: =IFERROR(INDEX('Tablero (To Do · Doing · Done)'!$B$6:$B$266,MATCH(28,'Tablero (To Do · Doing · Done)'!$T$6:$T$266,0)),"") | F33: =IFERROR(INDEX('Tablero (To Do · Doing · Done)'!$F$6:$F$266,MATCH(28,'Tablero (To Do · Doing · Done)'!$T$6:$T$266,0))&" · "&INDEX('Tablero (To Do · Doing · Done)'!$G$6:$G$266,MATCH(28,'Tablero (To Do · Doing · Done)'!$T$6:$T$266,0)),"") | H33: =IFERROR(INDEX('Tablero (To Do · Doing · Done)'!$B$6:$B$266,MATCH(28,'Tablero (To Do · Doing · Done)'!$U$6:$U$266,0)),"") | I33: =IFERROR(INDEX('Tablero (To Do · Doing · Done)'!$F$6:$F$266,MATCH(28,'Tablero (To Do · Doing · Done)'!$U$6:$U$266,0))&" · "&INDEX('Tablero (To Do · Doing · Done)'!$G$6:$G$266,MATCH(28,'Tablero (To Do · Doing · Done)'!$U$6:$U$266,0)),"")
B34: =IFERROR(INDEX('Tablero (To Do · Doing · Done)'!$B$6:$B$266,MATCH(29,'Tablero (To Do · Doing · Done)'!$S$6:$S$266,0)),"") | C34: =IFERROR(INDEX('Tablero (To Do · Doing · Done)'!$F$6:$F$266,MATCH(29,'Tablero (To Do · Doing · Done)'!$S$6:$S$266,0))&" · "&INDEX('Tablero (To Do · Doing · Done)'!$G$6:$G$266,MATCH(29,'Tablero (To Do · Doing · Done)'!$S$6:$S$266,0)),"") | E34: =IFERROR(INDEX('Tablero (To Do · Doing · Done)'!$B$6:$B$266,MATCH(29,'Tablero (To Do · Doing · Done)'!$T$6:$T$266,0)),"") | F34: =IFERROR(INDEX('Tablero (To Do · Doing · Done)'!$F$6:$F$266,MATCH(29,'Tablero (To Do · Doing · Done)'!$T$6:$T$266,0))&" · "&INDEX('Tablero (To Do · Doing · Done)'!$G$6:$G$266,MATCH(29,'Tablero (To Do · Doing · Done)'!$T$6:$T$266,0)),"") | H34: =IFERROR(INDEX('Tablero (To Do · Doing · Done)'!$B$6:$B$266,MATCH(29,'Tablero (To Do · Doing · Done)'!$U$6:$U$266,0)),"") | I34: =IFERROR(INDEX('Tablero (To Do · Doing · Done)'!$F$6:$F$266,MATCH(29,'Tablero (To Do · Doing · Done)'!$U$6:$U$266,0))&" · "&INDEX('Tablero (To Do · Doing · Done)'!$G$6:$G$266,MATCH(29,'Tablero (To Do · Doing · Done)'!$U$6:$U$266,0)),"")
B35: =IFERROR(INDEX('Tablero (To Do · Doing · Done)'!$B$6:$B$266,MATCH(30,'Tablero (To Do · Doing · Done)'!$S$6:$S$266,0)),"") | C35: =IFERROR(INDEX('Tablero (To Do · Doing · Done)'!$F$6:$F$266,MATCH(30,'Tablero (To Do · Doing · Done)'!$S$6:$S$266,0))&" · "&INDEX('Tablero (To Do · Doing · Done)'!$G$6:$G$266,MATCH(30,'Tablero (To Do · Doing · Done)'!$S$6:$S$266,0)),"") | E35: =IFERROR(INDEX('Tablero (To Do · Doing · Done)'!$B$6:$B$266,MATCH(30,'Tablero (To Do · Doing · Done)'!$T$6:$T$266,0)),"") | F35: =IFERROR(INDEX('Tablero (To Do · Doing · Done)'!$F$6:$F$266,MATCH(30,'Tablero (To Do · Doing · Done)'!$T$6:$T$266,0))&" · "&INDEX('Tablero (To Do · Doing · Done)'!$G$6:$G$266,MATCH(30,'Tablero (To Do · Doing · Done)'!$T$6:$T$266,0)),"") | H35: =IFERROR(INDEX('Tablero (To Do · Doing · Done)'!$B$6:$B$266,MATCH(30,'Tablero (To Do · Doing · Done)'!$U$6:$U$266,0)),"") | I35: =IFERROR(INDEX('Tablero (To Do · Doing · Done)'!$F$6:$F$266,MATCH(30,'Tablero (To Do · Doing · Done)'!$U$6:$U$266,0))&" · "&INDEX('Tablero (To Do · Doing · Done)'!$G$6:$G$266,MATCH(30,'Tablero (To Do · Doing · Done)'!$U$6:$U$266,0)),"")
B36: =IFERROR(INDEX('Tablero (To Do · Doing · Done)'!$B$6:$B$266,MATCH(31,'Tablero (To Do · Doing · Done)'!$S$6:$S$266,0)),"") | C36: =IFERROR(INDEX('Tablero (To Do · Doing · Done)'!$F$6:$F$266,MATCH(31,'Tablero (To Do · Doing · Done)'!$S$6:$S$266,0))&" · "&INDEX('Tablero (To Do · Doing · Done)'!$G$6:$G$266,MATCH(31,'Tablero (To Do · Doing · Done)'!$S$6:$S$266,0)),"") | E36: =IFERROR(INDEX('Tablero (To Do · Doing · Done)'!$B$6:$B$266,MATCH(31,'Tablero (To Do · Doing · Done)'!$T$6:$T$266,0)),"") | F36: =IFERROR(INDEX('Tablero (To Do · Doing · Done)'!$F$6:$F$266,MATCH(31,'Tablero (To Do · Doing · Done)'!$T$6:$T$266,0))&" · "&INDEX('Tablero (To Do · Doing · Done)'!$G$6:$G$266,MATCH(31,'Tablero (To Do · Doing · Done)'!$T$6:$T$266,0)),"") | H36: =IFERROR(INDEX('Tablero (To Do · Doing · Done)'!$B$6:$B$266,MATCH(31,'Tablero (To Do · Doing · Done)'!$U$6:$U$266,0)),"") | I36: =IFERROR(INDEX('Tablero (To Do · Doing · Done)'!$F$6:$F$266,MATCH(31,'Tablero (To Do · Doing · Done)'!$U$6:$U$266,0))&" · "&INDEX('Tablero (To Do · Doing · Done)'!$G$6:$G$266,MATCH(31,'Tablero (To Do · Doing · Done)'!$U$6:$U$266,0)),"")
B37: =IFERROR(INDEX('Tablero (To Do · Doing · Done)'!$B$6:$B$266,MATCH(32,'Tablero (To Do · Doing · Done)'!$S$6:$S$266,0)),"") | C37: =IFERROR(INDEX('Tablero (To Do · Doing · Done)'!$F$6:$F$266,MATCH(32,'Tablero (To Do · Doing · Done)'!$S$6:$S$266,0))&" · "&INDEX('Tablero (To Do · Doing · Done)'!$G$6:$G$266,MATCH(32,'Tablero (To Do · Doing · Done)'!$S$6:$S$266,0)),"") | E37: =IFERROR(INDEX('Tablero (To Do · Doing · Done)'!$B$6:$B$266,MATCH(32,'Tablero (To Do · Doing · Done)'!$T$6:$T$266,0)),"") | F37: =IFERROR(INDEX('Tablero (To Do · Doing · Done)'!$F$6:$F$266,MATCH(32,'Tablero (To Do · Doing · Done)'!$T$6:$T$266,0))&" · "&INDEX('Tablero (To Do · Doing · Done)'!$G$6:$G$266,MATCH(32,'Tablero (To Do · Doing · Done)'!$T$6:$T$266,0)),"") | H37: =IFERROR(INDEX('Tablero (To Do · Doing · Done)'!$B$6:$B$266,MATCH(32,'Tablero (To Do · Doing · Done)'!$U$6:$U$266,0)),"") | I37: =IFERROR(INDEX('Tablero (To Do · Doing · Done)'!$F$6:$F$266,MATCH(32,'Tablero (To Do · Doing · Done)'!$U$6:$U$266,0))&" · "&INDEX('Tablero (To Do · Doing · Done)'!$G$6:$G$266,MATCH(32,'Tablero (To Do · Doing · Done)'!$U$6:$U$266,0)),"")
B38: =IFERROR(INDEX('Tablero (To Do · Doing · Done)'!$B$6:$B$266,MATCH(33,'Tablero (To Do · Doing · Done)'!$S$6:$S$266,0)),"") | C38: =IFERROR(INDEX('Tablero (To Do · Doing · Done)'!$F$6:$F$266,MATCH(33,'Tablero (To Do · Doing · Done)'!$S$6:$S$266,0))&" · "&INDEX('Tablero (To Do · Doing · Done)'!$G$6:$G$266,MATCH(33,'Tablero (To Do · Doing · Done)'!$S$6:$S$266,0)),"") | E38: =IFERROR(INDEX('Tablero (To Do · Doing · Done)'!$B$6:$B$266,MATCH(33,'Tablero (To Do · Doing · Done)'!$T$6:$T$266,0)),"") | F38: =IFERROR(INDEX('Tablero (To Do · Doing · Done)'!$F$6:$F$266,MATCH(33,'Tablero (To Do · Doing · Done)'!$T$6:$T$266,0))&" · "&INDEX('Tablero (To Do · Doing · Done)'!$G$6:$G$266,MATCH(33,'Tablero (To Do · Doing · Done)'!$T$6:$T$266,0)),"") | H38: =IFERROR(INDEX('Tablero (To Do · Doing · Done)'!$B$6:$B$266,MATCH(33,'Tablero (To Do · Doing · Done)'!$U$6:$U$266,0)),"") | I38: =IFERROR(INDEX('Tablero (To Do · Doing · Done)'!$F$6:$F$266,MATCH(33,'Tablero (To Do · Doing · Done)'!$U$6:$U$266,0))&" · "&INDEX('Tablero (To Do · Doing · Done)'!$G$6:$G$266,MATCH(33,'Tablero (To Do · Doing · Done)'!$U$6:$U$266,0)),"")
B39: =IFERROR(INDEX('Tablero (To Do · Doing · Done)'!$B$6:$B$266,MATCH(34,'Tablero (To Do · Doing · Done)'!$S$6:$S$266,0)),"") | C39: =IFERROR(INDEX('Tablero (To Do · Doing · Done)'!$F$6:$F$266,MATCH(34,'Tablero (To Do · Doing · Done)'!$S$6:$S$266,0))&" · "&INDEX('Tablero (To Do · Doing · Done)'!$G$6:$G$266,MATCH(34,'Tablero (To Do · Doing · Done)'!$S$6:$S$266,0)),"") | E39: =IFERROR(INDEX('Tablero (To Do · Doing · Done)'!$B$6:$B$266,MATCH(34,'Tablero (To Do · Doing · Done)'!$T$6:$T$266,0)),"") | F39: =IFERROR(INDEX('Tablero (To Do · Doing · Done)'!$F$6:$F$266,MATCH(34,'Tablero (To Do · Doing · Done)'!$T$6:$T$266,0))&" · "&INDEX('Tablero (To Do · Doing · Done)'!$G$6:$G$266,MATCH(34,'Tablero (To Do · Doing · Done)'!$T$6:$T$266,0)),"") | H39: =IFERROR(INDEX('Tablero (To Do · Doing · Done)'!$B$6:$B$266,MATCH(34,'Tablero (To Do · Doing · Done)'!$U$6:$U$266,0)),"") | I39: =IFERROR(INDEX('Tablero (To Do · Doing · Done)'!$F$6:$F$266,MATCH(34,'Tablero (To Do · Doing · Done)'!$U$6:$U$266,0))&" · "&INDEX('Tablero (To Do · Doing · Done)'!$G$6:$G$266,MATCH(34,'Tablero (To Do · Doing · Done)'!$U$6:$U$266,0)),"")
B40: =IFERROR(INDEX('Tablero (To Do · Doing · Done)'!$B$6:$B$266,MATCH(35,'Tablero (To Do · Doing · Done)'!$S$6:$S$266,0)),"") | C40: =IFERROR(INDEX('Tablero (To Do · Doing · Done)'!$F$6:$F$266,MATCH(35,'Tablero (To Do · Doing · Done)'!$S$6:$S$266,0))&" · "&INDEX('Tablero (To Do · Doing · Done)'!$G$6:$G$266,MATCH(35,'Tablero (To Do · Doing · Done)'!$S$6:$S$266,0)),"") | E40: =IFERROR(INDEX('Tablero (To Do · Doing · Done)'!$B$6:$B$266,MATCH(35,'Tablero (To Do · Doing · Done)'!$T$6:$T$266,0)),"") | F40: =IFERROR(INDEX('Tablero (To Do · Doing · Done)'!$F$6:$F$266,MATCH(35,'Tablero (To Do · Doing · Done)'!$T$6:$T$266,0))&" · "&INDEX('Tablero (To Do · Doing · Done)'!$G$6:$G$266,MATCH(35,'Tablero (To Do · Doing · Done)'!$T$6:$T$266,0)),"") | H40: =IFERROR(INDEX('Tablero (To Do · Doing · Done)'!$B$6:$B$266,MATCH(35,'Tablero (To Do · Doing · Done)'!$U$6:$U$266,0)),"") | I40: =IFERROR(INDEX('Tablero (To Do · Doing · Done)'!$F$6:$F$266,MATCH(35,'Tablero (To Do · Doing · Done)'!$U$6:$U$266,0))&" · "&INDEX('Tablero (To Do · Doing · Done)'!$G$6:$G$266,MATCH(35,'Tablero (To Do · Doing · Done)'!$U$6:$U$266,0)),"")
B41: =IFERROR(INDEX('Tablero (To Do · Doing · Done)'!$B$6:$B$266,MATCH(36,'Tablero (To Do · Doing · Done)'!$S$6:$S$266,0)),"") | C41: =IFERROR(INDEX('Tablero (To Do · Doing · Done)'!$F$6:$F$266,MATCH(36,'Tablero (To Do · Doing · Done)'!$S$6:$S$266,0))&" · "&INDEX('Tablero (To Do · Doing · Done)'!$G$6:$G$266,MATCH(36,'Tablero (To Do · Doing · Done)'!$S$6:$S$266,0)),"") | E41: =IFERROR(INDEX('Tablero (To Do · Doing · Done)'!$B$6:$B$266,MATCH(36,'Tablero (To Do · Doing · Done)'!$T$6:$T$266,0)),"") | F41: =IFERROR(INDEX('Tablero (To Do · Doing · Done)'!$F$6:$F$266,MATCH(36,'Tablero (To Do · Doing · Done)'!$T$6:$T$266,0))&" · "&INDEX('Tablero (To Do · Doing · Done)'!$G$6:$G$266,MATCH(36,'Tablero (To Do · Doing · Done)'!$T$6:$T$266,0)),"") | H41: =IFERROR(INDEX('Tablero (To Do · Doing · Done)'!$B$6:$B$266,MATCH(36,'Tablero (To Do · Doing · Done)'!$U$6:$U$266,0)),"") | I41: =IFERROR(INDEX('Tablero (To Do · Doing · Done)'!$F$6:$F$266,MATCH(36,'Tablero (To Do · Doing · Done)'!$U$6:$U$266,0))&" · "&INDEX('Tablero (To Do · Doing · Done)'!$G$6:$G$266,MATCH(36,'Tablero (To Do · Doing · Done)'!$U$6:$U$266,0)),"")
B42: =IFERROR(INDEX('Tablero (To Do · Doing · Done)'!$B$6:$B$266,MATCH(37,'Tablero (To Do · Doing · Done)'!$S$6:$S$266,0)),"") | C42: =IFERROR(INDEX('Tablero (To Do · Doing · Done)'!$F$6:$F$266,MATCH(37,'Tablero (To Do · Doing · Done)'!$S$6:$S$266,0))&" · "&INDEX('Tablero (To Do · Doing · Done)'!$G$6:$G$266,MATCH(37,'Tablero (To Do · Doing · Done)'!$S$6:$S$266,0)),"") | E42: =IFERROR(INDEX('Tablero (To Do · Doing · Done)'!$B$6:$B$266,MATCH(37,'Tablero (To Do · Doing · Done)'!$T$6:$T$266,0)),"") | F42: =IFERROR(INDEX('Tablero (To Do · Doing · Done)'!$F$6:$F$266,MATCH(37,'Tablero (To Do · Doing · Done)'!$T$6:$T$266,0))&" · "&INDEX('Tablero (To Do · Doing · Done)'!$G$6:$G$266,MATCH(37,'Tablero (To Do · Doing · Done)'!$T$6:$T$266,0)),"") | H42: =IFERROR(INDEX('Tablero (To Do · Doing · Done)'!$B$6:$B$266,MATCH(37,'Tablero (To Do · Doing · Done)'!$U$6:$U$266,0)),"") | I42: =IFERROR(INDEX('Tablero (To Do · Doing · Done)'!$F$6:$F$266,MATCH(37,'Tablero (To Do · Doing · Done)'!$U$6:$U$266,0))&" · "&INDEX('Tablero (To Do · Doing · Done)'!$G$6:$G$266,MATCH(37,'Tablero (To Do · Doing · Done)'!$U$6:$U$266,0)),"")
B43: =IFERROR(INDEX('Tablero (To Do · Doing · Done)'!$B$6:$B$266,MATCH(38,'Tablero (To Do · Doing · Done)'!$S$6:$S$266,0)),"") | C43: =IFERROR(INDEX('Tablero (To Do · Doing · Done)'!$F$6:$F$266,MATCH(38,'Tablero (To Do · Doing · Done)'!$S$6:$S$266,0))&" · "&INDEX('Tablero (To Do · Doing · Done)'!$G$6:$G$266,MATCH(38,'Tablero (To Do · Doing · Done)'!$S$6:$S$266,0)),"") | E43: =IFERROR(INDEX('Tablero (To Do · Doing · Done)'!$B$6:$B$266,MATCH(38,'Tablero (To Do · Doing · Done)'!$T$6:$T$266,0)),"") | F43: =IFERROR(INDEX('Tablero (To Do · Doing · Done)'!$F$6:$F$266,MATCH(38,'Tablero (To Do · Doing · Done)'!$T$6:$T$266,0))&" · "&INDEX('Tablero (To Do · Doing · Done)'!$G$6:$G$266,MATCH(38,'Tablero (To Do · Doing · Done)'!$T$6:$T$266,0)),"") | H43: =IFERROR(INDEX('Tablero (To Do · Doing · Done)'!$B$6:$B$266,MATCH(38,'Tablero (To Do · Doing · Done)'!$U$6:$U$266,0)),"") | I43: =IFERROR(INDEX('Tablero (To Do · Doing · Done)'!$F$6:$F$266,MATCH(38,'Tablero (To Do · Doing · Done)'!$U$6:$U$266,0))&" · "&INDEX('Tablero (To Do · Doing · Done)'!$G$6:$G$266,MATCH(38,'Tablero (To Do · Doing · Done)'!$U$6:$U$266,0)),"")
B44: =IFERROR(INDEX('Tablero (To Do · Doing · Done)'!$B$6:$B$266,MATCH(39,'Tablero (To Do · Doing · Done)'!$S$6:$S$266,0)),"") | C44: =IFERROR(INDEX('Tablero (To Do · Doing · Done)'!$F$6:$F$266,MATCH(39,'Tablero (To Do · Doing · Done)'!$S$6:$S$266,0))&" · "&INDEX('Tablero (To Do · Doing · Done)'!$G$6:$G$266,MATCH(39,'Tablero (To Do · Doing · Done)'!$S$6:$S$266,0)),"") | E44: =IFERROR(INDEX('Tablero (To Do · Doing · Done)'!$B$6:$B$266,MATCH(39,'Tablero (To Do · Doing · Done)'!$T$6:$T$266,0)),"") | F44: =IFERROR(INDEX('Tablero (To Do · Doing · Done)'!$F$6:$F$266,MATCH(39,'Tablero (To Do · Doing · Done)'!$T$6:$T$266,0))&" · "&INDEX('Tablero (To Do · Doing · Done)'!$G$6:$G$266,MATCH(39,'Tablero (To Do · Doing · Done)'!$T$6:$T$266,0)),"") | H44: =IFERROR(INDEX('Tablero (To Do · Doing · Done)'!$B$6:$B$266,MATCH(39,'Tablero (To Do · Doing · Done)'!$U$6:$U$266,0)),"") | I44: =IFERROR(INDEX('Tablero (To Do · Doing · Done)'!$F$6:$F$266,MATCH(39,'Tablero (To Do · Doing · Done)'!$U$6:$U$266,0))&" · "&INDEX('Tablero (To Do · Doing · Done)'!$G$6:$G$266,MATCH(39,'Tablero (To Do · Doing · Done)'!$U$6:$U$266,0)),"")
B45: =IFERROR(INDEX('Tablero (To Do · Doing · Done)'!$B$6:$B$266,MATCH(40,'Tablero (To Do · Doing · Done)'!$S$6:$S$266,0)),"") | C45: =IFERROR(INDEX('Tablero (To Do · Doing · Done)'!$F$6:$F$266,MATCH(40,'Tablero (To Do · Doing · Done)'!$S$6:$S$266,0))&" · "&INDEX('Tablero (To Do · Doing · Done)'!$G$6:$G$266,MATCH(40,'Tablero (To Do · Doing · Done)'!$S$6:$S$266,0)),"") | E45: =IFERROR(INDEX('Tablero (To Do · Doing · Done)'!$B$6:$B$266,MATCH(40,'Tablero (To Do · Doing · Done)'!$T$6:$T$266,0)),"") | F45: =IFERROR(INDEX('Tablero (To Do · Doing · Done)'!$F$6:$F$266,MATCH(40,'Tablero (To Do · Doing · Done)'!$T$6:$T$266,0))&" · "&INDEX('Tablero (To Do · Doing · Done)'!$G$6:$G$266,MATCH(40,'Tablero (To Do · Doing · Done)'!$T$6:$T$266,0)),"") | H45: =IFERROR(INDEX('Tablero (To Do · Doing · Done)'!$B$6:$B$266,MATCH(40,'Tablero (To Do · Doing · Done)'!$U$6:$U$266,0)),"") | I45: =IFERROR(INDEX('Tablero (To Do · Doing · Done)'!$F$6:$F$266,MATCH(40,'Tablero (To Do · Doing · Done)'!$U$6:$U$266,0))&" · "&INDEX('Tablero (To Do · Doing · Done)'!$G$6:$G$266,MATCH(40,'Tablero (To Do · Doing · Done)'!$U$6:$U$266,0)),"")
B46: =IFERROR(INDEX('Tablero (To Do · Doing · Done)'!$B$6:$B$266,MATCH(41,'Tablero (To Do · Doing · Done)'!$S$6:$S$266,0)),"") | C46: =IFERROR(INDEX('Tablero (To Do · Doing · Done)'!$F$6:$F$266,MATCH(41,'Tablero (To Do · Doing · Done)'!$S$6:$S$266,0))&" · "&INDEX('Tablero (To Do · Doing · Done)'!$G$6:$G$266,MATCH(41,'Tablero (To Do · Doing · Done)'!$S$6:$S$266,0)),"") | E46: =IFERROR(INDEX('Tablero (To Do · Doing · Done)'!$B$6:$B$266,MATCH(41,'Tablero (To Do · Doing · Done)'!$T$6:$T$266,0)),"") | F46: =IFERROR(INDEX('Tablero (To Do · Doing · Done)'!$F$6:$F$266,MATCH(41,'Tablero (To Do · Doing · Done)'!$T$6:$T$266,0))&" · "&INDEX('Tablero (To Do · Doing · Done)'!$G$6:$G$266,MATCH(41,'Tablero (To Do · Doing · Done)'!$T$6:$T$266,0)),"") | H46: =IFERROR(INDEX('Tablero (To Do · Doing · Done)'!$B$6:$B$266,MATCH(41,'Tablero (To Do · Doing · Done)'!$U$6:$U$266,0)),"") | I46: =IFERROR(INDEX('Tablero (To Do · Doing · Done)'!$F$6:$F$266,MATCH(41,'Tablero (To Do · Doing · Done)'!$U$6:$U$266,0))&" · "&INDEX('Tablero (To Do · Doing · Done)'!$G$6:$G$266,MATCH(41,'Tablero (To Do · Doing · Done)'!$U$6:$U$266,0)),"")
B47: =IFERROR(INDEX('Tablero (To Do · Doing · Done)'!$B$6:$B$266,MATCH(42,'Tablero (To Do · Doing · Done)'!$S$6:$S$266,0)),"") | C47: =IFERROR(INDEX('Tablero (To Do · Doing · Done)'!$F$6:$F$266,MATCH(42,'Tablero (To Do · Doing · Done)'!$S$6:$S$266,0))&" · "&INDEX('Tablero (To Do · Doing · Done)'!$G$6:$G$266,MATCH(42,'Tablero (To Do · Doing · Done)'!$S$6:$S$266,0)),"") | E47: =IFERROR(INDEX('Tablero (To Do · Doing · Done)'!$B$6:$B$266,MATCH(42,'Tablero (To Do · Doing · Done)'!$T$6:$T$266,0)),"") | F47: =IFERROR(INDEX('Tablero (To Do · Doing · Done)'!$F$6:$F$266,MATCH(42,'Tablero (To Do · Doing · Done)'!$T$6:$T$266,0))&" · "&INDEX('Tablero (To Do · Doing · Done)'!$G$6:$G$266,MATCH(42,'Tablero (To Do · Doing · Done)'!$T$6:$T$266,0)),"") | H47: =IFERROR(INDEX('Tablero (To Do · Doing · Done)'!$B$6:$B$266,MATCH(42,'Tablero (To Do · Doing · Done)'!$U$6:$U$266,0)),"") | I47: =IFERROR(INDEX('Tablero (To Do · Doing · Done)'!$F$6:$F$266,MATCH(42,'Tablero (To Do · Doing · Done)'!$U$6:$U$266,0))&" · "&INDEX('Tablero (To Do · Doing · Done)'!$G$6:$G$266,MATCH(42,'Tablero (To Do · Doing · Done)'!$U$6:$U$266,0)),"")
B48: =IFERROR(INDEX('Tablero (To Do · Doing · Done)'!$B$6:$B$266,MATCH(43,'Tablero (To Do · Doing · Done)'!$S$6:$S$266,0)),"") | C48: =IFERROR(INDEX('Tablero (To Do · Doing · Done)'!$F$6:$F$266,MATCH(43,'Tablero (To Do · Doing · Done)'!$S$6:$S$266,0))&" · "&INDEX('Tablero (To Do · Doing · Done)'!$G$6:$G$266,MATCH(43,'Tablero (To Do · Doing · Done)'!$S$6:$S$266,0)),"") | E48: =IFERROR(INDEX('Tablero (To Do · Doing · Done)'!$B$6:$B$266,MATCH(43,'Tablero (To Do · Doing · Done)'!$T$6:$T$266,0)),"") | F48: =IFERROR(INDEX('Tablero (To Do · Doing · Done)'!$F$6:$F$266,MATCH(43,'Tablero (To Do · Doing · Done)'!$T$6:$T$266,0))&" · "&INDEX('Tablero (To Do · Doing · Done)'!$G$6:$G$266,MATCH(43,'Tablero (To Do · Doing · Done)'!$T$6:$T$266,0)),"") | H48: =IFERROR(INDEX('Tablero (To Do · Doing · Done)'!$B$6:$B$266,MATCH(43,'Tablero (To Do · Doing · Done)'!$U$6:$U$266,0)),"") | I48: =IFERROR(INDEX('Tablero (To Do · Doing · Done)'!$F$6:$F$266,MATCH(43,'Tablero (To Do · Doing · Done)'!$U$6:$U$266,0))&" · "&INDEX('Tablero (To Do · Doing · Done)'!$G$6:$G$266,MATCH(43,'Tablero (To Do · Doing · Done)'!$U$6:$U$266,0)),"")
B49: =IFERROR(INDEX('Tablero (To Do · Doing · Done)'!$B$6:$B$266,MATCH(44,'Tablero (To Do · Doing · Done)'!$S$6:$S$266,0)),"") | C49: =IFERROR(INDEX('Tablero (To Do · Doing · Done)'!$F$6:$F$266,MATCH(44,'Tablero (To Do · Doing · Done)'!$S$6:$S$266,0))&" · "&INDEX('Tablero (To Do · Doing · Done)'!$G$6:$G$266,MATCH(44,'Tablero (To Do · Doing · Done)'!$S$6:$S$266,0)),"") | E49: =IFERROR(INDEX('Tablero (To Do · Doing · Done)'!$B$6:$B$266,MATCH(44,'Tablero (To Do · Doing · Done)'!$T$6:$T$266,0)),"") | F49: =IFERROR(INDEX('Tablero (To Do · Doing · Done)'!$F$6:$F$266,MATCH(44,'Tablero (To Do · Doing · Done)'!$T$6:$T$266,0))&" · "&INDEX('Tablero (To Do · Doing · Done)'!$G$6:$G$266,MATCH(44,'Tablero (To Do · Doing · Done)'!$T$6:$T$266,0)),"") | H49: =IFERROR(INDEX('Tablero (To Do · Doing · Done)'!$B$6:$B$266,MATCH(44,'Tablero (To Do · Doing · Done)'!$U$6:$U$266,0)),"") | I49: =IFERROR(INDEX('Tablero (To Do · Doing · Done)'!$F$6:$F$266,MATCH(44,'Tablero (To Do · Doing · Done)'!$U$6:$U$266,0))&" · "&INDEX('Tablero (To Do · Doing · Done)'!$G$6:$G$266,MATCH(44,'Tablero (To Do · Doing · Done)'!$U$6:$U$266,0)),"")
B50: =IFERROR(INDEX('Tablero (To Do · Doing · Done)'!$B$6:$B$266,MATCH(45,'Tablero (To Do · Doing · Done)'!$S$6:$S$266,0)),"") | C50: =IFERROR(INDEX('Tablero (To Do · Doing · Done)'!$F$6:$F$266,MATCH(45,'Tablero (To Do · Doing · Done)'!$S$6:$S$266,0))&" · "&INDEX('Tablero (To Do · Doing · Done)'!$G$6:$G$266,MATCH(45,'Tablero (To Do · Doing · Done)'!$S$6:$S$266,0)),"") | E50: =IFERROR(INDEX('Tablero (To Do · Doing · Done)'!$B$6:$B$266,MATCH(45,'Tablero (To Do · Doing · Done)'!$T$6:$T$266,0)),"") | F50: =IFERROR(INDEX('Tablero (To Do · Doing · Done)'!$F$6:$F$266,MATCH(45,'Tablero (To Do · Doing · Done)'!$T$6:$T$266,0))&" · "&INDEX('Tablero (To Do · Doing · Done)'!$G$6:$G$266,MATCH(45,'Tablero (To Do · Doing · Done)'!$T$6:$T$266,0)),"") | H50: =IFERROR(INDEX('Tablero (To Do · Doing · Done)'!$B$6:$B$266,MATCH(45,'Tablero (To Do · Doing · Done)'!$U$6:$U$266,0)),"") | I50: =IFERROR(INDEX('Tablero (To Do · Doing · Done)'!$F$6:$F$266,MATCH(45,'Tablero (To Do · Doing · Done)'!$U$6:$U$266,0))&" · "&INDEX('Tablero (To Do · Doing · Done)'!$G$6:$G$266,MATCH(45,'Tablero (To Do · Doing · Done)'!$U$6:$U$266,0)),"")
B51: =IFERROR(INDEX('Tablero (To Do · Doing · Done)'!$B$6:$B$266,MATCH(46,'Tablero (To Do · Doing · Done)'!$S$6:$S$266,0)),"") | C51: =IFERROR(INDEX('Tablero (To Do · Doing · Done)'!$F$6:$F$266,MATCH(46,'Tablero (To Do · Doing · Done)'!$S$6:$S$266,0))&" · "&INDEX('Tablero (To Do · Doing · Done)'!$G$6:$G$266,MATCH(46,'Tablero (To Do · Doing · Done)'!$S$6:$S$266,0)),"") | E51: =IFERROR(INDEX('Tablero (To Do · Doing · Done)'!$B$6:$B$266,MATCH(46,'Tablero (To Do · Doing · Done)'!$T$6:$T$266,0)),"") | F51: =IFERROR(INDEX('Tablero (To Do · Doing · Done)'!$F$6:$F$266,MATCH(46,'Tablero (To Do · Doing · Done)'!$T$6:$T$266,0))&" · "&INDEX('Tablero (To Do · Doing · Done)'!$G$6:$G$266,MATCH(46,'Tablero (To Do · Doing · Done)'!$T$6:$T$266,0)),"") | H51: =IFERROR(INDEX('Tablero (To Do · Doing · Done)'!$B$6:$B$266,MATCH(46,'Tablero (To Do · Doing · Done)'!$U$6:$U$266,0)),"") | I51: =IFERROR(INDEX('Tablero (To Do · Doing · Done)'!$F$6:$F$266,MATCH(46,'Tablero (To Do · Doing · Done)'!$U$6:$U$266,0))&" · "&INDEX('Tablero (To Do · Doing · Done)'!$G$6:$G$266,MATCH(46,'Tablero (To Do · Doing · Done)'!$U$6:$U$266,0)),"")
B52: =IFERROR(INDEX('Tablero (To Do · Doing · Done)'!$B$6:$B$266,MATCH(47,'Tablero (To Do · Doing · Done)'!$S$6:$S$266,0)),"") | C52: =IFERROR(INDEX('Tablero (To Do · Doing · Done)'!$F$6:$F$266,MATCH(47,'Tablero (To Do · Doing · Done)'!$S$6:$S$266,0))&" · "&INDEX('Tablero (To Do · Doing · Done)'!$G$6:$G$266,MATCH(47,'Tablero (To Do · Doing · Done)'!$S$6:$S$266,0)),"") | E52: =IFERROR(INDEX('Tablero (To Do · Doing · Done)'!$B$6:$B$266,MATCH(47,'Tablero (To Do · Doing · Done)'!$T$6:$T$266,0)),"") | F52: =IFERROR(INDEX('Tablero (To Do · Doing · Done)'!$F$6:$F$266,MATCH(47,'Tablero (To Do · Doing · Done)'!$T$6:$T$266,0))&" · "&INDEX('Tablero (To Do · Doing · Done)'!$G$6:$G$266,MATCH(47,'Tablero (To Do · Doing · Done)'!$T$6:$T$266,0)),"") | H52: =IFERROR(INDEX('Tablero (To Do · Doing · Done)'!$B$6:$B$266,MATCH(47,'Tablero (To Do · Doing · Done)'!$U$6:$U$266,0)),"") | I52: =IFERROR(INDEX('Tablero (To Do · Doing · Done)'!$F$6:$F$266,MATCH(47,'Tablero (To Do · Doing · Done)'!$U$6:$U$266,0))&" · "&INDEX('Tablero (To Do · Doing · Done)'!$G$6:$G$266,MATCH(47,'Tablero (To Do · Doing · Done)'!$U$6:$U$266,0)),"")
B53: =IFERROR(INDEX('Tablero (To Do · Doing · Done)'!$B$6:$B$266,MATCH(48,'Tablero (To Do · Doing · Done)'!$S$6:$S$266,0)),"") | C53: =IFERROR(INDEX('Tablero (To Do · Doing · Done)'!$F$6:$F$266,MATCH(48,'Tablero (To Do · Doing · Done)'!$S$6:$S$266,0))&" · "&INDEX('Tablero (To Do · Doing · Done)'!$G$6:$G$266,MATCH(48,'Tablero (To Do · Doing · Done)'!$S$6:$S$266,0)),"") | E53: =IFERROR(INDEX('Tablero (To Do · Doing · Done)'!$B$6:$B$266,MATCH(48,'Tablero (To Do · Doing · Done)'!$T$6:$T$266,0)),"") | F53: =IFERROR(INDEX('Tablero (To Do · Doing · Done)'!$F$6:$F$266,MATCH(48,'Tablero (To Do · Doing · Done)'!$T$6:$T$266,0))&" · "&INDEX('Tablero (To Do · Doing · Done)'!$G$6:$G$266,MATCH(48,'Tablero (To Do · Doing · Done)'!$T$6:$T$266,0)),"") | H53: =IFERROR(INDEX('Tablero (To Do · Doing · Done)'!$B$6:$B$266,MATCH(48,'Tablero (To Do · Doing · Done)'!$U$6:$U$266,0)),"") | I53: =IFERROR(INDEX('Tablero (To Do · Doing · Done)'!$F$6:$F$266,MATCH(48,'Tablero (To Do · Doing · Done)'!$U$6:$U$266,0))&" · "&INDEX('Tablero (To Do · Doing · Done)'!$G$6:$G$266,MATCH(48,'Tablero (To Do · Doing · Done)'!$U$6:$U$266,0)),"")
B54: =IFERROR(INDEX('Tablero (To Do · Doing · Done)'!$B$6:$B$266,MATCH(49,'Tablero (To Do · Doing · Done)'!$S$6:$S$266,0)),"") | C54: =IFERROR(INDEX('Tablero (To Do · Doing · Done)'!$F$6:$F$266,MATCH(49,'Tablero (To Do · Doing · Done)'!$S$6:$S$266,0))&" · "&INDEX('Tablero (To Do · Doing · Done)'!$G$6:$G$266,MATCH(49,'Tablero (To Do · Doing · Done)'!$S$6:$S$266,0)),"") | E54: =IFERROR(INDEX('Tablero (To Do · Doing · Done)'!$B$6:$B$266,MATCH(49,'Tablero (To Do · Doing · Done)'!$T$6:$T$266,0)),"") | F54: =IFERROR(INDEX('Tablero (To Do · Doing · Done)'!$F$6:$F$266,MATCH(49,'Tablero (To Do · Doing · Done)'!$T$6:$T$266,0))&" · "&INDEX('Tablero (To Do · Doing · Done)'!$G$6:$G$266,MATCH(49,'Tablero (To Do · Doing · Done)'!$T$6:$T$266,0)),"") | H54: =IFERROR(INDEX('Tablero (To Do · Doing · Done)'!$B$6:$B$266,MATCH(49,'Tablero (To Do · Doing · Done)'!$U$6:$U$266,0)),"") | I54: =IFERROR(INDEX('Tablero (To Do · Doing · Done)'!$F$6:$F$266,MATCH(49,'Tablero (To Do · Doing · Done)'!$U$6:$U$266,0))&" · "&INDEX('Tablero (To Do · Doing · Done)'!$G$6:$G$266,MATCH(49,'Tablero (To Do · Doing · Done)'!$U$6:$U$266,0)),"")
B55: =IFERROR(INDEX('Tablero (To Do · Doing · Done)'!$B$6:$B$266,MATCH(50,'Tablero (To Do · Doing · Done)'!$S$6:$S$266,0)),"") | C55: =IFERROR(INDEX('Tablero (To Do · Doing · Done)'!$F$6:$F$266,MATCH(50,'Tablero (To Do · Doing · Done)'!$S$6:$S$266,0))&" · "&INDEX('Tablero (To Do · Doing · Done)'!$G$6:$G$266,MATCH(50,'Tablero (To Do · Doing · Done)'!$S$6:$S$266,0)),"") | E55: =IFERROR(INDEX('Tablero (To Do · Doing · Done)'!$B$6:$B$266,MATCH(50,'Tablero (To Do · Doing · Done)'!$T$6:$T$266,0)),"") | F55: =IFERROR(INDEX('Tablero (To Do · Doing · Done)'!$F$6:$F$266,MATCH(50,'Tablero (To Do · Doing · Done)'!$T$6:$T$266,0))&" · "&INDEX('Tablero (To Do · Doing · Done)'!$G$6:$G$266,MATCH(50,'Tablero (To Do · Doing · Done)'!$T$6:$T$266,0)),"") | H55: =IFERROR(INDEX('Tablero (To Do · Doing · Done)'!$B$6:$B$266,MATCH(50,'Tablero (To Do · Doing · Done)'!$U$6:$U$266,0)),"") | I55: =IFERROR(INDEX('Tablero (To Do · Doing · Done)'!$F$6:$F$266,MATCH(50,'Tablero (To Do · Doing · Done)'!$U$6:$U$266,0))&" · "&INDEX('Tablero (To Do · Doing · Done)'!$G$6:$G$266,MATCH(50,'Tablero (To Do · Doing · Done)'!$U$6:$U$266,0)),"")
B56: =IFERROR(INDEX('Tablero (To Do · Doing · Done)'!$B$6:$B$266,MATCH(51,'Tablero (To Do · Doing · Done)'!$S$6:$S$266,0)),"") | C56: =IFERROR(INDEX('Tablero (To Do · Doing · Done)'!$F$6:$F$266,MATCH(51,'Tablero (To Do · Doing · Done)'!$S$6:$S$266,0))&" · "&INDEX('Tablero (To Do · Doing · Done)'!$G$6:$G$266,MATCH(51,'Tablero (To Do · Doing · Done)'!$S$6:$S$266,0)),"") | E56: =IFERROR(INDEX('Tablero (To Do · Doing · Done)'!$B$6:$B$266,MATCH(51,'Tablero (To Do · Doing · Done)'!$T$6:$T$266,0)),"") | F56: =IFERROR(INDEX('Tablero (To Do · Doing · Done)'!$F$6:$F$266,MATCH(51,'Tablero (To Do · Doing · Done)'!$T$6:$T$266,0))&" · "&INDEX('Tablero (To Do · Doing · Done)'!$G$6:$G$266,MATCH(51,'Tablero (To Do · Doing · Done)'!$T$6:$T$266,0)),"") | H56: =IFERROR(INDEX('Tablero (To Do · Doing · Done)'!$B$6:$B$266,MATCH(51,'Tablero (To Do · Doing · Done)'!$U$6:$U$266,0)),"") | I56: =IFERROR(INDEX('Tablero (To Do · Doing · Done)'!$F$6:$F$266,MATCH(51,'Tablero (To Do · Doing · Done)'!$U$6:$U$266,0))&" · "&INDEX('Tablero (To Do · Doing · Done)'!$G$6:$G$266,MATCH(51,'Tablero (To Do · Doing · Done)'!$U$6:$U$266,0)),"")
B57: =IFERROR(INDEX('Tablero (To Do · Doing · Done)'!$B$6:$B$266,MATCH(52,'Tablero (To Do · Doing · Done)'!$S$6:$S$266,0)),"") | C57: =IFERROR(INDEX('Tablero (To Do · Doing · Done)'!$F$6:$F$266,MATCH(52,'Tablero (To Do · Doing · Done)'!$S$6:$S$266,0))&" · "&INDEX('Tablero (To Do · Doing · Done)'!$G$6:$G$266,MATCH(52,'Tablero (To Do · Doing · Done)'!$S$6:$S$266,0)),"") | E57: =IFERROR(INDEX('Tablero (To Do · Doing · Done)'!$B$6:$B$266,MATCH(52,'Tablero (To Do · Doing · Done)'!$T$6:$T$266,0)),"") | F57: =IFERROR(INDEX('Tablero (To Do · Doing · Done)'!$F$6:$F$266,MATCH(52,'Tablero (To Do · Doing · Done)'!$T$6:$T$266,0))&" · "&INDEX('Tablero (To Do · Doing · Done)'!$G$6:$G$266,MATCH(52,'Tablero (To Do · Doing · Done)'!$T$6:$T$266,0)),"") | H57: =IFERROR(INDEX('Tablero (To Do · Doing · Done)'!$B$6:$B$266,MATCH(52,'Tablero (To Do · Doing · Done)'!$U$6:$U$266,0)),"") | I57: =IFERROR(INDEX('Tablero (To Do · Doing · Done)'!$F$6:$F$266,MATCH(52,'Tablero (To Do · Doing · Done)'!$U$6:$U$266,0))&" · "&INDEX('Tablero (To Do · Doing · Done)'!$G$6:$G$266,MATCH(52,'Tablero (To Do · Doing · Done)'!$U$6:$U$266,0)),"")
B58: =IFERROR(INDEX('Tablero (To Do · Doing · Done)'!$B$6:$B$266,MATCH(53,'Tablero (To Do · Doing · Done)'!$S$6:$S$266,0)),"") | C58: =IFERROR(INDEX('Tablero (To Do · Doing · Done)'!$F$6:$F$266,MATCH(53,'Tablero (To Do · Doing · Done)'!$S$6:$S$266,0))&" · "&INDEX('Tablero (To Do · Doing · Done)'!$G$6:$G$266,MATCH(53,'Tablero (To Do · Doing · Done)'!$S$6:$S$266,0)),"") | E58: =IFERROR(INDEX('Tablero (To Do · Doing · Done)'!$B$6:$B$266,MATCH(53,'Tablero (To Do · Doing · Done)'!$T$6:$T$266,0)),"") | F58: =IFERROR(INDEX('Tablero (To Do · Doing · Done)'!$F$6:$F$266,MATCH(53,'Tablero (To Do · Doing · Done)'!$T$6:$T$266,0))&" · "&INDEX('Tablero (To Do · Doing · Done)'!$G$6:$G$266,MATCH(53,'Tablero (To Do · Doing · Done)'!$T$6:$T$266,0)),"") | H58: =IFERROR(INDEX('Tablero (To Do · Doing · Done)'!$B$6:$B$266,MATCH(53,'Tablero (To Do · Doing · Done)'!$U$6:$U$266,0)),"") | I58: =IFERROR(INDEX('Tablero (To Do · Doing · Done)'!$F$6:$F$266,MATCH(53,'Tablero (To Do · Doing · Done)'!$U$6:$U$266,0))&" · "&INDEX('Tablero (To Do · Doing · Done)'!$G$6:$G$266,MATCH(53,'Tablero (To Do · Doing · Done)'!$U$6:$U$266,0)),"")
B59: =IFERROR(INDEX('Tablero (To Do · Doing · Done)'!$B$6:$B$266,MATCH(54,'Tablero (To Do · Doing · Done)'!$S$6:$S$266,0)),"") | C59: =IFERROR(INDEX('Tablero (To Do · Doing · Done)'!$F$6:$F$266,MATCH(54,'Tablero (To Do · Doing · Done)'!$S$6:$S$266,0))&" · "&INDEX('Tablero (To Do · Doing · Done)'!$G$6:$G$266,MATCH(54,'Tablero (To Do · Doing · Done)'!$S$6:$S$266,0)),"") | E59: =IFERROR(INDEX('Tablero (To Do · Doing · Done)'!$B$6:$B$266,MATCH(54,'Tablero (To Do · Doing · Done)'!$T$6:$T$266,0)),"") | F59: =IFERROR(INDEX('Tablero (To Do · Doing · Done)'!$F$6:$F$266,MATCH(54,'Tablero (To Do · Doing · Done)'!$T$6:$T$266,0))&" · "&INDEX('Tablero (To Do · Doing · Done)'!$G$6:$G$266,MATCH(54,'Tablero (To Do · Doing · Done)'!$T$6:$T$266,0)),"") | H59: =IFERROR(INDEX('Tablero (To Do · Doing · Done)'!$B$6:$B$266,MATCH(54,'Tablero (To Do · Doing · Done)'!$U$6:$U$266,0)),"") | I59: =IFERROR(INDEX('Tablero (To Do · Doing · Done)'!$F$6:$F$266,MATCH(54,'Tablero (To Do · Doing · Done)'!$U$6:$U$266,0))&" · "&INDEX('Tablero (To Do · Doing · Done)'!$G$6:$G$266,MATCH(54,'Tablero (To Do · Doing · Done)'!$U$6:$U$266,0)),"")
B60: =IFERROR(INDEX('Tablero (To Do · Doing · Done)'!$B$6:$B$266,MATCH(55,'Tablero (To Do · Doing · Done)'!$S$6:$S$266,0)),"") | C60: =IFERROR(INDEX('Tablero (To Do · Doing · Done)'!$F$6:$F$266,MATCH(55,'Tablero (To Do · Doing · Done)'!$S$6:$S$266,0))&" · "&INDEX('Tablero (To Do · Doing · Done)'!$G$6:$G$266,MATCH(55,'Tablero (To Do · Doing · Done)'!$S$6:$S$266,0)),"") | E60: =IFERROR(INDEX('Tablero (To Do · Doing · Done)'!$B$6:$B$266,MATCH(55,'Tablero (To Do · Doing · Done)'!$T$6:$T$266,0)),"") | F60: =IFERROR(INDEX('Tablero (To Do · Doing · Done)'!$F$6:$F$266,MATCH(55,'Tablero (To Do · Doing · Done)'!$T$6:$T$266,0))&" · "&INDEX('Tablero (To Do · Doing · Done)'!$G$6:$G$266,MATCH(55,'Tablero (To Do · Doing · Done)'!$T$6:$T$266,0)),"") | H60: =IFERROR(INDEX('Tablero (To Do · Doing · Done)'!$B$6:$B$266,MATCH(55,'Tablero (To Do · Doing · Done)'!$U$6:$U$266,0)),"") | I60: =IFERROR(INDEX('Tablero (To Do · Doing · Done)'!$F$6:$F$266,MATCH(55,'Tablero (To Do · Doing · Done)'!$U$6:$U$266,0))&" · "&INDEX('Tablero (To Do · Doing · Done)'!$G$6:$G$266,MATCH(55,'Tablero (To Do · Doing · Done)'!$U$6:$U$266,0)),"")
B61: =IFERROR(INDEX('Tablero (To Do · Doing · Done)'!$B$6:$B$266,MATCH(56,'Tablero (To Do · Doing · Done)'!$S$6:$S$266,0)),"") | C61: =IFERROR(INDEX('Tablero (To Do · Doing · Done)'!$F$6:$F$266,MATCH(56,'Tablero (To Do · Doing · Done)'!$S$6:$S$266,0))&" · "&INDEX('Tablero (To Do · Doing · Done)'!$G$6:$G$266,MATCH(56,'Tablero (To Do · Doing · Done)'!$S$6:$S$266,0)),"") | E61: =IFERROR(INDEX('Tablero (To Do · Doing · Done)'!$B$6:$B$266,MATCH(56,'Tablero (To Do · Doing · Done)'!$T$6:$T$266,0)),"") | F61: =IFERROR(INDEX('Tablero (To Do · Doing · Done)'!$F$6:$F$266,MATCH(56,'Tablero (To Do · Doing · Done)'!$T$6:$T$266,0))&" · "&INDEX('Tablero (To Do · Doing · Done)'!$G$6:$G$266,MATCH(56,'Tablero (To Do · Doing · Done)'!$T$6:$T$266,0)),"") | H61: =IFERROR(INDEX('Tablero (To Do · Doing · Done)'!$B$6:$B$266,MATCH(56,'Tablero (To Do · Doing · Done)'!$U$6:$U$266,0)),"") | I61: =IFERROR(INDEX('Tablero (To Do · Doing · Done)'!$F$6:$F$266,MATCH(56,'Tablero (To Do · Doing · Done)'!$U$6:$U$266,0))&" · "&INDEX('Tablero (To Do · Doing · Done)'!$G$6:$G$266,MATCH(56,'Tablero (To Do · Doing · Done)'!$U$6:$U$266,0)),"")
B62: =IFERROR(INDEX('Tablero (To Do · Doing · Done)'!$B$6:$B$266,MATCH(57,'Tablero (To Do · Doing · Done)'!$S$6:$S$266,0)),"") | C62: =IFERROR(INDEX('Tablero (To Do · Doing · Done)'!$F$6:$F$266,MATCH(57,'Tablero (To Do · Doing · Done)'!$S$6:$S$266,0))&" · "&INDEX('Tablero (To Do · Doing · Done)'!$G$6:$G$266,MATCH(57,'Tablero (To Do · Doing · Done)'!$S$6:$S$266,0)),"") | E62: =IFERROR(INDEX('Tablero (To Do · Doing · Done)'!$B$6:$B$266,MATCH(57,'Tablero (To Do · Doing · Done)'!$T$6:$T$266,0)),"") | F62: =IFERROR(INDEX('Tablero (To Do · Doing · Done)'!$F$6:$F$266,MATCH(57,'Tablero (To Do · Doing · Done)'!$T$6:$T$266,0))&" · "&INDEX('Tablero (To Do · Doing · Done)'!$G$6:$G$266,MATCH(57,'Tablero (To Do · Doing · Done)'!$T$6:$T$266,0)),"") | H62: =IFERROR(INDEX('Tablero (To Do · Doing · Done)'!$B$6:$B$266,MATCH(57,'Tablero (To Do · Doing · Done)'!$U$6:$U$266,0)),"") | I62: =IFERROR(INDEX('Tablero (To Do · Doing · Done)'!$F$6:$F$266,MATCH(57,'Tablero (To Do · Doing · Done)'!$U$6:$U$266,0))&" · "&INDEX('Tablero (To Do · Doing · Done)'!$G$6:$G$266,MATCH(57,'Tablero (To Do · Doing · Done)'!$U$6:$U$266,0)),"")
B63: =IFERROR(INDEX('Tablero (To Do · Doing · Done)'!$B$6:$B$266,MATCH(58,'Tablero (To Do · Doing · Done)'!$S$6:$S$266,0)),"") | C63: =IFERROR(INDEX('Tablero (To Do · Doing · Done)'!$F$6:$F$266,MATCH(58,'Tablero (To Do · Doing · Done)'!$S$6:$S$266,0))&" · "&INDEX('Tablero (To Do · Doing · Done)'!$G$6:$G$266,MATCH(58,'Tablero (To Do · Doing · Done)'!$S$6:$S$266,0)),"") | E63: =IFERROR(INDEX('Tablero (To Do · Doing · Done)'!$B$6:$B$266,MATCH(58,'Tablero (To Do · Doing · Done)'!$T$6:$T$266,0)),"") | F63: =IFERROR(INDEX('Tablero (To Do · Doing · Done)'!$F$6:$F$266,MATCH(58,'Tablero (To Do · Doing · Done)'!$T$6:$T$266,0))&" · "&INDEX('Tablero (To Do · Doing · Done)'!$G$6:$G$266,MATCH(58,'Tablero (To Do · Doing · Done)'!$T$6:$T$266,0)),"") | H63: =IFERROR(INDEX('Tablero (To Do · Doing · Done)'!$B$6:$B$266,MATCH(58,'Tablero (To Do · Doing · Done)'!$U$6:$U$266,0)),"") | I63: =IFERROR(INDEX('Tablero (To Do · Doing · Done)'!$F$6:$F$266,MATCH(58,'Tablero (To Do · Doing · Done)'!$U$6:$U$266,0))&" · "&INDEX('Tablero (To Do · Doing · Done)'!$G$6:$G$266,MATCH(58,'Tablero (To Do · Doing · Done)'!$U$6:$U$266,0)),"")
B64: =IFERROR(INDEX('Tablero (To Do · Doing · Done)'!$B$6:$B$266,MATCH(59,'Tablero (To Do · Doing · Done)'!$S$6:$S$266,0)),"") | C64: =IFERROR(INDEX('Tablero (To Do · Doing · Done)'!$F$6:$F$266,MATCH(59,'Tablero (To Do · Doing · Done)'!$S$6:$S$266,0))&" · "&INDEX('Tablero (To Do · Doing · Done)'!$G$6:$G$266,MATCH(59,'Tablero (To Do · Doing · Done)'!$S$6:$S$266,0)),"") | E64: =IFERROR(INDEX('Tablero (To Do · Doing · Done)'!$B$6:$B$266,MATCH(59,'Tablero (To Do · Doing · Done)'!$T$6:$T$266,0)),"") | F64: =IFERROR(INDEX('Tablero (To Do · Doing · Done)'!$F$6:$F$266,MATCH(59,'Tablero (To Do · Doing · Done)'!$T$6:$T$266,0))&" · "&INDEX('Tablero (To Do · Doing · Done)'!$G$6:$G$266,MATCH(59,'Tablero (To Do · Doing · Done)'!$T$6:$T$266,0)),"") | H64: =IFERROR(INDEX('Tablero (To Do · Doing · Done)'!$B$6:$B$266,MATCH(59,'Tablero (To Do · Doing · Done)'!$U$6:$U$266,0)),"") | I64: =IFERROR(INDEX('Tablero (To Do · Doing · Done)'!$F$6:$F$266,MATCH(59,'Tablero (To Do · Doing · Done)'!$U$6:$U$266,0))&" · "&INDEX('Tablero (To Do · Doing · Done)'!$G$6:$G$266,MATCH(59,'Tablero (To Do · Doing · Done)'!$U$6:$U$266,0)),"")
B65: =IFERROR(INDEX('Tablero (To Do · Doing · Done)'!$B$6:$B$266,MATCH(60,'Tablero (To Do · Doing · Done)'!$S$6:$S$266,0)),"") | C65: =IFERROR(INDEX('Tablero (To Do · Doing · Done)'!$F$6:$F$266,MATCH(60,'Tablero (To Do · Doing · Done)'!$S$6:$S$266,0))&" · "&INDEX('Tablero (To Do · Doing · Done)'!$G$6:$G$266,MATCH(60,'Tablero (To Do · Doing · Done)'!$S$6:$S$266,0)),"") | E65: =IFERROR(INDEX('Tablero (To Do · Doing · Done)'!$B$6:$B$266,MATCH(60,'Tablero (To Do · Doing · Done)'!$T$6:$T$266,0)),"") | F65: =IFERROR(INDEX('Tablero (To Do · Doing · Done)'!$F$6:$F$266,MATCH(60,'Tablero (To Do · Doing · Done)'!$T$6:$T$266,0))&" · "&INDEX('Tablero (To Do · Doing · Done)'!$G$6:$G$266,MATCH(60,'Tablero (To Do · Doing · Done)'!$T$6:$T$266,0)),"") | H65: =IFERROR(INDEX('Tablero (To Do · Doing · Done)'!$B$6:$B$266,MATCH(60,'Tablero (To Do · Doing · Done)'!$U$6:$U$266,0)),"") | I65: =IFERROR(INDEX('Tablero (To Do · Doing · Done)'!$F$6:$F$266,MATCH(60,'Tablero (To Do · Doing · Done)'!$U$6:$U$266,0))&" · "&INDEX('Tablero (To Do · Doing · Done)'!$G$6:$G$266,MATCH(60,'Tablero (To Do · Doing · Done)'!$U$6:$U$266,0)),"")
B66: =IFERROR(INDEX('Tablero (To Do · Doing · Done)'!$B$6:$B$266,MATCH(61,'Tablero (To Do · Doing · Done)'!$S$6:$S$266,0)),"") | C66: =IFERROR(INDEX('Tablero (To Do · Doing · Done)'!$F$6:$F$266,MATCH(61,'Tablero (To Do · Doing · Done)'!$S$6:$S$266,0))&" · "&INDEX('Tablero (To Do · Doing · Done)'!$G$6:$G$266,MATCH(61,'Tablero (To Do · Doing · Done)'!$S$6:$S$266,0)),"") | E66: =IFERROR(INDEX('Tablero (To Do · Doing · Done)'!$B$6:$B$266,MATCH(61,'Tablero (To Do · Doing · Done)'!$T$6:$T$266,0)),"") | F66: =IFERROR(INDEX('Tablero (To Do · Doing · Done)'!$F$6:$F$266,MATCH(61,'Tablero (To Do · Doing · Done)'!$T$6:$T$266,0))&" · "&INDEX('Tablero (To Do · Doing · Done)'!$G$6:$G$266,MATCH(61,'Tablero (To Do · Doing · Done)'!$T$6:$T$266,0)),"") | H66: =IFERROR(INDEX('Tablero (To Do · Doing · Done)'!$B$6:$B$266,MATCH(61,'Tablero (To Do · Doing · Done)'!$U$6:$U$266,0)),"") | I66: =IFERROR(INDEX('Tablero (To Do · Doing · Done)'!$F$6:$F$266,MATCH(61,'Tablero (To Do · Doing · Done)'!$U$6:$U$266,0))&" · "&INDEX('Tablero (To Do · Doing · Done)'!$G$6:$G$266,MATCH(61,'Tablero (To Do · Doing · Done)'!$U$6:$U$266,0)),"")
B67: =IFERROR(INDEX('Tablero (To Do · Doing · Done)'!$B$6:$B$266,MATCH(62,'Tablero (To Do · Doing · Done)'!$S$6:$S$266,0)),"") | C67: =IFERROR(INDEX('Tablero (To Do · Doing · Done)'!$F$6:$F$266,MATCH(62,'Tablero (To Do · Doing · Done)'!$S$6:$S$266,0))&" · "&INDEX('Tablero (To Do · Doing · Done)'!$G$6:$G$266,MATCH(62,'Tablero (To Do · Doing · Done)'!$S$6:$S$266,0)),"") | E67: =IFERROR(INDEX('Tablero (To Do · Doing · Done)'!$B$6:$B$266,MATCH(62,'Tablero (To Do · Doing · Done)'!$T$6:$T$266,0)),"") | F67: =IFERROR(INDEX('Tablero (To Do · Doing · Done)'!$F$6:$F$266,MATCH(62,'Tablero (To Do · Doing · Done)'!$T$6:$T$266,0))&" · "&INDEX('Tablero (To Do · Doing · Done)'!$G$6:$G$266,MATCH(62,'Tablero (To Do · Doing · Done)'!$T$6:$T$266,0)),"") | H67: =IFERROR(INDEX('Tablero (To Do · Doing · Done)'!$B$6:$B$266,MATCH(62,'Tablero (To Do · Doing · Done)'!$U$6:$U$266,0)),"") | I67: =IFERROR(INDEX('Tablero (To Do · Doing · Done)'!$F$6:$F$266,MATCH(62,'Tablero (To Do · Doing · Done)'!$U$6:$U$266,0))&" · "&INDEX('Tablero (To Do · Doing · Done)'!$G$6:$G$266,MATCH(62,'Tablero (To Do · Doing · Done)'!$U$6:$U$266,0)),"")
B68: =IFERROR(INDEX('Tablero (To Do · Doing · Done)'!$B$6:$B$266,MATCH(63,'Tablero (To Do · Doing · Done)'!$S$6:$S$266,0)),"") | C68: =IFERROR(INDEX('Tablero (To Do · Doing · Done)'!$F$6:$F$266,MATCH(63,'Tablero (To Do · Doing · Done)'!$S$6:$S$266,0))&" · "&INDEX('Tablero (To Do · Doing · Done)'!$G$6:$G$266,MATCH(63,'Tablero (To Do · Doing · Done)'!$S$6:$S$266,0)),"") | E68: =IFERROR(INDEX('Tablero (To Do · Doing · Done)'!$B$6:$B$266,MATCH(63,'Tablero (To Do · Doing · Done)'!$T$6:$T$266,0)),"") | F68: =IFERROR(INDEX('Tablero (To Do · Doing · Done)'!$F$6:$F$266,MATCH(63,'Tablero (To Do · Doing · Done)'!$T$6:$T$266,0))&" · "&INDEX('Tablero (To Do · Doing · Done)'!$G$6:$G$266,MATCH(63,'Tablero (To Do · Doing · Done)'!$T$6:$T$266,0)),"") | H68: =IFERROR(INDEX('Tablero (To Do · Doing · Done)'!$B$6:$B$266,MATCH(63,'Tablero (To Do · Doing · Done)'!$U$6:$U$266,0)),"") | I68: =IFERROR(INDEX('Tablero (To Do · Doing · Done)'!$F$6:$F$266,MATCH(63,'Tablero (To Do · Doing · Done)'!$U$6:$U$266,0))&" · "&INDEX('Tablero (To Do · Doing · Done)'!$G$6:$G$266,MATCH(63,'Tablero (To Do · Doing · Done)'!$U$6:$U$266,0)),"")
B69: =IFERROR(INDEX('Tablero (To Do · Doing · Done)'!$B$6:$B$266,MATCH(64,'Tablero (To Do · Doing · Done)'!$S$6:$S$266,0)),"") | C69: =IFERROR(INDEX('Tablero (To Do · Doing · Done)'!$F$6:$F$266,MATCH(64,'Tablero (To Do · Doing · Done)'!$S$6:$S$266,0))&" · "&INDEX('Tablero (To Do · Doing · Done)'!$G$6:$G$266,MATCH(64,'Tablero (To Do · Doing · Done)'!$S$6:$S$266,0)),"") | E69: =IFERROR(INDEX('Tablero (To Do · Doing · Done)'!$B$6:$B$266,MATCH(64,'Tablero (To Do · Doing · Done)'!$T$6:$T$266,0)),"") | F69: =IFERROR(INDEX('Tablero (To Do · Doing · Done)'!$F$6:$F$266,MATCH(64,'Tablero (To Do · Doing · Done)'!$T$6:$T$266,0))&" · "&INDEX('Tablero (To Do · Doing · Done)'!$G$6:$G$266,MATCH(64,'Tablero (To Do · Doing · Done)'!$T$6:$T$266,0)),"") | H69: =IFERROR(INDEX('Tablero (To Do · Doing · Done)'!$B$6:$B$266,MATCH(64,'Tablero (To Do · Doing · Done)'!$U$6:$U$266,0)),"") | I69: =IFERROR(INDEX('Tablero (To Do · Doing · Done)'!$F$6:$F$266,MATCH(64,'Tablero (To Do · Doing · Done)'!$U$6:$U$266,0))&" · "&INDEX('Tablero (To Do · Doing · Done)'!$G$6:$G$266,MATCH(64,'Tablero (To Do · Doing · Done)'!$U$6:$U$266,0)),"")
B70: =IFERROR(INDEX('Tablero (To Do · Doing · Done)'!$B$6:$B$266,MATCH(65,'Tablero (To Do · Doing · Done)'!$S$6:$S$266,0)),"") | C70: =IFERROR(INDEX('Tablero (To Do · Doing · Done)'!$F$6:$F$266,MATCH(65,'Tablero (To Do · Doing · Done)'!$S$6:$S$266,0))&" · "&INDEX('Tablero (To Do · Doing · Done)'!$G$6:$G$266,MATCH(65,'Tablero (To Do · Doing · Done)'!$S$6:$S$266,0)),"") | E70: =IFERROR(INDEX('Tablero (To Do · Doing · Done)'!$B$6:$B$266,MATCH(65,'Tablero (To Do · Doing · Done)'!$T$6:$T$266,0)),"") | F70: =IFERROR(INDEX('Tablero (To Do · Doing · Done)'!$F$6:$F$266,MATCH(65,'Tablero (To Do · Doing · Done)'!$T$6:$T$266,0))&" · "&INDEX('Tablero (To Do · Doing · Done)'!$G$6:$G$266,MATCH(65,'Tablero (To Do · Doing · Done)'!$T$6:$T$266,0)),"") | H70: =IFERROR(INDEX('Tablero (To Do · Doing · Done)'!$B$6:$B$266,MATCH(65,'Tablero (To Do · Doing · Done)'!$U$6:$U$266,0)),"") | I70: =IFERROR(INDEX('Tablero (To Do · Doing · Done)'!$F$6:$F$266,MATCH(65,'Tablero (To Do · Doing · Done)'!$U$6:$U$266,0))&" · "&INDEX('Tablero (To Do · Doing · Done)'!$G$6:$G$266,MATCH(65,'Tablero (To Do · Doing · Done)'!$U$6:$U$266,0)),"")
B71: =IFERROR(INDEX('Tablero (To Do · Doing · Done)'!$B$6:$B$266,MATCH(66,'Tablero (To Do · Doing · Done)'!$S$6:$S$266,0)),"") | C71: =IFERROR(INDEX('Tablero (To Do · Doing · Done)'!$F$6:$F$266,MATCH(66,'Tablero (To Do · Doing · Done)'!$S$6:$S$266,0))&" · "&INDEX('Tablero (To Do · Doing · Done)'!$G$6:$G$266,MATCH(66,'Tablero (To Do · Doing · Done)'!$S$6:$S$266,0)),"") | E71: =IFERROR(INDEX('Tablero (To Do · Doing · Done)'!$B$6:$B$266,MATCH(66,'Tablero (To Do · Doing · Done)'!$T$6:$T$266,0)),"") | F71: =IFERROR(INDEX('Tablero (To Do · Doing · Done)'!$F$6:$F$266,MATCH(66,'Tablero (To Do · Doing · Done)'!$T$6:$T$266,0))&" · "&INDEX('Tablero (To Do · Doing · Done)'!$G$6:$G$266,MATCH(66,'Tablero (To Do · Doing · Done)'!$T$6:$T$266,0)),"") | H71: =IFERROR(INDEX('Tablero (To Do · Doing · Done)'!$B$6:$B$266,MATCH(66,'Tablero (To Do · Doing · Done)'!$U$6:$U$266,0)),"") | I71: =IFERROR(INDEX('Tablero (To Do · Doing · Done)'!$F$6:$F$266,MATCH(66,'Tablero (To Do · Doing · Done)'!$U$6:$U$266,0))&" · "&INDEX('Tablero (To Do · Doing · Done)'!$G$6:$G$266,MATCH(66,'Tablero (To Do · Doing · Done)'!$U$6:$U$266,0)),"")
B72: =IFERROR(INDEX('Tablero (To Do · Doing · Done)'!$B$6:$B$266,MATCH(67,'Tablero (To Do · Doing · Done)'!$S$6:$S$266,0)),"") | C72: =IFERROR(INDEX('Tablero (To Do · Doing · Done)'!$F$6:$F$266,MATCH(67,'Tablero (To Do · Doing · Done)'!$S$6:$S$266,0))&" · "&INDEX('Tablero (To Do · Doing · Done)'!$G$6:$G$266,MATCH(67,'Tablero (To Do · Doing · Done)'!$S$6:$S$266,0)),"") | E72: =IFERROR(INDEX('Tablero (To Do · Doing · Done)'!$B$6:$B$266,MATCH(67,'Tablero (To Do · Doing · Done)'!$T$6:$T$266,0)),"") | F72: =IFERROR(INDEX('Tablero (To Do · Doing · Done)'!$F$6:$F$266,MATCH(67,'Tablero (To Do · Doing · Done)'!$T$6:$T$266,0))&" · "&INDEX('Tablero (To Do · Doing · Done)'!$G$6:$G$266,MATCH(67,'Tablero (To Do · Doing · Done)'!$T$6:$T$266,0)),"") | H72: =IFERROR(INDEX('Tablero (To Do · Doing · Done)'!$B$6:$B$266,MATCH(67,'Tablero (To Do · Doing · Done)'!$U$6:$U$266,0)),"") | I72: =IFERROR(INDEX('Tablero (To Do · Doing · Done)'!$F$6:$F$266,MATCH(67,'Tablero (To Do · Doing · Done)'!$U$6:$U$266,0))&" · "&INDEX('Tablero (To Do · Doing · Done)'!$G$6:$G$266,MATCH(67,'Tablero (To Do · Doing · Done)'!$U$6:$U$266,0)),"")
B73: =IFERROR(INDEX('Tablero (To Do · Doing · Done)'!$B$6:$B$266,MATCH(68,'Tablero (To Do · Doing · Done)'!$S$6:$S$266,0)),"") | C73: =IFERROR(INDEX('Tablero (To Do · Doing · Done)'!$F$6:$F$266,MATCH(68,'Tablero (To Do · Doing · Done)'!$S$6:$S$266,0))&" · "&INDEX('Tablero (To Do · Doing · Done)'!$G$6:$G$266,MATCH(68,'Tablero (To Do · Doing · Done)'!$S$6:$S$266,0)),"") | E73: =IFERROR(INDEX('Tablero (To Do · Doing · Done)'!$B$6:$B$266,MATCH(68,'Tablero (To Do · Doing · Done)'!$T$6:$T$266,0)),"") | F73: =IFERROR(INDEX('Tablero (To Do · Doing · Done)'!$F$6:$F$266,MATCH(68,'Tablero (To Do · Doing · Done)'!$T$6:$T$266,0))&" · "&INDEX('Tablero (To Do · Doing · Done)'!$G$6:$G$266,MATCH(68,'Tablero (To Do · Doing · Done)'!$T$6:$T$266,0)),"") | H73: =IFERROR(INDEX('Tablero (To Do · Doing · Done)'!$B$6:$B$266,MATCH(68,'Tablero (To Do · Doing · Done)'!$U$6:$U$266,0)),"") | I73: =IFERROR(INDEX('Tablero (To Do · Doing · Done)'!$F$6:$F$266,MATCH(68,'Tablero (To Do · Doing · Done)'!$U$6:$U$266,0))&" · "&INDEX('Tablero (To Do · Doing · Done)'!$G$6:$G$266,MATCH(68,'Tablero (To Do · Doing · Done)'!$U$6:$U$266,0)),"")
B74: =IFERROR(INDEX('Tablero (To Do · Doing · Done)'!$B$6:$B$266,MATCH(69,'Tablero (To Do · Doing · Done)'!$S$6:$S$266,0)),"") | C74: =IFERROR(INDEX('Tablero (To Do · Doing · Done)'!$F$6:$F$266,MATCH(69,'Tablero (To Do · Doing · Done)'!$S$6:$S$266,0))&" · "&INDEX('Tablero (To Do · Doing · Done)'!$G$6:$G$266,MATCH(69,'Tablero (To Do · Doing · Done)'!$S$6:$S$266,0)),"") | E74: =IFERROR(INDEX('Tablero (To Do · Doing · Done)'!$B$6:$B$266,MATCH(69,'Tablero (To Do · Doing · Done)'!$T$6:$T$266,0)),"") | F74: =IFERROR(INDEX('Tablero (To Do · Doing · Done)'!$F$6:$F$266,MATCH(69,'Tablero (To Do · Doing · Done)'!$T$6:$T$266,0))&" · "&INDEX('Tablero (To Do · Doing · Done)'!$G$6:$G$266,MATCH(69,'Tablero (To Do · Doing · Done)'!$T$6:$T$266,0)),"") | H74: =IFERROR(INDEX('Tablero (To Do · Doing · Done)'!$B$6:$B$266,MATCH(69,'Tablero (To Do · Doing · Done)'!$U$6:$U$266,0)),"") | I74: =IFERROR(INDEX('Tablero (To Do · Doing · Done)'!$F$6:$F$266,MATCH(69,'Tablero (To Do · Doing · Done)'!$U$6:$U$266,0))&" · "&INDEX('Tablero (To Do · Doing · Done)'!$G$6:$G$266,MATCH(69,'Tablero (To Do · Doing · Done)'!$U$6:$U$266,0)),"")
B75: =IFERROR(INDEX('Tablero (To Do · Doing · Done)'!$B$6:$B$266,MATCH(70,'Tablero (To Do · Doing · Done)'!$S$6:$S$266,0)),"") | C75: =IFERROR(INDEX('Tablero (To Do · Doing · Done)'!$F$6:$F$266,MATCH(70,'Tablero (To Do · Doing · Done)'!$S$6:$S$266,0))&" · "&INDEX('Tablero (To Do · Doing · Done)'!$G$6:$G$266,MATCH(70,'Tablero (To Do · Doing · Done)'!$S$6:$S$266,0)),"") | E75: =IFERROR(INDEX('Tablero (To Do · Doing · Done)'!$B$6:$B$266,MATCH(70,'Tablero (To Do · Doing · Done)'!$T$6:$T$266,0)),"") | F75: =IFERROR(INDEX('Tablero (To Do · Doing · Done)'!$F$6:$F$266,MATCH(70,'Tablero (To Do · Doing · Done)'!$T$6:$T$266,0))&" · "&INDEX('Tablero (To Do · Doing · Done)'!$G$6:$G$266,MATCH(70,'Tablero (To Do · Doing · Done)'!$T$6:$T$266,0)),"") | H75: =IFERROR(INDEX('Tablero (To Do · Doing · Done)'!$B$6:$B$266,MATCH(70,'Tablero (To Do · Doing · Done)'!$U$6:$U$266,0)),"") | I75: =IFERROR(INDEX('Tablero (To Do · Doing · Done)'!$F$6:$F$266,MATCH(70,'Tablero (To Do · Doing · Done)'!$U$6:$U$266,0))&" · "&INDEX('Tablero (To Do · Doing · Done)'!$G$6:$G$266,MATCH(70,'Tablero (To Do · Doing · Done)'!$U$6:$U$266,0)),"")
B76: =IFERROR(INDEX('Tablero (To Do · Doing · Done)'!$B$6:$B$266,MATCH(71,'Tablero (To Do · Doing · Done)'!$S$6:$S$266,0)),"") | C76: =IFERROR(INDEX('Tablero (To Do · Doing · Done)'!$F$6:$F$266,MATCH(71,'Tablero (To Do · Doing · Done)'!$S$6:$S$266,0))&" · "&INDEX('Tablero (To Do · Doing · Done)'!$G$6:$G$266,MATCH(71,'Tablero (To Do · Doing · Done)'!$S$6:$S$266,0)),"") | E76: =IFERROR(INDEX('Tablero (To Do · Doing · Done)'!$B$6:$B$266,MATCH(71,'Tablero (To Do · Doing · Done)'!$T$6:$T$266,0)),"") | F76: =IFERROR(INDEX('Tablero (To Do · Doing · Done)'!$F$6:$F$266,MATCH(71,'Tablero (To Do · Doing · Done)'!$T$6:$T$266,0))&" · "&INDEX('Tablero (To Do · Doing · Done)'!$G$6:$G$266,MATCH(71,'Tablero (To Do · Doing · Done)'!$T$6:$T$266,0)),"") | H76: =IFERROR(INDEX('Tablero (To Do · Doing · Done)'!$B$6:$B$266,MATCH(71,'Tablero (To Do · Doing · Done)'!$U$6:$U$266,0)),"") | I76: =IFERROR(INDEX('Tablero (To Do · Doing · Done)'!$F$6:$F$266,MATCH(71,'Tablero (To Do · Doing · Done)'!$U$6:$U$266,0))&" · "&INDEX('Tablero (To Do · Doing · Done)'!$G$6:$G$266,MATCH(71,'Tablero (To Do · Doing · Done)'!$U$6:$U$266,0)),"")
B77: =IFERROR(INDEX('Tablero (To Do · Doing · Done)'!$B$6:$B$266,MATCH(72,'Tablero (To Do · Doing · Done)'!$S$6:$S$266,0)),"") | C77: =IFERROR(INDEX('Tablero (To Do · Doing · Done)'!$F$6:$F$266,MATCH(72,'Tablero (To Do · Doing · Done)'!$S$6:$S$266,0))&" · "&INDEX('Tablero (To Do · Doing · Done)'!$G$6:$G$266,MATCH(72,'Tablero (To Do · Doing · Done)'!$S$6:$S$266,0)),"") | E77: =IFERROR(INDEX('Tablero (To Do · Doing · Done)'!$B$6:$B$266,MATCH(72,'Tablero (To Do · Doing · Done)'!$T$6:$T$266,0)),"") | F77: =IFERROR(INDEX('Tablero (To Do · Doing · Done)'!$F$6:$F$266,MATCH(72,'Tablero (To Do · Doing · Done)'!$T$6:$T$266,0))&" · "&INDEX('Tablero (To Do · Doing · Done)'!$G$6:$G$266,MATCH(72,'Tablero (To Do · Doing · Done)'!$T$6:$T$266,0)),"") | H77: =IFERROR(INDEX('Tablero (To Do · Doing · Done)'!$B$6:$B$266,MATCH(72,'Tablero (To Do · Doing · Done)'!$U$6:$U$266,0)),"") | I77: =IFERROR(INDEX('Tablero (To Do · Doing · Done)'!$F$6:$F$266,MATCH(72,'Tablero (To Do · Doing · Done)'!$U$6:$U$266,0))&" · "&INDEX('Tablero (To Do · Doing · Done)'!$G$6:$G$266,MATCH(72,'Tablero (To Do · Doing · Done)'!$U$6:$U$266,0)),"")
B78: =IFERROR(INDEX('Tablero (To Do · Doing · Done)'!$B$6:$B$266,MATCH(73,'Tablero (To Do · Doing · Done)'!$S$6:$S$266,0)),"") | C78: =IFERROR(INDEX('Tablero (To Do · Doing · Done)'!$F$6:$F$266,MATCH(73,'Tablero (To Do · Doing · Done)'!$S$6:$S$266,0))&" · "&INDEX('Tablero (To Do · Doing · Done)'!$G$6:$G$266,MATCH(73,'Tablero (To Do · Doing · Done)'!$S$6:$S$266,0)),"") | E78: =IFERROR(INDEX('Tablero (To Do · Doing · Done)'!$B$6:$B$266,MATCH(73,'Tablero (To Do · Doing · Done)'!$T$6:$T$266,0)),"") | F78: =IFERROR(INDEX('Tablero (To Do · Doing · Done)'!$F$6:$F$266,MATCH(73,'Tablero (To Do · Doing · Done)'!$T$6:$T$266,0))&" · "&INDEX('Tablero (To Do · Doing · Done)'!$G$6:$G$266,MATCH(73,'Tablero (To Do · Doing · Done)'!$T$6:$T$266,0)),"") | H78: =IFERROR(INDEX('Tablero (To Do · Doing · Done)'!$B$6:$B$266,MATCH(73,'Tablero (To Do · Doing · Done)'!$U$6:$U$266,0)),"") | I78: =IFERROR(INDEX('Tablero (To Do · Doing · Done)'!$F$6:$F$266,MATCH(73,'Tablero (To Do · Doing · Done)'!$U$6:$U$266,0))&" · "&INDEX('Tablero (To Do · Doing · Done)'!$G$6:$G$266,MATCH(73,'Tablero (To Do · Doing · Done)'!$U$6:$U$266,0)),"")
B79: =IFERROR(INDEX('Tablero (To Do · Doing · Done)'!$B$6:$B$266,MATCH(74,'Tablero (To Do · Doing · Done)'!$S$6:$S$266,0)),"") | C79: =IFERROR(INDEX('Tablero (To Do · Doing · Done)'!$F$6:$F$266,MATCH(74,'Tablero (To Do · Doing · Done)'!$S$6:$S$266,0))&" · "&INDEX('Tablero (To Do · Doing · Done)'!$G$6:$G$266,MATCH(74,'Tablero (To Do · Doing · Done)'!$S$6:$S$266,0)),"") | E79: =IFERROR(INDEX('Tablero (To Do · Doing · Done)'!$B$6:$B$266,MATCH(74,'Tablero (To Do · Doing · Done)'!$T$6:$T$266,0)),"") | F79: =IFERROR(INDEX('Tablero (To Do · Doing · Done)'!$F$6:$F$266,MATCH(74,'Tablero (To Do · Doing · Done)'!$T$6:$T$266,0))&" · "&INDEX('Tablero (To Do · Doing · Done)'!$G$6:$G$266,MATCH(74,'Tablero (To Do · Doing · Done)'!$T$6:$T$266,0)),"") | H79: =IFERROR(INDEX('Tablero (To Do · Doing · Done)'!$B$6:$B$266,MATCH(74,'Tablero (To Do · Doing · Done)'!$U$6:$U$266,0)),"") | I79: =IFERROR(INDEX('Tablero (To Do · Doing · Done)'!$F$6:$F$266,MATCH(74,'Tablero (To Do · Doing · Done)'!$U$6:$U$266,0))&" · "&INDEX('Tablero (To Do · Doing · Done)'!$G$6:$G$266,MATCH(74,'Tablero (To Do · Doing · Done)'!$U$6:$U$266,0)),"")
B80: =IFERROR(INDEX('Tablero (To Do · Doing · Done)'!$B$6:$B$266,MATCH(75,'Tablero (To Do · Doing · Done)'!$S$6:$S$266,0)),"") | C80: =IFERROR(INDEX('Tablero (To Do · Doing · Done)'!$F$6:$F$266,MATCH(75,'Tablero (To Do · Doing · Done)'!$S$6:$S$266,0))&" · "&INDEX('Tablero (To Do · Doing · Done)'!$G$6:$G$266,MATCH(75,'Tablero (To Do · Doing · Done)'!$S$6:$S$266,0)),"") | E80: =IFERROR(INDEX('Tablero (To Do · Doing · Done)'!$B$6:$B$266,MATCH(75,'Tablero (To Do · Doing · Done)'!$T$6:$T$266,0)),"") | F80: =IFERROR(INDEX('Tablero (To Do · Doing · Done)'!$F$6:$F$266,MATCH(75,'Tablero (To Do · Doing · Done)'!$T$6:$T$266,0))&" · "&INDEX('Tablero (To Do · Doing · Done)'!$G$6:$G$266,MATCH(75,'Tablero (To Do · Doing · Done)'!$T$6:$T$266,0)),"") | H80: =IFERROR(INDEX('Tablero (To Do · Doing · Done)'!$B$6:$B$266,MATCH(75,'Tablero (To Do · Doing · Done)'!$U$6:$U$266,0)),"") | I80: =IFERROR(INDEX('Tablero (To Do · Doing · Done)'!$F$6:$F$266,MATCH(75,'Tablero (To Do · Doing · Done)'!$U$6:$U$266,0))&" · "&INDEX('Tablero (To Do · Doing · Done)'!$G$6:$G$266,MATCH(75,'Tablero (To Do · Doing · Done)'!$U$6:$U$266,0)),"")
B81: =IFERROR(INDEX('Tablero (To Do · Doing · Done)'!$B$6:$B$266,MATCH(76,'Tablero (To Do · Doing · Done)'!$S$6:$S$266,0)),"") | C81: =IFERROR(INDEX('Tablero (To Do · Doing · Done)'!$F$6:$F$266,MATCH(76,'Tablero (To Do · Doing · Done)'!$S$6:$S$266,0))&" · "&INDEX('Tablero (To Do · Doing · Done)'!$G$6:$G$266,MATCH(76,'Tablero (To Do · Doing · Done)'!$S$6:$S$266,0)),"") | E81: =IFERROR(INDEX('Tablero (To Do · Doing · Done)'!$B$6:$B$266,MATCH(76,'Tablero (To Do · Doing · Done)'!$T$6:$T$266,0)),"") | F81: =IFERROR(INDEX('Tablero (To Do · Doing · Done)'!$F$6:$F$266,MATCH(76,'Tablero (To Do · Doing · Done)'!$T$6:$T$266,0))&" · "&INDEX('Tablero (To Do · Doing · Done)'!$G$6:$G$266,MATCH(76,'Tablero (To Do · Doing · Done)'!$T$6:$T$266,0)),"") | H81: =IFERROR(INDEX('Tablero (To Do · Doing · Done)'!$B$6:$B$266,MATCH(76,'Tablero (To Do · Doing · Done)'!$U$6:$U$266,0)),"") | I81: =IFERROR(INDEX('Tablero (To Do · Doing · Done)'!$F$6:$F$266,MATCH(76,'Tablero (To Do · Doing · Done)'!$U$6:$U$266,0))&" · "&INDEX('Tablero (To Do · Doing · Done)'!$G$6:$G$266,MATCH(76,'Tablero (To Do · Doing · Done)'!$U$6:$U$266,0)),"")
B82: =IFERROR(INDEX('Tablero (To Do · Doing · Done)'!$B$6:$B$266,MATCH(77,'Tablero (To Do · Doing · Done)'!$S$6:$S$266,0)),"") | C82: =IFERROR(INDEX('Tablero (To Do · Doing · Done)'!$F$6:$F$266,MATCH(77,'Tablero (To Do · Doing · Done)'!$S$6:$S$266,0))&" · "&INDEX('Tablero (To Do · Doing · Done)'!$G$6:$G$266,MATCH(77,'Tablero (To Do · Doing · Done)'!$S$6:$S$266,0)),"") | E82: =IFERROR(INDEX('Tablero (To Do · Doing · Done)'!$B$6:$B$266,MATCH(77,'Tablero (To Do · Doing · Done)'!$T$6:$T$266,0)),"") | F82: =IFERROR(INDEX('Tablero (To Do · Doing · Done)'!$F$6:$F$266,MATCH(77,'Tablero (To Do · Doing · Done)'!$T$6:$T$266,0))&" · "&INDEX('Tablero (To Do · Doing · Done)'!$G$6:$G$266,MATCH(77,'Tablero (To Do · Doing · Done)'!$T$6:$T$266,0)),"") | H82: =IFERROR(INDEX('Tablero (To Do · Doing · Done)'!$B$6:$B$266,MATCH(77,'Tablero (To Do · Doing · Done)'!$U$6:$U$266,0)),"") | I82: =IFERROR(INDEX('Tablero (To Do · Doing · Done)'!$F$6:$F$266,MATCH(77,'Tablero (To Do · Doing · Done)'!$U$6:$U$266,0))&" · "&INDEX('Tablero (To Do · Doing · Done)'!$G$6:$G$266,MATCH(77,'Tablero (To Do · Doing · Done)'!$U$6:$U$266,0)),"")
B83: =IFERROR(INDEX('Tablero (To Do · Doing · Done)'!$B$6:$B$266,MATCH(78,'Tablero (To Do · Doing · Done)'!$S$6:$S$266,0)),"") | C83: =IFERROR(INDEX('Tablero (To Do · Doing · Done)'!$F$6:$F$266,MATCH(78,'Tablero (To Do · Doing · Done)'!$S$6:$S$266,0))&" · "&INDEX('Tablero (To Do · Doing · Done)'!$G$6:$G$266,MATCH(78,'Tablero (To Do · Doing · Done)'!$S$6:$S$266,0)),"") | E83: =IFERROR(INDEX('Tablero (To Do · Doing · Done)'!$B$6:$B$266,MATCH(78,'Tablero (To Do · Doing · Done)'!$T$6:$T$266,0)),"") | F83: =IFERROR(INDEX('Tablero (To Do · Doing · Done)'!$F$6:$F$266,MATCH(78,'Tablero (To Do · Doing · Done)'!$T$6:$T$266,0))&" · "&INDEX('Tablero (To Do · Doing · Done)'!$G$6:$G$266,MATCH(78,'Tablero (To Do · Doing · Done)'!$T$6:$T$266,0)),"") | H83: =IFERROR(INDEX('Tablero (To Do · Doing · Done)'!$B$6:$B$266,MATCH(78,'Tablero (To Do · Doing · Done)'!$U$6:$U$266,0)),"") | I83: =IFERROR(INDEX('Tablero (To Do · Doing · Done)'!$F$6:$F$266,MATCH(78,'Tablero (To Do · Doing · Done)'!$U$6:$U$266,0))&" · "&INDEX('Tablero (To Do · Doing · Done)'!$G$6:$G$266,MATCH(78,'Tablero (To Do · Doing · Done)'!$U$6:$U$266,0)),"")
B84: =IFERROR(INDEX('Tablero (To Do · Doing · Done)'!$B$6:$B$266,MATCH(79,'Tablero (To Do · Doing · Done)'!$S$6:$S$266,0)),"") | C84: =IFERROR(INDEX('Tablero (To Do · Doing · Done)'!$F$6:$F$266,MATCH(79,'Tablero (To Do · Doing · Done)'!$S$6:$S$266,0))&" · "&INDEX('Tablero (To Do · Doing · Done)'!$G$6:$G$266,MATCH(79,'Tablero (To Do · Doing · Done)'!$S$6:$S$266,0)),"") | E84: =IFERROR(INDEX('Tablero (To Do · Doing · Done)'!$B$6:$B$266,MATCH(79,'Tablero (To Do · Doing · Done)'!$T$6:$T$266,0)),"") | F84: =IFERROR(INDEX('Tablero (To Do · Doing · Done)'!$F$6:$F$266,MATCH(79,'Tablero (To Do · Doing · Done)'!$T$6:$T$266,0))&" · "&INDEX('Tablero (To Do · Doing · Done)'!$G$6:$G$266,MATCH(79,'Tablero (To Do · Doing · Done)'!$T$6:$T$266,0)),"") | H84: =IFERROR(INDEX('Tablero (To Do · Doing · Done)'!$B$6:$B$266,MATCH(79,'Tablero (To Do · Doing · Done)'!$U$6:$U$266,0)),"") | I84: =IFERROR(INDEX('Tablero (To Do · Doing · Done)'!$F$6:$F$266,MATCH(79,'Tablero (To Do · Doing · Done)'!$U$6:$U$266,0))&" · "&INDEX('Tablero (To Do · Doing · Done)'!$G$6:$G$266,MATCH(79,'Tablero (To Do · Doing · Done)'!$U$6:$U$266,0)),"")
B85: =IFERROR(INDEX('Tablero (To Do · Doing · Done)'!$B$6:$B$266,MATCH(80,'Tablero (To Do · Doing · Done)'!$S$6:$S$266,0)),"") | C85: =IFERROR(INDEX('Tablero (To Do · Doing · Done)'!$F$6:$F$266,MATCH(80,'Tablero (To Do · Doing · Done)'!$S$6:$S$266,0))&" · "&INDEX('Tablero (To Do · Doing · Done)'!$G$6:$G$266,MATCH(80,'Tablero (To Do · Doing · Done)'!$S$6:$S$266,0)),"") | E85: =IFERROR(INDEX('Tablero (To Do · Doing · Done)'!$B$6:$B$266,MATCH(80,'Tablero (To Do · Doing · Done)'!$T$6:$T$266,0)),"") | F85: =IFERROR(INDEX('Tablero (To Do · Doing · Done)'!$F$6:$F$266,MATCH(80,'Tablero (To Do · Doing · Done)'!$T$6:$T$266,0))&" · "&INDEX('Tablero (To Do · Doing · Done)'!$G$6:$G$266,MATCH(80,'Tablero (To Do · Doing · Done)'!$T$6:$T$266,0)),"") | H85: =IFERROR(INDEX('Tablero (To Do · Doing · Done)'!$B$6:$B$266,MATCH(80,'Tablero (To Do · Doing · Done)'!$U$6:$U$266,0)),"") | I85: =IFERROR(INDEX('Tablero (To Do · Doing · Done)'!$F$6:$F$266,MATCH(80,'Tablero (To Do · Doing · Done)'!$U$6:$U$266,0))&" · "&INDEX('Tablero (To Do · Doing · Done)'!$G$6:$G$266,MATCH(80,'Tablero (To Do · Doing · Done)'!$U$6:$U$266,0)),"")
B86: =IFERROR(INDEX('Tablero (To Do · Doing · Done)'!$B$6:$B$266,MATCH(81,'Tablero (To Do · Doing · Done)'!$S$6:$S$266,0)),"") | C86: =IFERROR(INDEX('Tablero (To Do · Doing · Done)'!$F$6:$F$266,MATCH(81,'Tablero (To Do · Doing · Done)'!$S$6:$S$266,0))&" · "&INDEX('Tablero (To Do · Doing · Done)'!$G$6:$G$266,MATCH(81,'Tablero (To Do · Doing · Done)'!$S$6:$S$266,0)),"") | E86: =IFERROR(INDEX('Tablero (To Do · Doing · Done)'!$B$6:$B$266,MATCH(81,'Tablero (To Do · Doing · Done)'!$T$6:$T$266,0)),"") | F86: =IFERROR(INDEX('Tablero (To Do · Doing · Done)'!$F$6:$F$266,MATCH(81,'Tablero (To Do · Doing · Done)'!$T$6:$T$266,0))&" · "&INDEX('Tablero (To Do · Doing · Done)'!$G$6:$G$266,MATCH(81,'Tablero (To Do · Doing · Done)'!$T$6:$T$266,0)),"") | H86: =IFERROR(INDEX('Tablero (To Do · Doing · Done)'!$B$6:$B$266,MATCH(81,'Tablero (To Do · Doing · Done)'!$U$6:$U$266,0)),"") | I86: =IFERROR(INDEX('Tablero (To Do · Doing · Done)'!$F$6:$F$266,MATCH(81,'Tablero (To Do · Doing · Done)'!$U$6:$U$266,0))&" · "&INDEX('Tablero (To Do · Doing · Done)'!$G$6:$G$266,MATCH(81,'Tablero (To Do · Doing · Done)'!$U$6:$U$266,0)),"")
B87: =IFERROR(INDEX('Tablero (To Do · Doing · Done)'!$B$6:$B$266,MATCH(82,'Tablero (To Do · Doing · Done)'!$S$6:$S$266,0)),"") | C87: =IFERROR(INDEX('Tablero (To Do · Doing · Done)'!$F$6:$F$266,MATCH(82,'Tablero (To Do · Doing · Done)'!$S$6:$S$266,0))&" · "&INDEX('Tablero (To Do · Doing · Done)'!$G$6:$G$266,MATCH(82,'Tablero (To Do · Doing · Done)'!$S$6:$S$266,0)),"") | E87: =IFERROR(INDEX('Tablero (To Do · Doing · Done)'!$B$6:$B$266,MATCH(82,'Tablero (To Do · Doing · Done)'!$T$6:$T$266,0)),"") | F87: =IFERROR(INDEX('Tablero (To Do · Doing · Done)'!$F$6:$F$266,MATCH(82,'Tablero (To Do · Doing · Done)'!$T$6:$T$266,0))&" · "&INDEX('Tablero (To Do · Doing · Done)'!$G$6:$G$266,MATCH(82,'Tablero (To Do · Doing · Done)'!$T$6:$T$266,0)),"") | H87: =IFERROR(INDEX('Tablero (To Do · Doing · Done)'!$B$6:$B$266,MATCH(82,'Tablero (To Do · Doing · Done)'!$U$6:$U$266,0)),"") | I87: =IFERROR(INDEX('Tablero (To Do · Doing · Done)'!$F$6:$F$266,MATCH(82,'Tablero (To Do · Doing · Done)'!$U$6:$U$266,0))&" · "&INDEX('Tablero (To Do · Doing · Done)'!$G$6:$G$266,MATCH(82,'Tablero (To Do · Doing · Done)'!$U$6:$U$266,0)),"")
B88: =IFERROR(INDEX('Tablero (To Do · Doing · Done)'!$B$6:$B$266,MATCH(83,'Tablero (To Do · Doing · Done)'!$S$6:$S$266,0)),"") | C88: =IFERROR(INDEX('Tablero (To Do · Doing · Done)'!$F$6:$F$266,MATCH(83,'Tablero (To Do · Doing · Done)'!$S$6:$S$266,0))&" · "&INDEX('Tablero (To Do · Doing · Done)'!$G$6:$G$266,MATCH(83,'Tablero (To Do · Doing · Done)'!$S$6:$S$266,0)),"") | E88: =IFERROR(INDEX('Tablero (To Do · Doing · Done)'!$B$6:$B$266,MATCH(83,'Tablero (To Do · Doing · Done)'!$T$6:$T$266,0)),"") | F88: =IFERROR(INDEX('Tablero (To Do · Doing · Done)'!$F$6:$F$266,MATCH(83,'Tablero (To Do · Doing · Done)'!$T$6:$T$266,0))&" · "&INDEX('Tablero (To Do · Doing · Done)'!$G$6:$G$266,MATCH(83,'Tablero (To Do · Doing · Done)'!$T$6:$T$266,0)),"") | H88: =IFERROR(INDEX('Tablero (To Do · Doing · Done)'!$B$6:$B$266,MATCH(83,'Tablero (To Do · Doing · Done)'!$U$6:$U$266,0)),"") | I88: =IFERROR(INDEX('Tablero (To Do · Doing · Done)'!$F$6:$F$266,MATCH(83,'Tablero (To Do · Doing · Done)'!$U$6:$U$266,0))&" · "&INDEX('Tablero (To Do · Doing · Done)'!$G$6:$G$266,MATCH(83,'Tablero (To Do · Doing · Done)'!$U$6:$U$266,0)),"")
B89: =IFERROR(INDEX('Tablero (To Do · Doing · Done)'!$B$6:$B$266,MATCH(84,'Tablero (To Do · Doing · Done)'!$S$6:$S$266,0)),"") | C89: =IFERROR(INDEX('Tablero (To Do · Doing · Done)'!$F$6:$F$266,MATCH(84,'Tablero (To Do · Doing · Done)'!$S$6:$S$266,0))&" · "&INDEX('Tablero (To Do · Doing · Done)'!$G$6:$G$266,MATCH(84,'Tablero (To Do · Doing · Done)'!$S$6:$S$266,0)),"") | E89: =IFERROR(INDEX('Tablero (To Do · Doing · Done)'!$B$6:$B$266,MATCH(84,'Tablero (To Do · Doing · Done)'!$T$6:$T$266,0)),"") | F89: =IFERROR(INDEX('Tablero (To Do · Doing · Done)'!$F$6:$F$266,MATCH(84,'Tablero (To Do · Doing · Done)'!$T$6:$T$266,0))&" · "&INDEX('Tablero (To Do · Doing · Done)'!$G$6:$G$266,MATCH(84,'Tablero (To Do · Doing · Done)'!$T$6:$T$266,0)),"") | H89: =IFERROR(INDEX('Tablero (To Do · Doing · Done)'!$B$6:$B$266,MATCH(84,'Tablero (To Do · Doing · Done)'!$U$6:$U$266,0)),"") | I89: =IFERROR(INDEX('Tablero (To Do · Doing · Done)'!$F$6:$F$266,MATCH(84,'Tablero (To Do · Doing · Done)'!$U$6:$U$266,0))&" · "&INDEX('Tablero (To Do · Doing · Done)'!$G$6:$G$266,MATCH(84,'Tablero (To Do · Doing · Done)'!$U$6:$U$266,0)),"")
B90: =IFERROR(INDEX('Tablero (To Do · Doing · Done)'!$B$6:$B$266,MATCH(85,'Tablero (To Do · Doing · Done)'!$S$6:$S$266,0)),"") | C90: =IFERROR(INDEX('Tablero (To Do · Doing · Done)'!$F$6:$F$266,MATCH(85,'Tablero (To Do · Doing · Done)'!$S$6:$S$266,0))&" · "&INDEX('Tablero (To Do · Doing · Done)'!$G$6:$G$266,MATCH(85,'Tablero (To Do · Doing · Done)'!$S$6:$S$266,0)),"") | E90: =IFERROR(INDEX('Tablero (To Do · Doing · Done)'!$B$6:$B$266,MATCH(85,'Tablero (To Do · Doing · Done)'!$T$6:$T$266,0)),"") | F90: =IFERROR(INDEX('Tablero (To Do · Doing · Done)'!$F$6:$F$266,MATCH(85,'Tablero (To Do · Doing · Done)'!$T$6:$T$266,0))&" · "&INDEX('Tablero (To Do · Doing · Done)'!$G$6:$G$266,MATCH(85,'Tablero (To Do · Doing · Done)'!$T$6:$T$266,0)),"") | H90: =IFERROR(INDEX('Tablero (To Do · Doing · Done)'!$B$6:$B$266,MATCH(85,'Tablero (To Do · Doing · Done)'!$U$6:$U$266,0)),"") | I90: =IFERROR(INDEX('Tablero (To Do · Doing · Done)'!$F$6:$F$266,MATCH(85,'Tablero (To Do · Doing · Done)'!$U$6:$U$266,0))&" · "&INDEX('Tablero (To Do · Doing · Done)'!$G$6:$G$266,MATCH(85,'Tablero (To Do · Doing · Done)'!$U$6:$U$266,0)),"")
B91: =IFERROR(INDEX('Tablero (To Do · Doing · Done)'!$B$6:$B$266,MATCH(86,'Tablero (To Do · Doing · Done)'!$S$6:$S$266,0)),"") | C91: =IFERROR(INDEX('Tablero (To Do · Doing · Done)'!$F$6:$F$266,MATCH(86,'Tablero (To Do · Doing · Done)'!$S$6:$S$266,0))&" · "&INDEX('Tablero (To Do · Doing · Done)'!$G$6:$G$266,MATCH(86,'Tablero (To Do · Doing · Done)'!$S$6:$S$266,0)),"") | E91: =IFERROR(INDEX('Tablero (To Do · Doing · Done)'!$B$6:$B$266,MATCH(86,'Tablero (To Do · Doing · Done)'!$T$6:$T$266,0)),"") | F91: =IFERROR(INDEX('Tablero (To Do · Doing · Done)'!$F$6:$F$266,MATCH(86,'Tablero (To Do · Doing · Done)'!$T$6:$T$266,0))&" · "&INDEX('Tablero (To Do · Doing · Done)'!$G$6:$G$266,MATCH(86,'Tablero (To Do · Doing · Done)'!$T$6:$T$266,0)),"") | H91: =IFERROR(INDEX('Tablero (To Do · Doing · Done)'!$B$6:$B$266,MATCH(86,'Tablero (To Do · Doing · Done)'!$U$6:$U$266,0)),"") | I91: =IFERROR(INDEX('Tablero (To Do · Doing · Done)'!$F$6:$F$266,MATCH(86,'Tablero (To Do · Doing · Done)'!$U$6:$U$266,0))&" · "&INDEX('Tablero (To Do · Doing · Done)'!$G$6:$G$266,MATCH(86,'Tablero (To Do · Doing · Done)'!$U$6:$U$266,0)),"")
B92: =IFERROR(INDEX('Tablero (To Do · Doing · Done)'!$B$6:$B$266,MATCH(87,'Tablero (To Do · Doing · Done)'!$S$6:$S$266,0)),"") | C92: =IFERROR(INDEX('Tablero (To Do · Doing · Done)'!$F$6:$F$266,MATCH(87,'Tablero (To Do · Doing · Done)'!$S$6:$S$266,0))&" · "&INDEX('Tablero (To Do · Doing · Done)'!$G$6:$G$266,MATCH(87,'Tablero (To Do · Doing · Done)'!$S$6:$S$266,0)),"") | E92: =IFERROR(INDEX('Tablero (To Do · Doing · Done)'!$B$6:$B$266,MATCH(87,'Tablero (To Do · Doing · Done)'!$T$6:$T$266,0)),"") | F92: =IFERROR(INDEX('Tablero (To Do · Doing · Done)'!$F$6:$F$266,MATCH(87,'Tablero (To Do · Doing · Done)'!$T$6:$T$266,0))&" · "&INDEX('Tablero (To Do · Doing · Done)'!$G$6:$G$266,MATCH(87,'Tablero (To Do · Doing · Done)'!$T$6:$T$266,0)),"") | H92: =IFERROR(INDEX('Tablero (To Do · Doing · Done)'!$B$6:$B$266,MATCH(87,'Tablero (To Do · Doing · Done)'!$U$6:$U$266,0)),"") | I92: =IFERROR(INDEX('Tablero (To Do · Doing · Done)'!$F$6:$F$266,MATCH(87,'Tablero (To Do · Doing · Done)'!$U$6:$U$266,0))&" · "&INDEX('Tablero (To Do · Doing · Done)'!$G$6:$G$266,MATCH(87,'Tablero (To Do · Doing · Done)'!$U$6:$U$266,0)),"")
B93: =IFERROR(INDEX('Tablero (To Do · Doing · Done)'!$B$6:$B$266,MATCH(88,'Tablero (To Do · Doing · Done)'!$S$6:$S$266,0)),"") | C93: =IFERROR(INDEX('Tablero (To Do · Doing · Done)'!$F$6:$F$266,MATCH(88,'Tablero (To Do · Doing · Done)'!$S$6:$S$266,0))&" · "&INDEX('Tablero (To Do · Doing · Done)'!$G$6:$G$266,MATCH(88,'Tablero (To Do · Doing · Done)'!$S$6:$S$266,0)),"") | E93: =IFERROR(INDEX('Tablero (To Do · Doing · Done)'!$B$6:$B$266,MATCH(88,'Tablero (To Do · Doing · Done)'!$T$6:$T$266,0)),"") | F93: =IFERROR(INDEX('Tablero (To Do · Doing · Done)'!$F$6:$F$266,MATCH(88,'Tablero (To Do · Doing · Done)'!$T$6:$T$266,0))&" · "&INDEX('Tablero (To Do · Doing · Done)'!$G$6:$G$266,MATCH(88,'Tablero (To Do · Doing · Done)'!$T$6:$T$266,0)),"") | H93: =IFERROR(INDEX('Tablero (To Do · Doing · Done)'!$B$6:$B$266,MATCH(88,'Tablero (To Do · Doing · Done)'!$U$6:$U$266,0)),"") | I93: =IFERROR(INDEX('Tablero (To Do · Doing · Done)'!$F$6:$F$266,MATCH(88,'Tablero (To Do · Doing · Done)'!$U$6:$U$266,0))&" · "&INDEX('Tablero (To Do · Doing · Done)'!$G$6:$G$266,MATCH(88,'Tablero (To Do · Doing · Done)'!$U$6:$U$266,0)),"")
B94: =IFERROR(INDEX('Tablero (To Do · Doing · Done)'!$B$6:$B$266,MATCH(89,'Tablero (To Do · Doing · Done)'!$S$6:$S$266,0)),"") | C94: =IFERROR(INDEX('Tablero (To Do · Doing · Done)'!$F$6:$F$266,MATCH(89,'Tablero (To Do · Doing · Done)'!$S$6:$S$266,0))&" · "&INDEX('Tablero (To Do · Doing · Done)'!$G$6:$G$266,MATCH(89,'Tablero (To Do · Doing · Done)'!$S$6:$S$266,0)),"") | E94: =IFERROR(INDEX('Tablero (To Do · Doing · Done)'!$B$6:$B$266,MATCH(89,'Tablero (To Do · Doing · Done)'!$T$6:$T$266,0)),"") | F94: =IFERROR(INDEX('Tablero (To Do · Doing · Done)'!$F$6:$F$266,MATCH(89,'Tablero (To Do · Doing · Done)'!$T$6:$T$266,0))&" · "&INDEX('Tablero (To Do · Doing · Done)'!$G$6:$G$266,MATCH(89,'Tablero (To Do · Doing · Done)'!$T$6:$T$266,0)),"") | H94: =IFERROR(INDEX('Tablero (To Do · Doing · Done)'!$B$6:$B$266,MATCH(89,'Tablero (To Do · Doing · Done)'!$U$6:$U$266,0)),"") | I94: =IFERROR(INDEX('Tablero (To Do · Doing · Done)'!$F$6:$F$266,MATCH(89,'Tablero (To Do · Doing · Done)'!$U$6:$U$266,0))&" · "&INDEX('Tablero (To Do · Doing · Done)'!$G$6:$G$266,MATCH(89,'Tablero (To Do · Doing · Done)'!$U$6:$U$266,0)),"")
B95: =IFERROR(INDEX('Tablero (To Do · Doing · Done)'!$B$6:$B$266,MATCH(90,'Tablero (To Do · Doing · Done)'!$S$6:$S$266,0)),"") | C95: =IFERROR(INDEX('Tablero (To Do · Doing · Done)'!$F$6:$F$266,MATCH(90,'Tablero (To Do · Doing · Done)'!$S$6:$S$266,0))&" · "&INDEX('Tablero (To Do · Doing · Done)'!$G$6:$G$266,MATCH(90,'Tablero (To Do · Doing · Done)'!$S$6:$S$266,0)),"") | E95: =IFERROR(INDEX('Tablero (To Do · Doing · Done)'!$B$6:$B$266,MATCH(90,'Tablero (To Do · Doing · Done)'!$T$6:$T$266,0)),"") | F95: =IFERROR(INDEX('Tablero (To Do · Doing · Done)'!$F$6:$F$266,MATCH(90,'Tablero (To Do · Doing · Done)'!$T$6:$T$266,0))&" · "&INDEX('Tablero (To Do · Doing · Done)'!$G$6:$G$266,MATCH(90,'Tablero (To Do · Doing · Done)'!$T$6:$T$266,0)),"") | H95: =IFERROR(INDEX('Tablero (To Do · Doing · Done)'!$B$6:$B$266,MATCH(90,'Tablero (To Do · Doing · Done)'!$U$6:$U$266,0)),"") | I95: =IFERROR(INDEX('Tablero (To Do · Doing · Done)'!$F$6:$F$266,MATCH(90,'Tablero (To Do · Doing · Done)'!$U$6:$U$266,0))&" · "&INDEX('Tablero (To Do · Doing · Done)'!$G$6:$G$266,MATCH(90,'Tablero (To Do · Doing · Done)'!$U$6:$U$266,0)),"")
B96: =IFERROR(INDEX('Tablero (To Do · Doing · Done)'!$B$6:$B$266,MATCH(91,'Tablero (To Do · Doing · Done)'!$S$6:$S$266,0)),"") | C96: =IFERROR(INDEX('Tablero (To Do · Doing · Done)'!$F$6:$F$266,MATCH(91,'Tablero (To Do · Doing · Done)'!$S$6:$S$266,0))&" · "&INDEX('Tablero (To Do · Doing · Done)'!$G$6:$G$266,MATCH(91,'Tablero (To Do · Doing · Done)'!$S$6:$S$266,0)),"") | E96: =IFERROR(INDEX('Tablero (To Do · Doing · Done)'!$B$6:$B$266,MATCH(91,'Tablero (To Do · Doing · Done)'!$T$6:$T$266,0)),"") | F96: =IFERROR(INDEX('Tablero (To Do · Doing · Done)'!$F$6:$F$266,MATCH(91,'Tablero (To Do · Doing · Done)'!$T$6:$T$266,0))&" · "&INDEX('Tablero (To Do · Doing · Done)'!$G$6:$G$266,MATCH(91,'Tablero (To Do · Doing · Done)'!$T$6:$T$266,0)),"") | H96: =IFERROR(INDEX('Tablero (To Do · Doing · Done)'!$B$6:$B$266,MATCH(91,'Tablero (To Do · Doing · Done)'!$U$6:$U$266,0)),"") | I96: =IFERROR(INDEX('Tablero (To Do · Doing · Done)'!$F$6:$F$266,MATCH(91,'Tablero (To Do · Doing · Done)'!$U$6:$U$266,0))&" · "&INDEX('Tablero (To Do · Doing · Done)'!$G$6:$G$266,MATCH(91,'Tablero (To Do · Doing · Done)'!$U$6:$U$266,0)),"")
B97: =IFERROR(INDEX('Tablero (To Do · Doing · Done)'!$B$6:$B$266,MATCH(92,'Tablero (To Do · Doing · Done)'!$S$6:$S$266,0)),"") | C97: =IFERROR(INDEX('Tablero (To Do · Doing · Done)'!$F$6:$F$266,MATCH(92,'Tablero (To Do · Doing · Done)'!$S$6:$S$266,0))&" · "&INDEX('Tablero (To Do · Doing · Done)'!$G$6:$G$266,MATCH(92,'Tablero (To Do · Doing · Done)'!$S$6:$S$266,0)),"") | E97: =IFERROR(INDEX('Tablero (To Do · Doing · Done)'!$B$6:$B$266,MATCH(92,'Tablero (To Do · Doing · Done)'!$T$6:$T$266,0)),"") | F97: =IFERROR(INDEX('Tablero (To Do · Doing · Done)'!$F$6:$F$266,MATCH(92,'Tablero (To Do · Doing · Done)'!$T$6:$T$266,0))&" · "&INDEX('Tablero (To Do · Doing · Done)'!$G$6:$G$266,MATCH(92,'Tablero (To Do · Doing · Done)'!$T$6:$T$266,0)),"") | H97: =IFERROR(INDEX('Tablero (To Do · Doing · Done)'!$B$6:$B$266,MATCH(92,'Tablero (To Do · Doing · Done)'!$U$6:$U$266,0)),"") | I97: =IFERROR(INDEX('Tablero (To Do · Doing · Done)'!$F$6:$F$266,MATCH(92,'Tablero (To Do · Doing · Done)'!$U$6:$U$266,0))&" · "&INDEX('Tablero (To Do · Doing · Done)'!$G$6:$G$266,MATCH(92,'Tablero (To Do · Doing · Done)'!$U$6:$U$266,0)),"")
B98: =IFERROR(INDEX('Tablero (To Do · Doing · Done)'!$B$6:$B$266,MATCH(93,'Tablero (To Do · Doing · Done)'!$S$6:$S$266,0)),"") | C98: =IFERROR(INDEX('Tablero (To Do · Doing · Done)'!$F$6:$F$266,MATCH(93,'Tablero (To Do · Doing · Done)'!$S$6:$S$266,0))&" · "&INDEX('Tablero (To Do · Doing · Done)'!$G$6:$G$266,MATCH(93,'Tablero (To Do · Doing · Done)'!$S$6:$S$266,0)),"") | E98: =IFERROR(INDEX('Tablero (To Do · Doing · Done)'!$B$6:$B$266,MATCH(93,'Tablero (To Do · Doing · Done)'!$T$6:$T$266,0)),"") | F98: =IFERROR(INDEX('Tablero (To Do · Doing · Done)'!$F$6:$F$266,MATCH(93,'Tablero (To Do · Doing · Done)'!$T$6:$T$266,0))&" · "&INDEX('Tablero (To Do · Doing · Done)'!$G$6:$G$266,MATCH(93,'Tablero (To Do · Doing · Done)'!$T$6:$T$266,0)),"") | H98: =IFERROR(INDEX('Tablero (To Do · Doing · Done)'!$B$6:$B$266,MATCH(93,'Tablero (To Do · Doing · Done)'!$U$6:$U$266,0)),"") | I98: =IFERROR(INDEX('Tablero (To Do · Doing · Done)'!$F$6:$F$266,MATCH(93,'Tablero (To Do · Doing · Done)'!$U$6:$U$266,0))&" · "&INDEX('Tablero (To Do · Doing · Done)'!$G$6:$G$266,MATCH(93,'Tablero (To Do · Doing · Done)'!$U$6:$U$266,0)),"")
B99: =IFERROR(INDEX('Tablero (To Do · Doing · Done)'!$B$6:$B$266,MATCH(94,'Tablero (To Do · Doing · Done)'!$S$6:$S$266,0)),"") | C99: =IFERROR(INDEX('Tablero (To Do · Doing · Done)'!$F$6:$F$266,MATCH(94,'Tablero (To Do · Doing · Done)'!$S$6:$S$266,0))&" · "&INDEX('Tablero (To Do · Doing · Done)'!$G$6:$G$266,MATCH(94,'Tablero (To Do · Doing · Done)'!$S$6:$S$266,0)),"") | E99: =IFERROR(INDEX('Tablero (To Do · Doing · Done)'!$B$6:$B$266,MATCH(94,'Tablero (To Do · Doing · Done)'!$T$6:$T$266,0)),"") | F99: =IFERROR(INDEX('Tablero (To Do · Doing · Done)'!$F$6:$F$266,MATCH(94,'Tablero (To Do · Doing · Done)'!$T$6:$T$266,0))&" · "&INDEX('Tablero (To Do · Doing · Done)'!$G$6:$G$266,MATCH(94,'Tablero (To Do · Doing · Done)'!$T$6:$T$266,0)),"") | H99: =IFERROR(INDEX('Tablero (To Do · Doing · Done)'!$B$6:$B$266,MATCH(94,'Tablero (To Do · Doing · Done)'!$U$6:$U$266,0)),"") | I99: =IFERROR(INDEX('Tablero (To Do · Doing · Done)'!$F$6:$F$266,MATCH(94,'Tablero (To Do · Doing · Done)'!$U$6:$U$266,0))&" · "&INDEX('Tablero (To Do · Doing · Done)'!$G$6:$G$266,MATCH(94,'Tablero (To Do · Doing · Done)'!$U$6:$U$266,0)),"")
B100: =IFERROR(INDEX('Tablero (To Do · Doing · Done)'!$B$6:$B$266,MATCH(95,'Tablero (To Do · Doing · Done)'!$S$6:$S$266,0)),"") | C100: =IFERROR(INDEX('Tablero (To Do · Doing · Done)'!$F$6:$F$266,MATCH(95,'Tablero (To Do · Doing · Done)'!$S$6:$S$266,0))&" · "&INDEX('Tablero (To Do · Doing · Done)'!$G$6:$G$266,MATCH(95,'Tablero (To Do · Doing · Done)'!$S$6:$S$266,0)),"") | E100: =IFERROR(INDEX('Tablero (To Do · Doing · Done)'!$B$6:$B$266,MATCH(95,'Tablero (To Do · Doing · Done)'!$T$6:$T$266,0)),"") | F100: =IFERROR(INDEX('Tablero (To Do · Doing · Done)'!$F$6:$F$266,MATCH(95,'Tablero (To Do · Doing · Done)'!$T$6:$T$266,0))&" · "&INDEX('Tablero (To Do · Doing · Done)'!$G$6:$G$266,MATCH(95,'Tablero (To Do · Doing · Done)'!$T$6:$T$266,0)),"") | H100: =IFERROR(INDEX('Tablero (To Do · Doing · Done)'!$B$6:$B$266,MATCH(95,'Tablero (To Do · Doing · Done)'!$U$6:$U$266,0)),"") | I100: =IFERROR(INDEX('Tablero (To Do · Doing · Done)'!$F$6:$F$266,MATCH(95,'Tablero (To Do · Doing · Done)'!$U$6:$U$266,0))&" · "&INDEX('Tablero (To Do · Doing · Done)'!$G$6:$G$266,MATCH(95,'Tablero (To Do · Doing · Done)'!$U$6:$U$266,0)),"")
B101: =IFERROR(INDEX('Tablero (To Do · Doing · Done)'!$B$6:$B$266,MATCH(96,'Tablero (To Do · Doing · Done)'!$S$6:$S$266,0)),"") | C101: =IFERROR(INDEX('Tablero (To Do · Doing · Done)'!$F$6:$F$266,MATCH(96,'Tablero (To Do · Doing · Done)'!$S$6:$S$266,0))&" · "&INDEX('Tablero (To Do · Doing · Done)'!$G$6:$G$266,MATCH(96,'Tablero (To Do · Doing · Done)'!$S$6:$S$266,0)),"") | E101: =IFERROR(INDEX('Tablero (To Do · Doing · Done)'!$B$6:$B$266,MATCH(96,'Tablero (To Do · Doing · Done)'!$T$6:$T$266,0)),"") | F101: =IFERROR(INDEX('Tablero (To Do · Doing · Done)'!$F$6:$F$266,MATCH(96,'Tablero (To Do · Doing · Done)'!$T$6:$T$266,0))&" · "&INDEX('Tablero (To Do · Doing · Done)'!$G$6:$G$266,MATCH(96,'Tablero (To Do · Doing · Done)'!$T$6:$T$266,0)),"") | H101: =IFERROR(INDEX('Tablero (To Do · Doing · Done)'!$B$6:$B$266,MATCH(96,'Tablero (To Do · Doing · Done)'!$U$6:$U$266,0)),"") | I101: =IFERROR(INDEX('Tablero (To Do · Doing · Done)'!$F$6:$F$266,MATCH(96,'Tablero (To Do · Doing · Done)'!$U$6:$U$266,0))&" · "&INDEX('Tablero (To Do · Doing · Done)'!$G$6:$G$266,MATCH(96,'Tablero (To Do · Doing · Done)'!$U$6:$U$266,0)),"")
B102: =IFERROR(INDEX('Tablero (To Do · Doing · Done)'!$B$6:$B$266,MATCH(97,'Tablero (To Do · Doing · Done)'!$S$6:$S$266,0)),"") | C102: =IFERROR(INDEX('Tablero (To Do · Doing · Done)'!$F$6:$F$266,MATCH(97,'Tablero (To Do · Doing · Done)'!$S$6:$S$266,0))&" · "&INDEX('Tablero (To Do · Doing · Done)'!$G$6:$G$266,MATCH(97,'Tablero (To Do · Doing · Done)'!$S$6:$S$266,0)),"") | E102: =IFERROR(INDEX('Tablero (To Do · Doing · Done)'!$B$6:$B$266,MATCH(97,'Tablero (To Do · Doing · Done)'!$T$6:$T$266,0)),"") | F102: =IFERROR(INDEX('Tablero (To Do · Doing · Done)'!$F$6:$F$266,MATCH(97,'Tablero (To Do · Doing · Done)'!$T$6:$T$266,0))&" · "&INDEX('Tablero (To Do · Doing · Done)'!$G$6:$G$266,MATCH(97,'Tablero (To Do · Doing · Done)'!$T$6:$T$266,0)),"") | H102: =IFERROR(INDEX('Tablero (To Do · Doing · Done)'!$B$6:$B$266,MATCH(97,'Tablero (To Do · Doing · Done)'!$U$6:$U$266,0)),"") | I102: =IFERROR(INDEX('Tablero (To Do · Doing · Done)'!$F$6:$F$266,MATCH(97,'Tablero (To Do · Doing · Done)'!$U$6:$U$266,0))&" · "&INDEX('Tablero (To Do · Doing · Done)'!$G$6:$G$266,MATCH(97,'Tablero (To Do · Doing · Done)'!$U$6:$U$266,0)),"")
...

Sheet Resumen
B2: Resumen del sprint (se actualiza solo)
B4: Responsable | C4: To Do | D4: Doing | E4: Done | F4: Horas pendientes | G4: Alertas de control
B5: Fernando | C5: =COUNTIFS('Tablero (To Do · Doing · Done)'!$G$6:$G$266,B5,'Tablero (To Do · Doing · Done)'!$K$6:$K$266,"To Do") | D5: =COUNTIFS('Tablero (To Do · Doing · Done)'!$G$6:$G$266,B5,'Tablero (To Do · Doing · Done)'!$K$6:$K$266,"Doing") | E5: =COUNTIFS('Tablero (To Do · Doing · Done)'!$G$6:$G$266,B5,'Tablero (To Do · Doing · Done)'!$K$6:$K$266,"Done") | F5: =SUMIFS('Tablero (To Do · Doing · Done)'!$H$6:$H$266,'Tablero (To Do · Doing · Done)'!$G$6:$G$266,B5,'Tablero (To Do · Doing · Done)'!$K$6:$K$266,"<>Done") | G5: =COUNTIFS('Tablero (To Do · Doing · Done)'!$G$6:$G$266,B5,'Tablero (To Do · Doing · Done)'!$R$6:$R$266,"⚠*")
B6: Henry | C6: =COUNTIFS('Tablero (To Do · Doing · Done)'!$G$6:$G$266,B6,'Tablero (To Do · Doing · Done)'!$K$6:$K$266,"To Do") | D6: =COUNTIFS('Tablero (To Do · Doing · Done)'!$G$6:$G$266,B6,'Tablero (To Do · Doing · Done)'!$K$6:$K$266,"Doing") | E6: =COUNTIFS('Tablero (To Do · Doing · Done)'!$G$6:$G$266,B6,'Tablero (To Do · Doing · Done)'!$K$6:$K$266,"Done") | F6: =SUMIFS('Tablero (To Do · Doing · Done)'!$H$6:$H$266,'Tablero (To Do · Doing · Done)'!$G$6:$G$266,B6,'Tablero (To Do · Doing · Done)'!$K$6:$K$266,"<>Done") | G6: =COUNTIFS('Tablero (To Do · Doing · Done)'!$G$6:$G$266,B6,'Tablero (To Do · Doing · Done)'!$R$6:$R$266,"⚠*")
B7: Nicolás | C7: =COUNTIFS('Tablero (To Do · Doing · Done)'!$G$6:$G$266,B7,'Tablero (To Do · Doing · Done)'!$K$6:$K$266,"To Do") | D7: =COUNTIFS('Tablero (To Do · Doing · Done)'!$G$6:$G$266,B7,'Tablero (To Do · Doing · Done)'!$K$6:$K$266,"Doing") | E7: =COUNTIFS('Tablero (To Do · Doing · Done)'!$G$6:$G$266,B7,'Tablero (To Do · Doing · Done)'!$K$6:$K$266,"Done") | F7: =SUMIFS('Tablero (To Do · Doing · Done)'!$H$6:$H$266,'Tablero (To Do · Doing · Done)'!$G$6:$G$266,B7,'Tablero (To Do · Doing · Done)'!$K$6:$K$266,"<>Done") | G7: =COUNTIFS('Tablero (To Do · Doing · Done)'!$G$6:$G$266,B7,'Tablero (To Do · Doing · Done)'!$R$6:$R$266,"⚠*")
B8: Adiel | C8: =COUNTIFS('Tablero (To Do · Doing · Done)'!$G$6:$G$266,B8,'Tablero (To Do · Doing · Done)'!$K$6:$K$266,"To Do") | D8: =COUNTIFS('Tablero (To Do · Doing · Done)'!$G$6:$G$266,B8,'Tablero (To Do · Doing · Done)'!$K$6:$K$266,"Doing") | E8: =COUNTIFS('Tablero (To Do · Doing · Done)'!$G$6:$G$266,B8,'Tablero (To Do · Doing · Done)'!$K$6:$K$266,"Done") | F8: =SUMIFS('Tablero (To Do · Doing · Done)'!$H$6:$H$266,'Tablero (To Do · Doing · Done)'!$G$6:$G$266,B8,'Tablero (To Do · Doing · Done)'!$K$6:$K$266,"<>Done") | G8: =COUNTIFS('Tablero (To Do · Doing · Done)'!$G$6:$G$266,B8,'Tablero (To Do · Doing · Done)'!$R$6:$R$266,"⚠*")
B9: Total | C9: =SUM(C5:C8) | D9: =SUM(D5:D8) | E9: =SUM(E5:E8) | F9: =SUM(F5:F8) | G9: =SUM(G5:G8)
B12: Historia | C12: Nombre | D12: Puntos | E12: Tareas | F12: Done | G12: % avance | H12: Estado de la historia
B13: HU-01 | C13: Crear proyecto | D13: 3 | E13: =COUNTIF('Tablero (To Do · Doing · Done)'!$C$6:$C$266,B13) | F13: =COUNTIFS('Tablero (To Do · Doing · Done)'!$C$6:$C$266,B13,'Tablero (To Do · Doing · Done)'!$K$6:$K$266,"Done") | G13: =IF(E13=0,0,F13/E13) | H13: =IF(COUNTIFS('Tablero (To Do · Doing · Done)'!$C$6:$C$266,B13,'Tablero (To Do · Doing · Done)'!$E$6:$E$266,"Aceptación",'Tablero (To Do · Doing · Done)'!$K$6:$K$266,"Done")=1,"Done",IF(F13>0,"Doing","To Do"))
B14: HU-03 | C14: Reportar la obra en semanas | D14: 3 | E14: =COUNTIF('Tablero (To Do · Doing · Done)'!$C$6:$C$266,B14) | F14: =COUNTIFS('Tablero (To Do · Doing · Done)'!$C$6:$C$266,B14,'Tablero (To Do · Doing · Done)'!$K$6:$K$266,"Done") | G14: =IF(E14=0,0,F14/E14) | H14: =IF(COUNTIFS('Tablero (To Do · Doing · Done)'!$C$6:$C$266,B14,'Tablero (To Do · Doing · Done)'!$E$6:$E$266,"Aceptación",'Tablero (To Do · Doing · Done)'!$K$6:$K$266,"Done")=1,"Done",IF(F14>0,"Doing","To Do"))
B15: HU-07 | C15: Importar catálogo de insumos del S10 | D15: 8 | E15: =COUNTIF('Tablero (To Do · Doing · Done)'!$C$6:$C$266,B15) | F15: =COUNTIFS('Tablero (To Do · Doing · Done)'!$C$6:$C$266,B15,'Tablero (To Do · Doing · Done)'!$K$6:$K$266,"Done") | G15: =IF(E15=0,0,F15/E15) | H15: =IF(COUNTIFS('Tablero (To Do · Doing · Done)'!$C$6:$C$266,B15,'Tablero (To Do · Doing · Done)'!$E$6:$E$266,"Aceptación",'Tablero (To Do · Doing · Done)'!$K$6:$K$266,"Done")=1,"Done",IF(F15>0,"Doing","To Do"))
B16: HU-08 | C16: Registrar insumos | D16: 5 | E16: =COUNTIF('Tablero (To Do · Doing · Done)'!$C$6:$C$266,B16) | F16: =COUNTIFS('Tablero (To Do · Doing · Done)'!$C$6:$C$266,B16,'Tablero (To Do · Doing · Done)'!$K$6:$K$266,"Done") | G16: =IF(E16=0,0,F16/E16) | H16: =IF(COUNTIFS('Tablero (To Do · Doing · Done)'!$C$6:$C$266,B16,'Tablero (To Do · Doing · Done)'!$E$6:$E$266,"Aceptación",'Tablero (To Do · Doing · Done)'!$K$6:$K$266,"Done")=1,"Done",IF(F16>0,"Doing","To Do"))
B17: HU-12 | C17: Loguear usuario | D17: 5 | E17: =COUNTIF('Tablero (To Do · Doing · Done)'!$C$6:$C$266,B17) | F17: =COUNTIFS('Tablero (To Do · Doing · Done)'!$C$6:$C$266,B17,'Tablero (To Do · Doing · Done)'!$K$6:$K$266,"Done") | G17: =IF(E17=0,0,F17/E17) | H17: =IF(COUNTIFS('Tablero (To Do · Doing · Done)'!$C$6:$C$266,B17,'Tablero (To Do · Doing · Done)'!$E$6:$E$266,"Aceptación",'Tablero (To Do · Doing · Done)'!$K$6:$K$266,"Done")=1,"Done",IF(F17>0,"Doing","To Do"))
B18: HU-13 | C18: Asignar roles | D18: 5 | E18: =COUNTIF('Tablero (To Do · Doing · Done)'!$C$6:$C$266,B18) | F18: =COUNTIFS('Tablero (To Do · Doing · Done)'!$C$6:$C$266,B18,'Tablero (To Do · Doing · Done)'!$K$6:$K$266,"Done") | G18: =IF(E18=0,0,F18/E18) | H18: =IF(COUNTIFS('Tablero (To Do · Doing · Done)'!$C$6:$C$266,B18,'Tablero (To Do · Doing · Done)'!$E$6:$E$266,"Aceptación",'Tablero (To Do · Doing · Done)'!$K$6:$K$266,"Done")=1,"Done",IF(F18>0,"Doing","To Do"))
B19: HU-14 | C19: Asignar usuarios a obras | D19: 3 | E19: =COUNTIF('Tablero (To Do · Doing · Done)'!$C$6:$C$266,B19) | F19: =COUNTIFS('Tablero (To Do · Doing · Done)'!$C$6:$C$266,B19,'Tablero (To Do · Doing · Done)'!$K$6:$K$266,"Done") | G19: =IF(E19=0,0,F19/E19) | H19: =IF(COUNTIFS('Tablero (To Do · Doing · Done)'!$C$6:$C$266,B19,'Tablero (To Do · Doing · Done)'!$E$6:$E$266,"Aceptación",'Tablero (To Do · Doing · Done)'!$K$6:$K$266,"Done")=1,"Done",IF(F19>0,"Doing","To Do"))
B20: HU-15 | C20: Autorizar celular de la obra | D20: 5 | E20: =COUNTIF('Tablero (To Do · Doing · Done)'!$C$6:$C$266,B20) | F20: =COUNTIFS('Tablero (To Do · Doing · Done)'!$C$6:$C$266,B20,'Tablero (To Do · Doing · Done)'!$K$6:$K$266,"Done") | G20: =IF(E20=0,0,F20/E20) | H20: =IF(COUNTIFS('Tablero (To Do · Doing · Done)'!$C$6:$C$266,B20,'Tablero (To Do · Doing · Done)'!$E$6:$E$266,"Aceptación",'Tablero (To Do · Doing · Done)'!$K$6:$K$266,"Done")=1,"Done",IF(F20>0,"Doing","To Do"))
B21: HU-16 | C21: Importar precios unitarios | D21: 8 | E21: =COUNTIF('Tablero (To Do · Doing · Done)'!$C$6:$C$266,B21) | F21: =COUNTIFS('Tablero (To Do · Doing · Done)'!$C$6:$C$266,B21,'Tablero (To Do · Doing · Done)'!$K$6:$K$266,"Done") | G21: =IF(E21=0,0,F21/E21) | H21: =IF(COUNTIFS('Tablero (To Do · Doing · Done)'!$C$6:$C$266,B21,'Tablero (To Do · Doing · Done)'!$E$6:$E$266,"Aceptación",'Tablero (To Do · Doing · Done)'!$K$6:$K$266,"Done")=1,"Done",IF(F21>0,"Doing","To Do"))
